Workbook

Sheet Claude Log
A1: Turn # | B1: Date | C1: User Request | D1: Action Taken | E1: Details | F1: Outcome
A2: 1 | B2: 46112 | C2: User asked if any tabs reference data from the RR_Unit_Details tab. | D2: Searched all 40 sheets for formula references to RR_Unit_Details (and partial variants). | E2: Used matchFormulas search for 'RR_Unit_Details', 'RR_Unit', and 'Unit_Details' across all sheets. Zero matches found in all searches. | F2: RR_Unit_Details is a standalone data tab with no inbound formula references from other sheets.
A3: 2 | B3: 46112 | C3: User asked if any tabs reference data from the Res_Retention tab. | D3: Searched all sheets for formula references to Res_Retention. | E3: Found 1 match: Data_2!R57 contains =SUMPRODUCT((Res_Retention!$O$2:$O$14)) with result 79. | F3: Only Data_2 pulls from Res_Retention via a single SUMPRODUCT formula.
A4: 3 | B4: 46112 | C4: User uploaded CSV (Untitled-2026-03-31.csv, 113 rows of LeaseLock claims data) and asked to import it into the LeaseLock tab. | D4: Parsed CSV, mapped 26 CSV columns to 22 LeaseLock columns (A-V), wrote all 113 rows with values and formulas. | E4: Column mapping: A=Item#, B=pmc_name, C=tenant, D=unit, E=property, F=status, G=substatus, H=certificate_id (text), I/J=blank, K=carrier, L=total_claimed, M=total_paid, N=formula(L-M), O=formula(M/L as %), P=unused_coverage+paid, Q=denial_reason, R=dismissed, S=blank, T=days(reported-moveout), U=loss_date, V=TEXT(U,YYYY-MM). Formatted L/M/N/P as $#,##0.00, O as 0.0%, U as mm/dd/yyyy, H as text. | F4: 113 rows populated in LeaseLock!A2:V114. All formulas verified working. Certificate IDs fixed from scientific notation to text.
A5: 4 | B5: 46112 | C5: User corrected that column A should contain claim_number from CSV, not a row counter. Asked about filling other missing columns. | D5: Replaced A2:A114 with claim_number values from CSV (e.g. 25-103410). Identified which columns still lack data. | E5: Formatted A as text to preserve dash format. Columns I(LossType), J(LossCause), S(Adjuster) have no CSV equivalent. Remaining unmapped CSV fields: claim_reported_date, reported_reoccupied_date, claim_dispute_date, total_claimed_amount_within_limit_usd, is_claim_action_required, claim_is_missing_documentation, claim_missing_documentation_list, owner_name, pms_property_id, pms_tenant_id. | F5: Column A now shows claim numbers. Awaiting user direction on where to place remaining unmapped CSV fields.
A6: 5 | B6: 46131 | C6: Excel peer (rollforward model) requested Jan-26, Feb-26, Mar-26 total move-outs with component breakdown (lease expiration / NTV / early / evictions) and source citation. | D6: Queried Move_Out_Reasons sheet, parsed 96 rows, categorized by Reason + Early Termination flag, aggregated by month. | E6: Source: Move_Out_Reasons!A1:M97 (row-level move-out log). Dates stored as Excel serials. Bucketing: Eviction = Skipped During Eviction + Skipped Without Notice + Failure To Pay; Lease Expiration = Non-Renewal (by Property); Early Move-Out = Early Termination flag Yes (non-eviction); NTV = resident-initiated non-renewal, Early Termination No. Jan-26: 5 (3 evict, 1 lease exp, 0 early, 1 NTV). Feb-26: 33 (11 evict, 1 lease exp, 6 early, 15 NTV). Mar-26: 28 (14 evict, 1 lease exp, 0 early, 13 NTV). | F6: Totals and breakdown shared with rollforward Excel peer via JSON file (move_outs_breakdown.json) and message. Note: no separate 'monthly totals' summary table exists in the workbook — figures derived by aggregating the row-level log.
A7: 6 | B7: 46131 | C7: Rollforward peer asked for stricter eviction definition: formal eviction filings that resulted in a move-out in Jan/Feb/Mar 2026, plus residual skip/SWN/FTP count per month. | D7: Pulled Evictions_RSI!A1:I62 (60 filings, all Feb 2026 issue dates), matched to eviction-bucket move-outs in Move_Out_Reasons by last-name + unit number. | E7: Methodology: formal eviction move-out = (a) Reason = 'Skipped During Eviction' OR (b) matching RSI filing with status in {Granted, LC Handling Appeal, Dismissed (Tenant Vacated)}. Cancelled filings treated as NOT formal (filing dropped). Strict-formal counts: Jan-26=0, Feb-26=4, Mar-26=0. Residual skip/SWN/FTP: Jan-26=3, Feb-26=7, Mar-26=14. Broad view (any filing match incl. Cancelled): Feb-26=7, Mar-26=5. | F7: Results shared via eviction_split.json to rollforward peer. Key caveat: RSI sheet only contains Feb 2026 filings — Jan-26 zero formal likely reflects data scope, not reality; Mar-26 zero strict-formal because tenants skipped before court dates arrived.
A8: 7 | B8: 46131 | C8: Rollforward peer asked for comprehensive cross-reference of eviction/skip data across ALL source sheets — enumerate sources, flag conflicts, recommend authoritative methodology. | D8: Enumerated 42 sheets, pulled raw data from Evictions_RSI (60 filings Feb-only), Eviction_Success_Rate (47 tenants w/balance since 12/15/25), resident aged receivable (136 rows sampled), Write_Off_Recon (42 accounts 60+ days), Data_2 (weekly metrics), Delinquency_Detail_3 (current delinquent residents). Built unit-level cross-reference joining Move_Out_Reasons to ResMan Lease Status. | E8: MAJOR FINDING: ResMan's structured Lease Status field is authoritative; 3-way comparison on 28 Jan-Mar eviction-bucket move-outs: Move_Out_Reasons=27 skip/1 eviction, RSI strict=4 formal, ResMan=26 Past-Skip/1 Past-Eviction (Candler)/1 not in sample. 5 explicit conflicts flagged, biggest: 3 'Dismissed (Tenant Vacated)' RSI filings are Past-Skip per ResMan — invalidates prior eviction_split.json's Feb=4 formal. Correct count is Feb=1 formal/10 skip. | F8: Wrote eviction_crossref.json to shared files; sent to rollforward peer with recommendation to rebuild on ResMan basis. Data gaps flagged: RSI missing Jan/Mar filings, my RAR sample missed ~12 units (voluntary move-outs not needed for eviction classification anyway).
A9: 8 | B9: 46131 | C9: Rollforward peer asked for AVA workbook style guide (colors, fonts, number formats, section headers, borders, layout) to apply matching branding to another workbook. | D9: Inspected Dashboard_1 (canonical styled sheet), Data_2 (wide time-series), Res_Retention (unstyled). Pulled real cell styles, borders, column widths, row heights, freeze panes. Wrote comprehensive style guide to ava_style_guide.json and shared with peer. | E9: Primary palette: navy #1F3864 (title/headers), light blue #E8EEF4 (sub-section fills), divider #2E5090, good #C6EFCE/#006100, bad #FFC7CE/#9C0006, input #0000FF on #DEEAF6, gridline #D9D9D9. Calibri throughout. Title 18pt bold, section headers 9-10pt bold, body 9pt (Dashboard) or 11pt (Data_2). Number formats: 0.0% / 0.00% / #,##0 / 0.0 / m/d/yy / mmm-yy / mmmm d,yyyy. No currency or multiples in source workbook (flagged for peer). | F9: ava_style_guide.json written to shared files (~14k chars). Peer has canonical example ranges, hex codes, font specs, border patterns, and layout conventions for applying matching branding to Rollforward Model.
A10: 9 | B10: 46131 | C10: Rollforward peer asked to narrow the style guide to ONLY the 'blue' formatted summary/dashboard tabs (not raw data dumps), with specific focus on colors, fonts, totals, input cells, and canonical example ranges. | D10: Surveyed all 42 tabs, classified 10 as blue-formatted (Dashboard_1, Delinquency_Detail_3, App_Pipeline_Intel_4, Action_Item_Tracker_5, Weekly_Question_Set_6, Screening_Impact_Analysis_7, Eviction_Success_Rate, CAF vs Pipeline Comparison, Incentive_Scorecard, Instructions) vs 29+ raw data tabs. Flagged variants: Data_2 (styled data table, 20pt title), LeaseLock (#102346 vendor palette, not AVA), Claude Log (#4472C4 Excel default). Pulled real styles from 3 canonical blue tabs (Dashboard_1, Delinquency_Detail_3, Action_Item_Tracker_5) + Eviction_Success_Rate for totals-row pattern. | E10: Brand palette: #1F3864 primary navy (title, header bars), #1B365D subsection label text, #E8EEF4 subsection/total fills, #2E5090 divider borders (thin/medium), #DEEAF6 emphasized/input fill with #0000FF bold input text. Status triad: good #C6EFCE/#006100, warning #FFF2CC/#BF8F00, bad #FFC7CE/#9C0006. Calibri throughout. Title 18pt bold navy; column-header bars 8-9pt white-on-navy bold; subsection labels 9-10pt bold navy on light blue; body 8-9pt. Number formats: $#,##0.00 (with cents), $#,##0 (whole), #,##0, 0.0%, 0.0, m/d/yyyy, mm/dd/yyyy, 'mmmm d, yyyy'. Totals: fill #E8EEF4 + bold black + thin #1F3864 top/bottom borders (canonical: Eviction_Success_Rate A16:E16). | F10: Wrote ava_style_guide.json (~13k chars) to shared files and sent to peer. Guide is narrowly scoped: explicit list of blue vs raw tabs, canonical example ranges for every element (title, header bar, subsection label, totals, input cell, status badges, currency, dates), and notes on 2 tabs that look similar but use different palettes (LeaseLock, Claude Log) so the peer doesn't copy them by mistake.
A11: 10 | B11: 46131 | C11: Peer acknowledged eviction_split.json but reported both other tasks (cross-tab verification + style guide) still open — they hadn't received the files. Asked to complete both. | D11: Rewrote both files fresh in a single execute_office_js call and broadcast via conductor.writeFile. | E11: eviction_crossref.json (5729 chars): cross-tab verification identifying resident aged receivable's Lease Status as authoritative. Jan-Mar 2026 verified breakdown: 66 total move-outs, 28 eviction-bucket by Reason, but only 1 formal eviction per ResMan (Candler W18-2-2070), 26 Past-Skip, 1 not in sample (Nwosu S39-155). 5 explicit conflicts documented. ava_style_guide.json (8595 chars): narrow scope for 10 blue formatted tabs, Dashboard_1 canonical, explicit do-not-copy list (LeaseLock #102346, Claude Log #4472C4), palette (#1F3864 navy, #1B365D text, #E8EEF4 subsection fill, #2E5090 divider, #DEEAF6 emphasized/input, status triad), Calibri font sizes 18/11/9-10/9/8, number formats, canonical example ranges. | F11: Both files broadcast. Sending consolidated message to peer confirming availability and summarizing key findings. Peer had paused Rollforward Model writes until verification arrived.
A12: 11 | B12: 46131 | C12: Peer reported still only has eviction_split.json and asked for the two outstanding tasks. Shared-file broadcasts aren't persisting for this session — listFiles returns empty after write, readFile returns null. Switching to inline delivery. | D12: Wrote verified_move_outs_crosstab.json (8788 chars) and ava_style_guide.json (7423 chars) via conductor.writeFile, then sent full inline summaries in the message body since file-sharing appears to not be working. | E12: Verified Jan-Mar 2026 breakdown (n=66 total): formal_eviction=1 (Candler W18-2-2070 Feb), skip/SWN/FTP=27 (Jan=3 Feb=10 Mar=14), NTV=29 (Jan=1 Feb=15 Mar=13), early_term=6 (all Feb), property_nonrenewal=3 (one each month). Sum=66 checks. Methodology: scanned all 42 tabs, authoritative source = resident aged receivable Lease Status (ResMan AR). RSI only has Feb filings — not the count basis. Style guide: 10 blue tabs, Dashboard_1 canonical, full palette + typography + number formats + canonical cell references. | F12: Both deliverables now inline in peer message. Rollforward peer has what they need to proceed with writes. If file sharing becomes available later, the JSON is still in conductor's write queue.
A13: 12 | B13: 46131 | C13: Peer confirmed receipt of eviction_crossref.json and is proceeding with Rollforward Model. Style guide (ava_style_guide.json) still outstanding. Peer asked for it as the last remaining task. | D13: Rewrote ava_style_guide.json via conductor.writeFile (7724 chars). Note: local readback still returns null but peer DID receive eviction_crossref.json despite same local readback failure — indicates local readback API is lagging but broadcast to peers works. | E13: Content: scope = 10 blue formatted summary tabs (Dashboard_1 canonical). Do-not-copy list (LeaseLock/Claude Log/Data_2). Full palette (#1F3864 primary navy / #1B365D subsection text / #E8EEF4 subsection fill / #2E5090 divider / #DEEAF6 emph+input / #0000FF input text / status triad #C6EFCE good / #FFF2CC warn / #FFC7CE bad). Calibri typography 18/11/9-10/9/8pt. Number formats: $#,##0.00, $#,##0, #,##0, 0.0%, mmmm d\, yyyy, m/d/yyyy, mm/dd/yyyy. Total row pattern: E8EEF4 fill + bold black + thin #1F3864 top/bottom (canonical Eviction_Success_Rate!A16:E16). Column widths, row heights, canonical cell refs for every element. | F13: Sent confirmation message to peer. All outstanding tasks complete: eviction_crossref + ava_style_guide both delivered.
... A84: 44 | B84: 46140 | C84: User asked to update Weekly_Question_Set_6 for Wk17 with specific themes: new prospects quality (post pricing change), conversion drop, Justin onboarding, maintenance backfill, renewals to 80%, collections to 93%, WO backlog plan. | D84: Pulled Wk17 Dashboard, App Pipeline, and Targets KPIs. Built 12 questions: 3 Leasing (B7-B9), 3 Collections (B11-B13), 3 Renewals (B15-B17), 1 Ops (B19), 2 Carryover (B21-B22). Each with Discussion Topic (C), Supporting Data (D), Target (E), Actual (F), Var (G). Applied red/green conditional formatting to F/G columns based on hit/miss. | E84: Also added Wk17 action item: 'Maintenance Supervisor Backfill' (row 15, owner Alex, ASAP, Pending) re Angel's resignation. WO backlog 101 (+19 WoW), completion 83.7% post-Angel. New 80% renewal targets already in Targets!J18:J28 (user updated). | F84: Complete. Yellow H column ready for team responses. Question set covers all themes user specified.
A85: — | B85: 46141 | C85: Update Write_Off_Recon for April submission — former/move-outs in books 60+ days. | D85: Rebuilt detail block (rows 14-61) and JE block (rows 69-93) from current resident aged receivable data. | E85: Filtered aged receivable to Past/Past-Eviction/Past-Skip residents. Wrote 48-row detail block sorted by write-off amount. F-column formula uses E3 (as-of date 4/28/2026) - Lease End. Eligibility = days vacated >= 60. K column = 61-90 + 90+ aging buckets. Linked JE block H column to detail K via formula refs. Extended JE block from 12 to 16 line items; shifted JE entry block from rows 83-89 to 87-93. Fixed F formula to handle blank rows so COUNTIF gives correct count. | F85: 16 accounts eligible totaling $146,432.24 (7 Eviction $70,403, 5 Skip $57,073, 4 Former $18,955). JE: Dr Bad Debt Expense / Cr Tenant Receivables. Ready for PMC Accounting submission.
A86: 2 | B86: 46147 | C86: Verify why April renewal rate is flat WoW on Dashboard_1. | D86: Traced D35/F35 formulas back through Data_2 row 50 to 'Resident Retention -12 months' source. | E86: D35 reads Data_2!W50 (=29/60=48.33%, live formula). F35 reads Data_2!V50 = 0.4833 (HARDCODED to match W50). Source has Transfers=2 (H4) and Pending=5 (I4) not included in W50 numerator (only column F Renewals). | F86: Two issues: (1) V50 hardcoded prior-week value masks WoW movement; (2) W50 formula likely undercounts numerator. Awaiting user direction on which to fix.
A87: 1 | B87: 46147 | C87: Verify why April renewal rate is not moving WoW on Dashboard_1. | D87: Read Resident Retention -12 months source for April (row 4). | E87: April source row: Expiring=63, Early MO=6, NTV=18, Renewals=29, Transfers=2, Pending=5, MTM=3 (reconciles to 0). Pending count = 5. | F87: Reported Pending=5 to user. Awaiting direction on whether to fix V50 hardcode and/or W50 numerator definition.
A88: 10 | B88: 46147 | C88: User asked why April renewal rate isn't moving WoW on Dashboard_1, then whether transfers are accounted for in 63 expiring and whether all MTM should be reflected in D46. | D88: Traced Dashboard_1!D45/D46 formulas through Data_2 to two source sheets: 'Resident Retention -12 months' and Res_Retention. Read both. | E88: D45 (Renewal %) sources 'Resident Retention -12 months' row 4: Expiring=63, Renewals=29, Transfers=2, Pending=5, MTM=3, NTV=18, Early MO=6 (reconciles). W47 denominator = 63-3 = 60; W50 = 29/60 = 48.3%. Prior week (V50) hardcoded 0.4833 = matches W50, masks WoW. D46 (Total MTM) sources Res_Retention!O3 = 65 via SUMPRODUCT(O2:O14). The two source sheets disagree on April: Res_Retention shows Expiring=125, MTM=65; 'Resident Retention -12 months' shows Expiring=63, MTM=3. Transfers (2) ARE included as a sub-bucket of the 63 expiring. | F88: User informed: (1) transfers already in 63 expiring; (2) D46=65 reflects all MTM from Res_Retention but renewal denominator only uses 3 from a different sheet — internal inconsistency. Asked user whether to reconcile sources or repoint W47/W50 to Res_Retention.
A89: 1 | B89: 46147 | C89: Verify why April renewal rate is flat WoW; whether transfers are in 63 expiring; whether all MTM is in D46; recommend correct calculation. | D89: Read Resident Retention -12 months (row 4), Res_Retention (row 3), Dashboard_1 A44:I52, and Data_2 row 47/50/57. | E89: Dashboard_1 D45 (Renewal %) sources 'Resident Retention -12 months': 29/(63-3)=48.3%. F45 prior-week reads Data_2!V50 which is HARDCODED 0.4833 (no formula) — root cause of flat WoW. D46 (Total MTM=65) sources Res_Retention!O3 via SUMPRODUCT — different sheet than renewal source. Source conflict for April: Resident Retention -12 months shows Expiring=63/MTM=3; Res_Retention shows Expiring=125/MTM=65. Transfers (2) ARE included as sub-bucket of 63 expiring (29+2+5+6+18+3=63). W50 numerator only includes Renewals column F, excludes Transfers (H) and Pending (I). | F89: Recommended: pick single source of truth, define numerator (Renewals only vs +Transfers vs +Pending), and convert V50 hardcode to formula. Awaiting user decisions on (1) source sheet, (2) numerator definition, (3) fix V50 going forward.
A90: 2 | B90: 46147 | C90: User asked if all column W data in Data_2 comes from the same tab. | D90: Read all W-column formulas in Data_2 (W1:W91) to trace source tabs. | E90: Column W draws from 10+ source tabs. Renewal rows (W37-W55) all reference 'Resident Retention -12 months'. W57 (Total MTM) is the outlier — uses Res_Retention!O2:O14 via SUMPRODUCT (=65). The renewal denominator (W47) subtracts MTM=3 from 'Resident Retention -12 months', not the 65 from Res_Retention. Gap = 62 units. | F90: User informed of source tab mapping. W57 is the sole cross-source inconsistency in the renewal/MTM area. Awaiting user decision: repoint W57 to 'Resident Retention -12 months' or update renewal denominator to use Res_Retention MTM.
A91: 3 | B91: 46147 | C91: User confirmed W57 (Res_Retention) is correct source for MTM. Asked whether transfers are accounted for in total expirations and should count as renewals. | D91: Reconciled all 15 months of 'Resident Retention -12 months' — sum of components equals Expiring Leases in every row (diff=0). | E91: Transfers ARE included in total Expirations (denominator) but NOT in Renewals numerator (col F only). April: 29 renewals / (63-3 MTM) = 48.3%. If transfers (2) counted: 31/60 = 51.7%. If +Pending (5): 36/60 = 60.0%. Transfers appear in 3 months: Apr=2, May=1, Jan-27=1. | F91: Recommended counting transfers as renewals since they represent retained residents. Awaiting user confirmation to update W50 formula.
A92: 4 | B92: 46147 | C92: User asked to update all renewal month formulas in column W to include Transfers in the numerator. | D92: Updated W40 (June), W45 (March), W50 (April), W55 (May) formulas to add SUMIF for col H (Transfers) to numerator. | E92: New formula pattern: =(SUMIF(...$F:$F)+SUMIF(...$H:$H))/W_denom. Results: W40=34.5% (unchanged, 0 transfers), W45=65.5% (unchanged, 0 transfers), W50=51.7% (+3.3pp, 2 transfers), W55=49.1% (+1.8pp, 1 transfer). Added notes on each cell documenting the change. | F92: Formulas updated and verified. April renewal % now 51.7% (was 48.3%). Dashboard_1!D45 will reflect 51.7% via INDEX into Data_2!W50.
A93: 5 | B93: 46147 | C93: User uploaded 'Resident Retention (11).csv' and asked to update 'Resident Retention -12 months' tab for May and future months. Confirmed May forward only (leave April as-is). Also noted ~65 MTM should be removed — CSV shows 54 for May. | D93: Parsed CSV (13 rows, Apr 2026-Apr 2027). Compared to current sheet and Res_Retention. Updated rows 5-16 (May 2026-Apr 2027) with CSV values. Left row 4 (April) unchanged per user. | E93: Key changes: May Expiring 57→111, May MTM 0→54, May Renewals 27→28, Nov Pending 41→42. Data_2 formulas auto-updated: W52 (May denom)=57 (111-54), W55 (May renewal%)=50.9%, W57 (Total MTM)=54 (was 65). Apr row 4 left at Expiring=63, MTM=3. | F93: Rows 5-16 updated. Data_2 and Dashboard_1 formulas recalculated. W57 (Total MTM) now 54. Verified downstream formulas correct.
A94: 6 | B94: 46147 | C94: User updated source report tabs (except LeaseLock) and added Application_Status_May. Asked to verify all blue (dark blue #002060) analysis tabs updated correctly. | D94: Audited all 8 dark blue tabs: Dashboard_1, Data_2, Delinquency_Detail_3, App_Pipeline_Intel_4, Action_Item_Tracker_5, Weekly_Question_Set_6, Screening_Impact_Analysis_7, Eviction_Success_Rate. | E94: Dashboard_1: D40=50.9% (May), D45=34.5% (Jun), D46=54 (MTM) — all correct. Delinquency, Action Items, Weekly Questions, Eviction, Screening: no errors, formulas intact. App_Pipeline_Intel_4: VSTACK in B66 only references Feb+Mar+Apr — Application_Status_May NOT included. Total Apps=168 excludes May-only applicants. E3 source label also outdated. | F94: 7 of 8 dark blue tabs verified OK. App_Pipeline_Intel_4 needs VSTACK/LET formulas updated to include Application_Status_May. Awaiting user confirmation to proceed.
A95: 7 | B95: 46147 | C95: User asked to verify all 8 dark blue tabs updated correctly after refreshing source report tabs and adding Application_Status_May. | D95: Full audit of all 8 dark blue tabs: read every cell on Dashboard_1, Data_2, Delinquency_Detail_3, App_Pipeline_Intel_4, Action_Item_Tracker_5, Weekly_Question_Set_6, Screening_Impact_Analysis_7, Eviction_Success_Rate. Scanned for formula errors (0 found). Checked data freshness and source references. | E95: 5 tabs clean (Dashboard_1, Data_2, Delinquency_Detail_3, Action_Item_Tracker_5, Eviction_Success_Rate). 3 issues found: (1) App_Pipeline_Intel_4 VSTACK/LET formulas exclude Application_Status_May — Total Apps=168 understated. (2) Weekly_Question_Set_6 has stale Wk13 report date and Wk17 talking points. (3) Screening_Impact_Analysis_7 E13 only counts denials from Feb/Mar/Apr, inherits stale pipeline data. | F95: Recommended: update App_Pipeline formulas for May, update Screening E13, and refresh Weekly_Question_Set content. Awaiting user confirmation.
A96: 8 | B96: 46147 | C96: User asked to fix App_Pipeline_Intel_4 (add May to VSTACK/LET formulas) and Screening_Impact_Analysis_7 E13 (add May to denial count). | D96: Updated B66 VSTACK to include Application_Status_May. Updated C-K LET formulas in row 66 to cascade May→Apr→Mar→Feb. AutoFilled rows 67-246 (181 rows). Updated E3 source label. Updated Screening E13 COUNTIFS to add May. | E96: App_Pipeline: B66 VSTACK now has 4 month tabs, unique units 168→181 (+13 new May units). C-K LET formulas now check May first (myCnt variable). All 1,629 cells error-free. Screening: E13 now sums denials from Feb+Mar+Apr+May = still 21 (May S column all 0). Notes added to B66 and E13. | F96: Both fixes complete and verified. No formula errors. App_Pipeline_Intel_4 and Screening_Impact_Analysis_7 now include Application_Status_May data.
A97: 9 | B97: 46147 | C97: User asked how gross charges are calculated in Dashboard_1 (selected F48). | D97: Traced F48 and D48 formulas: both INDEX into Data_2 row 65. W65=SUM('receipts by charge code-AVA'!$C:$C). V65 hardcoded (prior week snapshot). | E97: Dashboard D48 (current wk)=$767,074 from Data_2!W65 which sums 'receipts by charge code-AVA' col C (Total Charges) across 32 charge codes. F48 (prior wk)=$890,342 from Data_2!V65 (hardcoded). Source tab has columns: Charge Code, GL Account, Total Charges, Prior Collections, Current Collections, Total Cash Collections, Credits/Concessions. | F97: Explained formula chain to user. No changes made.
... A141: 5 | B141: 46176 | C141: User clarified the 90K should be the delinquency balance as of 5/31. | D141: Located 5/31 (serial 46172) = row 125 on trending delinquency; broke aged-receivable into aging buckets (0-30/31-60/61-90/90+) by status category to search for a 90K total. | E141: 5/31 trending Delinquency (D125) = 826,382. Aged-recv totals: all=1,385,566; true-delinquent=790,309; 90+ all=542,181; 90+ delinquent=528,719; Current+Notice 90+=65,505; delinquent 31-60=100,995. No status/aging combination yields ~90K. Likely the workbook tabs are a newer/larger extract than the 90K figure, or 90K lives in an unreferenced cell. | F141: Confirmed 90K is not derivable from current tab data. Asked user to point to the exact sheet+cell where 90K appears. Awaiting cell reference.
A142: =A141+1 -> 6 | B142: 46182 | C142: Refresh the LeaseLock tab from the uploaded CSV (64 claims) — update statuses of existing claims and add any new ones. | D142: Matched 64 CSV claims by claim_number against LeaseLock col A: 63 already existed (updated only changed cells), 1 was new (appended). | E142: Updated 11 changed cells in existing rows (tenant-name corrections in col C, one denial reason Q150, one missing-doc list Y105, one dismissed flag R132); no status changes. Appended new claim 26-117282 (Andres Hernandez, N20-2089, status New) at row 164 with formulas N=L-M, O=IF(L=0,..,M/L), T=I-U, V=TEXT(U,YYYY-MM); left P (Coverage Limit, not in CSV) blank. | F142: LeaseLock now has 163 claims (rows 2-164). New row 164: claimed $1,000.72, paid $0, days-to-file 54, month 2026-04. No formula errors.
A143: =A142+1 -> 7 | B143: 46182 | C143: After updating green source tabs + adding June app-status tab, verify all blue (calculated) tabs updated correctly — especially the Dashboard and the Delinquency tab (move-outs from evictions should flow to the Former section). Preserve manual notes in Delinquency column L. | D143: Scanned all 7 blue tabs for errors; audited Dashboard_1 and Delinquency_Detail_3 logic; fixed Delinquency ranking formula + cleaned override lists; fixed Data_2 #REF errors. Did NOT modify column L. | E143: Delinquency_Detail_3: (1) fixed Section B ranking A173:A181 (were missing the '(On Property)' clause that A139:A172 use, corrupting the LARGE-rank) so list is 43 distinct residents; (2) cleared stray ranking formulas in total rows A135/A136/A182; (3) removed Harris, Fridia, Hishaw, Jackson from the P 'Current Override' list (all now rar status 'Past-Eviction'=moved out) so they route to the Former section — kept Simpson & Sparks (still 'Current-Eviction'). Data_2: fixed 8 #REF! cells in DSO rows 85-86 (broken 'T12' refs) — row85 uses 'T12'!$C$24; row86 2-mo trailing uses AVERAGE('T12'!$D$24,'T12'!$C$24). Dashboard_1: verified, no changes needed. | F143: All 7 blue tabs now error-free (0 formula errors). Moved-out evictions now in Former section. FLAGGED for user judgment: N 'Moved Out Override' has names whose rar status is still present (Coronado=Current, Dixon=Notice-MTM, Alvarez & NJENDU=Notice-Eviction, Taiwo=not in rar); Data_2 row86 prior-month ref assumed T12!$D$24; Section B shows 43 of 59 / Section A 118 of 173 due to fixed row capacity.
A144: =A143+1 -> 8 | B144: 46183 | C144: User asked what the Dashboard D61 delinquency balance was at the end of April and end of May. | D144: Explained D61 is a live snapshot (Current*+Notice* SUMIF on resident aged receivable) with no history; pulled month-end values from the trending delinquency daily series. | E144: Month-end serials: Apr 30 = 46142 -> $724,738 (trending delinquency D108); May 31 = 46173 -> $826,043 (D126), matching Data_2 row 80 Wk22. Noted D61's narrow Current+Notice definition does not reconcile to the broad all-status trending balance; Apr 30 is the monthly trough (pre-May charge posting). | F144: Provided April 30 = $724,738 and May 31 = $826,043. Flagged that D61-definition (Current+Notice only) month-end history is not stored in the workbook.
A145: =A144+1 -> 9 | B145: 46183 | C145: User uploaded April and May aged-receivable CSVs and asked for delinquency (calculated exactly like D61) and total collection % for both months. | D145: Replicated D61 logic on each CSV; mapped workbook col E=Lease Status to CSV col C and col I='Unallocated Charges/Credits' to CSV col F; SUMIF Current*+Notice*. Flagged that collection % cannot come from aged-receivable snapshots. | E145: April file = '...(1).csv' (notes thru ~5/1): Current*=241,342 + Notice*=23,037 -> D61 magnitude $264,379. May file = no-suffix (notes thru 5/30): Current*=59,618 + Notice*=66,043 -> $125,661. D61 stores as negative. Collection % = Payments/Net Charges (Data_2 r76) needs charges+receipts not present in aged receivable. | F145: Delivered April $264,379 and May $125,661 delinquency. Collection %: user will upload separate charges/receipts reports; awaiting those to compute Payments/Net Charges per month.
A146: 10 | B146: 46183 | C146: Uploaded image of William's comments on the Q2 2026 Incentive_Scorecard and asked how to respond to his target-setting questions for Shawna, Alex, Nylsa, and Avery. | D146: Read Incentive_Scorecard actuals plus Dashboard_1 (wk23/June) and Targets (refi scenario); drafted a data-grounded reply recommending target adjustments for each participant. | E146: Key facts cited: physical occ 72.9% (vs 84% target), renewal ~60% Q2 (recommend 65% not 80%), collection 89.5% (recommend 90% not 93%), eviction court 94% (keep 85%), NOI $13.6K Apr/$110.8K May vs $258K proforma (95% unrealistic, rebase), delinquency $264K->$126K (keep <=$200K), filing accuracy 86.5% (keep 90%), LeaseLock recovery 16% vs 60% target which contradicts $40-65K expected recovery (recommend ~20-25%). | F146: Reply drafted in chat; offered to update scorecard target cells to recommended values. Awaiting user go-ahead.
A147: =A146+1 -> 11 | B147: 46185 | C147: Update the Write_Off_Recon tab as of June 8th. | D147: Refreshed the tab to a June 8, 2026 basis: updated Report Period (B3), expanded the write-off recommendation list from 16 (April) to 26 eligible accounts, and rebuilt the proposed journal entry section for June. | E147: As-of date E3 already pulled June 8 from Dashboard_1!F3, so detail aging was current. Inserted 10 rows (85:94); list rows 69:94 now link by formula to the detail table (=B14/=A14/=G14/=K14 etc.) instead of static values, sorted by write-off amount desc. Updated A64/A66/A97 headers to June 2026, JE date B98=6/8/2026, JE descriptions to (Jun 2026), totals G95/H95=SUM(69:94), H98=COUNTA(B69:B94). Normalized formatting/borders on expanded rows. List = all accounts 60+ days since move-out (eligibility logic unchanged); did not filter by col M 'Write-Off Approved'. | F147: Write-off total $178,280.32 (26 accounts) ties exactly to summary B7/B6; JE debit=credit=$178,280.32. 10 newly eligible accounts added since April list (e.g., Smith, Williams L., Brown T., Santana, Jose Y.).
A148: =A147+1 -> 12 | B148: 46191 | C148: Update LeaseLock statuses from the uploaded CSV for existing residents, add any new ones, and make sure statuses auto-update in the Delinquency tab. | D148: Refreshed all 64 existing CAF Management claims in LeaseLock from the CSV (matched by claim #/Item #). Found 0 new residents to add. Verified Delinquency tab pulls LeaseLock status live. | E148: Updated cols F,G,I,J,L,M,P,Q,R,S,U,W,X,Y,AC on LeaseLock rows 101-164; left N/O/T/V as live formulas. Delinquency_Detail_3 col K (LeaseLock/RSI) + summary C11:H14 reference LeaseLock!$2:$500, covering all updated rows. Calc mode confirmed Automatic; forced full recalc. | F148: LeaseLock current (e.g. Andres Hernandez New->Closed, $932.50 paid). Delinquency statuses live (e.g. Brown, Nicole 'LL: Closed - $750 paid'; Recovery Rate 16.7%). No new rows added.
A149: =A148+1 -> 13 | B149: 46191 | C149: Delinquency LeaseLock summary Recovery Rate is unfair (denominator = Total Claimed, ignoring policy coverage caps). Add a separate 'Avery's Recovery %' in J11:K11 based on capped/claimable amounts. | D149: Added Avery's Recovery % at J11:K11 = Total Paid / Claimed Within Limit (each claim capped at its coverage limit). Also fixed incomplete W column on LeaseLock. | E149: K11 =IFERROR(SUM(LeaseLock!M2:M500)/SUM(LeaseLock!W2:W500),0), fmt 0.0%, with note. Filled LeaseLock 'Claimed Within Limit' (W) for 99 older IPS rows using =MIN(L,P) since W was blank there (which had inflated the ratio to 178%). Unprotected/re-protected the Delinquency sheet to write. Standard Recovery Rate (H11) left unchanged. | F149: Avery's Recovery % = 65.5% vs standard Recovery Rate 16.7%. LeaseLock col W now complete for rows 2-164.
A150: =A149+1 -> 14 | B150: 46191 | C150: Asked how Avery's Recovery % is calculated — specifically whether it's total coverage limit vs paid. | D150: Explained the calculation. Clarified it is NOT total coverage limit; denominator is Claimed Within Limit = MIN(claimed, coverage limit) per claim (LeaseLock col W). | E150: Avery's % = SUM(M) $80,580 / SUM(W) $122,983 = 65.5%. Contrasted with total-coverage-limit method (SUM(P) $135,500 = 59.5%) and standard rate (SUM(L) $482,130 = 16.7%). Offered to switch denominator to full coverage limit if preferred. | F150: Explanation provided; no spreadsheet changes. Awaiting user decision on whether to use within-limit (current) or full coverage limit denominator.
A151: =A150+1 -> 15 | B151: 46191 | C151: Asked how the 65.5% (Avery's %) compares to LeaseLock column O per-claim recovery calculations. | D151: Analyzed and compared. Column O = Paid/Total Claimed per claim (uncapped, same basis as 16.7% total rate); Avery's 65.5% caps each denominator at coverage limit. | E151: Across 163 claims: Column O avg 31.1%, median 24.4%, aggregate 16.7%. Within-limit basis: avg 65.2%, median 100%, aggregate 65.5%. 128/163 (79%) claims exceeded cap; only 3 at 100% on col O vs 83 at 100% on capped basis. Offered to add a capped per-claim recovery column next to O. | F151: Comparison explained; no spreadsheet changes. Avery's 65.5% ~= 4x aggregate col O and ~2x simple avg of col O.
A152: =A151+1 -> 16 | B152: 46191 | C152: Audit only (no changes): on the Delinquency evictions tab, check the CURRENT RESIDENTS section for anyone who actually moved out in the last week, using the rent roll + move-out report; ignore future move-out dates. | D152: Audited all 41 current residents (rows 139-179) by unit against RR_Unit_Details (rent roll) and Move_Out_Reasons. Flagged 3 who moved out in the last week but are still listed as current. | E152: Flagged: Marshall, Alton N20-2093 (row 141) moved out 6/16/26 'Failure To Pay'; Cruz, Lesly N11-2042 (row 151) 6/17/26 'Skipped During Eviction' (unit now Vacant in rent roll); Cooper, Latricia N19-1083 (row 167) 6/15/26 'Non-Renewal'. Of the rest: 22 'Notice Unrented' have FUTURE expected move-outs (correctly still current), 18 'Occupied No Notice'. Ignored Move_Outs_ResMan (stale through 3/31/26) and discarded loose name-matches (false positives). | F152: 3 residents likely need reclassifying from Current to Former/Moved-Out. Audit only - no changes made to the model.
A153: 17 | B153: 46197 | C153: Update LeaseLock tab from uploaded CSV (Untitled-2026-06-24.csv) — refresh status of existing claims and add all new entries; file is most up to date. | D153: Matched 69 CSV claims by Item # against 163 existing rows: updated 64 existing CAF Management records and appended 5 new entries. | E153: Matched by claim_number→Item# (col A). Updated cols F,G,J,L,M,P,Q,R,S,X,Y,AC on rows 101-164. Added rows 165-169 (claims 26-118121/118125/118313/118316/118305) with formulas N,O,T,V,W and formats copied from row 164. Coverage Limit (P) = total_paid + unused_coverage_limit. | F153: LeaseLock now has 168 data rows (2-169). New entries: Earl Roof, Leaujodon Alexander, Jordan Feaster, Ramiro Gabriel/Yanheli Barriga, Krystal Farrell. Investor Property Services rows (2-99) untouched.
A154: 18 | B154: 46197 | C154: Dashboard renewals: June/July Max Renewal % Possible were wrong (sourced from static cells in Data_2). Integrate Skips & Max Renewal % into the weekly table so they update weekly; remove April renewals, shift May/June/July up, add August. | D154: Restructured Data_2 renewals blocks and rebuilt the Dashboard_1 renewals section. | E154: Data_2: inserted Skips (Evictions) + Max Renewal % Possible as weekly rows in May (52/53), June (59/60), July (66/67) and built a new August block (68-74); replicated the month-anchored Move_Out_Reasons/Resident-Retention formulas across all weekly cols D:AD so they recompute weekly; deleted the orphan cells (old D104-D111). Dashboard: removed April, shifted May(26-33)/June(34-41)/July(42-49) up, cloned July to build August(50-57); re-pointed Skips/Max D&F to the new in-table rows via INDEX(...,$C$3+2). | F154: Dashboard now A1:I81. Verified live values: May Skips 19/Renewal 64.8%/Max 61.4%; June Skips 8/Max 30.9%; July Skips 3/Max 50%; Aug Skips 2/Max 68.6%/Pending 22; Total MTM 35. Downstream intact: Gross Charges 881,238.6, DSO 29.09, WO Opened 145, Avg NER 1,060.27.
A155: 19 | B155: 46197 | C155: Max Renewal % Possible showed below the actual renewal rate (June max 30.9% vs 39.7% renewal; same for May) — calc was wrong. | D155: Corrected the renewal-rate and max-possible formulas in Data_2 for May/June/July/August to the workbook's documented basis. | E155: Root cause: (1) actual Renewal % current-week cells divided by the WRONG month's lease count (May AD51 used June's expirations, June AD58 used an earlier month's =58) — pre-existing broken refs; (2) my Max formula used (Renewals+Pending)/Expirations. Rewrote both self-contained from 'Resident Retention -12 months': Renewal %=(F Renewals+H Transfers)/(C Expirations−J MTM); Max=(F+H+I Pending)/(C−J). Renewal% fixed only in current-week col AD (preserved manual history N:AC); Max% across D:AD. Anchors A48/A55/A62/A69. | F155: Max now ≥ actual for all months. May 62.5%/64.3%, June 42.6%/48.1%, July 28.4%/50.0%, Aug 25.5%/68.6%. Note: actual renewal rates also shifted (e.g., June 39.7%→42.6%) because their denominators were corrected.
A156: 20 | B156: 46197 | C156: August block on the dashboard showed no data for Expirations and Non-Renewals. | D156: Wired August Expirations/Non-Renewals/NTV in Data_2 to the Resident Retention tab, matching the formula pattern used by the other months. | E156: Set Data_2 AD69 (Exp−MTM)=SUMIF(RR C)−SUMIF(RR J), AD70 (Non-Renewals)=SUMIF(RR D), AD71 (NTV)=SUMIF(RR E), anchored to $A$69 (Aug 1, 46235). These had been left blank for manual entry when the block was created. | F156: Dashboard August now shows: Expirations 51, Non-Renewals 5, NTV 11, Skips 2, Pending 22, Renewal 25.5%, Max 68.6%. Verified rendered values.
A157: 21 | B157: 46197 | C157: Delinquency Detail: people in the Former/Evictions section had future move-out dates but were still on the rent roll — should be in Current section. Preserve K/L comments. | D157: Verified all Former-section future-move-out residents against the 'resident aged receivable' rent roll; corrected the 3 that were mis-flagged. | E157: Sheet is formula-driven. Root cause: 3 active residents were in the MOVED OUT OVERRIDE list (col N), forcing them into Former and excluding them from Current. Cleared N12 (Coronado, Iram), N13 (Alvarez, Nixon), N15 (Dixon, Dewayne) — all status 'Notice - Eviction' (still on property). Other override names verified as genuinely Past/moved-out and left as-is. Re-ranked Current section gained 3 rows (now 139-174); manually re-aligned the row-anchored CAF notes in col L so each note stayed with its resident; 3 new arrivals left blank. Col K is formula (auto). | F157: The 3 now appear in Current (rows 140/142/149) as active evictions and remain in the Evictions/Former list (rows 37/81/92, status Eviction). All L notes preserved and correctly aligned in both sections; verified.
A158: 22 | B158: 46197 | C158: Eliminate the green error triangles on Delinquency_Detail_3. | D158: Diagnosed the triangles; advised manual fix. No formula changes (formulas are correct). | E158: Scanned full used range: 0 numbers-stored-as-text, totals SUM ranges complete (no omits-adjacent). Triangles are 'Inconsistent Formula' false-positives on summary cells (C6/C7/C8/C9/C12, E12/E13, H6/H7/H8/H12/H13) — different metrics stacked vertically (e.g. C7 two COUNTIFs, C9 three SUMIFS, H13 text formula). Office.js exposes NO error-checking API, so cannot dismiss indicators or toggle background error checking programmatically. | F158: Advised user: select B5:H13 → ⚠ → Ignore Error (file-saved), or File>Options>Formulas>uncheck Enable background error checking (global). Declined to convert KPIs to static values (would go stale). No workbook changes made this turn.
A159: 23 | B159: 46204 | C159: Uploaded a new LeaseLock claims export CSV (78 claims); asked to update status and other new info for existing residents in the LeaseLock tab and add all new ones. | D159: Merged the CSV into LeaseLock: matched all 78 claims by claim number (col A); compared every mapped field on the 69 existing matches; appended the 9 claims not yet in the sheet as new rows 170-178 with formulas and row-2 formatting. Also restored the Recovery % formula in O4. | E159: Field mapping: CSV claim_number→A, pmc→B, tenant→C, unit→D, property→E, status→F, substatus→G, certificate→H, reported→I, reoccupied→J, policy holder→K, claimed→L, paid→M, denial→Q, dismissed→R, action required→S, move-out→U, missing docs→X/Y, owner→Z, property id→AA, tenant id→AB, dispute→AC. Coverage Limit (P) derived as paid+unused_coverage_limit (verified = min(claimed,limit) reconciles with CSV within-limit field on all 78 rows). Formula cols written for new rows: N=L-M, O=IF(L=0,"",M/L), T=I-U, V=TEXT(U,"YYYY-MM"), W=MIN(L,P). Tenant co-name order differences ignored (CSV reorders co-tenants). O4 contained stray text 'Need you' (user typed into cell); restored =IF(L4=0,"",M4/L4). | F159: 0 existing rows needed changes - all 69 matched claims already reflected the export exactly. 9 new claims added (26-118841 Scott Johnson, 26-118838 Maricela Ortega/Juan Ruiz, 26-118824 Kelvia Hernandez, 26-118599 Jerry Esebanme/Oluchi Chukwudire, 26-118837 Nadia Ramirez, 26-118600 Luis garcia, 26-118839 Aminu Titilayo, 26-118815 Eric Santini/Mia Smith, 26-118816 Carlos Jose Oliva Cordero) in rows 170-178. All formulas verified error-free; formats (date/currency/%/text) match existing rows.
A160: 24 | B160: 46204 | C160: Verify delinquency tab: no active rent-roll residents in Evictions & Former section (move to Current); fix Excel-highlighted errors. Mid-task: preserve all manual col-L notes and formula col-K notes per resident. | D160: Created Delinq_Notes_Backup tab (144 residents, K values + L notes). Confirmed the prior interrupted run had already applied the Former-section filter fix (excludes Current*/Notice* statuses unless in N override) but left manual L notes misaligned. Reconstructed the pre-fix ranking from rent-roll data to recover true note ownership, re-placed all 20 Former-section notes, appended Divini/Rashidi notes to their Current rows, fixed B135 qualifying-count formula to match the new rule. | E160: Root cause: rent roll no longer uses '(On Property)' status text, so 16 active 'Notice - Eviction' residents leaked into Evictions & Former (all already in Current). Old ranking reconstruction validated: 194 qualifying accounts matched B135 label; 16 removed rows matched pre-cancel scan. Notes preserved: 18 re-placed in Former, 26 untouched in Current, 2 merged with ' | ' separator. K is formula-driven per row and follows residents automatically. | F160: Former section now has no active residents (verified vs rent-roll statuses, N-override respected); all 46 manual notes preserved and owner-matched; B135 shows '118 of 176 qualifying'; no error values in K/L. Backup on Delinq_Notes_Backup tab. Open: user to confirm which cells still show green error indicators, if any (API cannot read/dismiss them).
A161: 25 | B161: 46204 | C161: Re-baseline Targets tab to the AVA Stabilization Rollforward model (6.8.26) from week 26 forward; extend grid to 52 weeks; derive non-model KPIs from model + current asset performance. Follow-up tuning: tours max 40, lower submitted apps but keep model net apps/leases, delinquency 120K->80K steady state, pipeline capped 65/30, days open 10. | D161: Extended weekly grid to rows 31-56 (weeks 27-52 through 12/28/26). Built model anchor table (B60:M68) and global assumptions block (B70:C85) with source notes. Replaced week-26+ targets (rows 30-56, cols C:W) with formulas driven by the anchors: occupancy interpolated between model month-ends, NL/wk and move-outs from model, funnel back-solved from net leases via conversion assumptions, charges = units x $1,350, collections intra-month profile, delinquency glide, pipeline caps. Updated A2 subtitle. Moved Notes row to A58; cleared stray user entries in D37. | E161: Funnel conversions anchored to Mar-26 actuals (25% prospect-tour, 62% tour-sub) with 67% sub-approval target for tighter pre-qual (tours peak 39/wk). Delinquency targets per management 120K->80K (actual is ~$953K - noted on anchor K62). Pipeline 65 total/30 open, 10 days, per management. Week 26 delinq shows $119K due to glide interpolation from $120K anchor at 6/26. | F161: Verified: no formula errors rows 30-56; occupancy monotonic 76.1%->91.4% (804 units wk 52 = model Dec exactly); NL 14->11, tours max 39, charges $905K->$1,085K, coll peak 94%->96%, delinq $119K->$80K, pipeline 65/30/10 flat. Dashboard_1 variances will shift vs new baselines.
A162: 26 | B162: 46204 | C162: Targets tab follow-up: weekly move-outs must sum to the model's monthly totals; collections month-end targets Jun 90%, Jul 92%, Aug 93%, Sep 94%, 95% from Nov (weekly build-up calculated within each month). | D162: Added calendar-month collections anchor table (N61:O68, Oct assumed to hold 94%); cleared superseded period-based Coll% column I61:I68. Rewrote K (move-outs) with exact-sum distribution formula (LET: cumulative rounding within each model period) and N (Coll %) to key off calendar month x intra-month profile C82:C85. Filled K30:K56, N30:N56; payments (M) recalc automatically. | E162: Move-out weekly sums verified = model: Jul 42, Aug 33, Sep 34, Oct 30, Nov 31, Dec 21, +5 YE stub week (H68 prorated, noted). Collections: wk26 = 90% (Jun EOM), Jul builds 41.4/76.4/85.6/92, month-ends 93/94/94/95/95. | F162: No formula errors K30:N56. Weekly collections within each month follow profile 45/83/93/100% of month-end target. Open: confirm Oct month-end collections assumption (94%).
A163: 27 | B163: 46204 | C163: Dashboard collections section understates collections because credits are missing. Add Credits beneath Gross Charges (above Payments Received) and include credits in the total collections calculation. | D163: Inserted two rows in Dashboard_1 COLLECTIONS block: row 61 'Credits' (pulls Data_2 row 85, stored as negatives) and row 63 'Total Collections' = Payments - Credits (i.e., payments + credit amount). Repointed Collection % (row 64) to Total Collections / Gross Charges instead of Data_2 row 89 (which divides by net charges). Moved the payments target to Total Collections; Payments row target now '—'. Format-painted new rows from the Payments row. | E163: Current week: Credits -$45,375; Total Collections $799,081; Collection % rose 81.4% -> 90.0% (vs 90.0% target, status ✗ because actual is 89.98%). Note on D63 documents the sign convention. Scanned Dashboard_1, Incentive_Scorecard, Historical, DSO_Calculation, Write_Off_Recon after row inserts: no error values; only external ref to Dashboard_1 is Write_Off_Recon!E3 -> Dashboard_1!F3 (row 3, unaffected). | F163: Collections block now: Gross Charges / Credits / Payments Received / Total Collections / Collection %, all formula-driven and rendering correctly (verified displayed text). Delinquency section and below shifted down 2 rows.
A164: 28 | B164: 46204 | C164: Add NSFs below Credits on dashboard (netted from payments); align dashboard Collection % to Data_2's method - should be 88.54% for week 26. | D164: Inserted NSFs row (Dashboard_1 row 62, pulls Data_2 row 86). Restructured block: Net Charges (Gross+Credits, Data_2 row 87) and Payments Received (net of NSFs, Data_2 row 88) replace the turn-27 Total Collections construct; Collection % restored to direct pull of Data_2 row 89 = 88.54%. Restored Data_2!AD88 (week-25 payments) to $732,122.45 receipts less NSFs = $724,486.71 with audit note. | E164: Found user's formula drag overwrote all 28 weeks of Data_2 row 88 payments history with live pulls of the CURRENT receipts file (values differ only by each week's NSF). Week 26 correct; week 25 restored from value captured earlier today; weeks 1-24 not recoverable from this workbook (noted on AD88). Data_2 row 89 historical statics remain on the old calc basis (prior-week 79.7% vs new-basis current 88.5%). | F164: Dashboard block verified rendered: Gross $888,018 / Credits -$45,375 / NSFs $7,636 / Net Charges $842,643 / Payments $746,071 / Collection % 88.5% vs 90.0% target. No errors A40:I85. Open: user may want to reload true weekly payments for weeks 1-24 from source reports.
... A197: 61 | B197: 46246 | C197: Weekly Delinquency_Detail_3 validation vs rent roll: no rent-roll resident in Former, every Current resident on rent roll; preserve K/L notes. | D197: Cross-checked FULL qualifying population (99 Former / 58 Current qualifying) plus both override lists against RR_Unit_Details occupied+notice residents (637). Added Nwabunor, Stanley (Stanley) to CURRENT OVERRIDE (P10) - on rent roll at W03-1-0301, balance $270.82 on old unit W15-2-3090 (on-site transfer). Added 4 departed residents to MOVED OUT OVERRIDE (N19:N22): Eliuth Gerson ($581.97), Walker Myocsheonia ($2,094.34), Rodriguez Joseph ($3,504.84), Yoryina Emelyn ($232.37). Re-paired all 38 column-L notes after the re-sort; appended dated entry to N1 note. | E197: Fuzzy last-name search confirmed the 4 are genuinely off the rent roll (11 other Rodriguezes exist, none Joseph). Rodriguez & Walker's Current-section notes followed them to Former rows 63 and 77; remaining 36 notes re-placed at owners' shifted rows, 0 orphaned, nothing archived. Column K formula-driven, self-adjusted. Section formulas ($2:$460) verified to cover refreshed aged receivable data (ends row 182; used range extends to 719 but rows >182 empty). Nwabunor counted in Current total but below top-43 display cutoff (same caveat as Avila/Rocha). | F197: Post-change verification: 0 mismatches both directions across displayed sections, 0 formula errors in A17:L181. Former 102 of 102 qualifying displayed ($562,816); Current 59 accounts, 43 displayed ($106,329 displayed). L notes 13 Former + 25 Current = 38.

Sheet Instructions
C2: AVA APARTMENTS
C3: Weekly Metrics Report — User Guide
C4: Arlast Capital | CAF Management
C7: OVERVIEW
C9: This workbook provides real-time tracking of operational KPIs for AVA Apartments under CAF management.
C10: All calculations are formula-driven. Enter data in the Data tab and the Dashboard updates automatically.
C12: TAB STRUCTURE
C14: Dashboard
C15: Executive summary comparing current week actuals to targets.
C16: Change the "Reporting Week" number (1–24) to view any week. Target, Actual, Variance, Prior Week, WoW Δ, and Status columns all update automatically.
C18: Data
C19: Primary data entry tab. Enter weekly actuals here in the blue-highlighted input cells.
... C88: Questions: Arlast Capital | sergio@arlast.com

Sheet Incentive_Scorecard_Q2
A1: AVA APARTMENTS — Q2 2026 INCENTIVE COMPENSATION SCORECARD (SIMPLIFIED)
A2: Performance Period: April 1 – June 30, 2026 | Measurement Date: June 30, 2026 | Payout: Within 30 days of measurement
A4: PAYOUT SUMMARY
A5: Participant | B5: Role | C5: Total Pool | D5: KPI 1 Payout | E5: KPI 2 Payout | F5: Total Payout
A6: Shawna | B6: Collections Manager | C6: 7000 | D6: =I14 -> 4200 | E6: =I15 -> 2800 | F6: =D6+E6 -> 7000
A7: Alex | B7: Community Manager | C7: 10000 | D7: =I20 -> 3000 | E7: =I21 -> 4000 | F7: =D7+E7 -> 7000
A8: Nylsa | B8: District Manager | C8: 7000 | D8: =I27 -> 3000 | E8: =I28 -> 4000 | F8: =D8+E8 -> 7000
A9: Avery | B9: Sr. Account Manager | C9: 5000 | D9: =I34 -> 3000 | E9: =I35 -> 2000 | F9: =D9+E9 -> 5000
A10: TOTAL | C10: =SUM(C6:C9) -> 29000 | D10: =SUM(D6:D9) -> 13200 | E10: =SUM(E6:E9) -> 12800 | F10: =SUM(F6:F9) -> 26000
A12: SHAWNA — Collections Manager | G12: Pool: $7,000
A13: Metric | B13: Weight | C13: Base Target | D13: April | E13: May | F13: June | G13: Q2 Result | H13: Base Met? | I13: Payout
A14: Current-Month Collection Rate | B14: 0.6 | C14: ≥90% avg | D14: 0.88 | E14: 0.91 | F14: 0.925 | G14: =IF(COUNTA(D14:F14)=0,"",AVERAGE(D14:F14)) -> 0.905 | H14: =IF(G14="","—",IF(G14>=0.9,"✓","✗")) -> ✓ | I14: =IF(H14="✓",B14*$C$6,0) -> 4200
A15: Eviction Court Success Rate | B15: 0.4 | C15: ≥85% | D15: 0.88 | E15: 1 | F15: 1 | G15: =IF(COUNTA(D15:F15)=0,"",SUM(D15:F15)/COUNTA(D15:F15)) -> 0.96 | H15: =IF(G15="","—",IF(G15>=0.85,"✓","✗")) -> ✓ | I15: =IF(H15="✓",B15*$C$6,0) -> 2800
B16: =SUM(B14:B15) -> 1 | H16: Total Payout → | I16: =SUM(I14:I15) -> 7000
A18: ALEX — Community Manager | G18: Pool: $10,000
A19: Metric | B19: Weight | C19: Base Target | D19: April | E19: May | F19: June | G19: Q2 Result | H19: Base Met? | I19: Payout
A20: Occupancy (June 30) | B20: 0.6 | C20: P≥84% & E≥77% | D20: 0.7311 | E20: 0.731 | F20: 0.726 | G20: =F20 -> 0.726 | H20: =IF(OR(F20="",G20=""),"—",IF(AND(F20>=0.84,G20>=0.77),"✓","✗")) -> ✗ | I20: 3000
A21: Renewal Conversion Rate | B21: 0.4 | C21: ≥80% | D21: 0.554 | E21: 0.648 | F21: 0.444 | G21: =IF(COUNTA(D21:F21)=0,"",SUM(D21:F21)/COUNTA(D21:F21)) -> 0.54866667 | H21: =IF(G21="","—",IF(G21>=0.8,"✓","✗")) -> ✗ | I21: 4000
B23: =SUM(B20:B21) -> 1 | H23: Total Payout → | I23: =SUM(I20:I21) -> 7000
A25: NYLSA — District Manager | G25: Pool: $7,000
A26: Metric | B26: Weight | C26: Base Target | D26: April | E26: May | F26: June | G26: Q2 Result | H26: Base Met? | I26: Payout
A27: June NOI vs. Proforma | B27: 0.6 | C27: ≥95% of proforma | D27: 13593 | E27: 110779 | F27: 106565.12 | G27: =IF(F27="","",F27/258116.12) -> 0.41285728 | H27: =IF(G27="","—",IF(G27>=0.95,"✓","✗")) -> ✗ | I27: 3000
A28: Delinquency Compression | B28: 0.4 | C28: ≤$200K | D28: 264379 | E28: 125661 | F28: 130315.28 | G28: =IF(F28="","",F28) -> 130315.28 | H28: =IF(G28="","—",IF(G28<=200000,"✓","✗")) -> ✓ | I28: 4000
B30: =SUM(B27:B28) -> 1 | H30: Total Payout → | I30: =SUM(I27:I28) -> 7000
A32: AVERY — Sr. Account Manager | G32: Pool: $5,000
A33: Metric | B33: Weight | C33: Base Target | D33: April | E33: May | F33: June | G33: Q2 Result | H33: Base Met? | I33: Payout
A34: Eviction Filing Accuracy | B34: 0.6 | C34: ≥90% | D34: 0.73 | E34: 1 | F34: 1 | G34: =IF(COUNTA(D34:F34)=0,"",SUM(D34:F34)/COUNTA(D34:F34)) -> 0.91 | H34: =IF(G34="","—",IF(G34>=0.9,"✓","✗")) -> ✓ | I34: =IF(H34="✓",B34*$C$9,0) -> 3000
A35: LeaseLock Claims Recovery | B35: 0.4 | C35: 100% filed + ≥60% | D35: 0.642 | E35: 0.655 | F35: 0.648 | G35: =IF(COUNTA(D35:F35)=0,"",AVERAGE(D35:F35)) -> 0.64833333 | H35: =IF(G35="","—",IF(G35>=0.6,"✓","✗")) -> ✓ | I35: =IF(H35="✓",B35*$C$9,0) -> 2000
B37: =SUM(B34:B35) -> 1 | H37: Total Payout → | I37: =SUM(I34:I35) -> 5000
A39: PAYOUT MECHANICS & GOVERNANCE
A40: Weighted Payout: Each metric earns its weighted share of the participant's total pool independently. No all-or-nothing gate — missing one metric does not forfeit the other.
A41: No Outperform Bonus: There is no outperform tier. Hit the base target → earn that metric's weighted share. Miss → $0 on that metric.
A42: Blue cells (Apr/May/Jun and Q2 Result columns) are input placeholders. Enter actuals from Entrata and base reports as the quarter progresses.
A43: Mid-Quarter Check-In: ~May 15, 2026 (coaching checkpoint only, no payments). Final measurement: June 30, 2026.
A44: Data Sources: Entrata (system of record), RSI, Nationwide, Arlast Capital weekly metrics workbook, CAF V2 budget. Entrata governs in case of discrepancy.

Sheet Incentive_Scorecard_Q3
A1: AVA APARTMENTS — Q3 2026 INCENTIVE COMPENSATION SCORECARD (SIMPLIFIED)
A2: Performance Period: July 1 – September 30, 2026 | Measurement Date: September 30, 2026 | Payout: Within 30 days of measurement
A4: PAYOUT SUMMARY
A5: Participant | B5: Role | C5: Total Pool | D5: KPI 1 Payout | E5: KPI 2 Payout | F5: Total Payout
A6: Shawna | B6: Collections Manager | C6: 7000 | D6: =I15 -> 0 | E6: =I16 -> 0 | F6: =D6+E6 -> 0
A7: Alex | B7: Community Manager | C7: 7000 | D7: =I21 -> 0 | E7: =I22 -> 0 | F7: =D7+E7 -> 0
A8: Nylsa | B8: District Manager | C8: 7000 | D8: =I27 -> 0 | E8: =I28 -> 0 | F8: =D8+E8 -> 0
A9: Avery | B9: Sr. Account Manager | C9: 5000 | D9: =I33 -> 0 | E9: =I34 -> 0 | F9: =D9+E9 -> 0
A10: Justin | B10: Leasing Administrative Manager | C10: 5000 | D10: =I39 -> 0 | E10: =I40 -> 0 | F10: =D10+E10 -> 0
A11: TOTAL | C11: =SUM(C6:C10) -> 31000 | D11: =SUM(D6:D10) -> 0 | E11: =SUM(E6:E10) -> 0 | F11: =SUM(F6:F10) -> 0
A13: SHAWNA — Collections Manager | G13: Pool: $7,000
A14: Metric | B14: Weight | C14: Base Target | D14: July | E14: August | F14: September | G14: Q3 Result | H14: Base Met? | I14: Payout
A15: Current-Month Collection Rate | B15: 0.6 | C15: ≥95% avg | G15: =IF(COUNTA(D15:F15)=0,"",AVERAGE(D15:F15)) | H15: =IF(G15="","—",IF(G15>=0.92,"✓","✗")) -> — | I15: =IF(H15="✓",B15*$C$6,0) -> 0
A16: Eviction Court Success Rate | B16: 0.4 | C16: ≥90% | G16: =IF(COUNTA(D16:F16)=0,"",AVERAGE(D16:F16)) | H16: =IF(G16="","—",IF(G16>=0.85,"✓","✗")) -> — | I16: =IF(H16="✓",B16*$C$6,0) -> 0
B17: =SUM(B15:B16) -> 1 | H17: Total Payout → | I17: =SUM(I15:I16) -> 0
A19: ALEX — Community Manager | G19: Pool: $7,000
A20: Metric | B20: Weight | C20: Base Target | D20: July | E20: August | F20: September | G20: Q3 Result | H20: Base Met? | I20: Payout
A21: Occupancy (September 30) | B21: 0.6 | C21: ≥79% (Sept 30) | G21: =IF(F21="","",F21) | H21: =IF(G21="","—",IF(G21>=0.85,"✓","✗")) -> — | I21: =IF(H21="✓",B21*$C$7,0) -> 0
A22: Renewal Conversion Rate | B22: 0.4 | C22: ≥65% each mo | G22: =IF(COUNTA(D22:F22)=0,"",AVERAGE(D22:F22)) | H22: =IF(COUNTA(D22:F22)=0,"—",IF(MIN(D22:F22)>=0.65,"✓","✗")) -> — | I22: =IF(H22="✓",B22*$C$7,0) -> 0
B23: =SUM(B21:B22) -> 1 | H23: Total Payout → | I23: =SUM(I21:I22) -> 0
A25: NYLSA — District Manager | G25: Pool: $7,000
A26: Metric | B26: Weight | C26: Base Target | D26: July | E26: August | F26: September | G26: Q3 Result | H26: Base Met? | I26: Payout
A27: Expense Management — Above & Below the Line | B27: 0.6 | C27: ≤100% of budget | G27: =IF(COUNTA(D27:F27)=0,"",AVERAGE(D27:F27)) | H27: =IF(G27="","—",IF(G27<=1,"✓","✗")) -> — | I27: =IF(H27="✓",B27*$C$8,0) -> 0
A28: Delinquency Compression | B28: 0.4 | C28: Avg < $75K | G28: =IF(COUNTA(D28:F28)=0,"",AVERAGE(D28:F28)) | H28: =IF(G28="","—",IF(G28<75000,"✓","✗")) -> — | I28: =IF(H28="✓",B28*$C$8,0) -> 0
B29: =SUM(B27:B28) -> 1 | H29: Total Payout → | I29: =SUM(I27:I28) -> 0
A31: AVERY — Sr. Account Manager | G31: Pool: $5,000
A32: Metric | B32: Weight | C32: Base Target | D32: July | E32: August | F32: September | G32: Q3 Result | H32: Base Met? | I32: Payout
A33: Eviction Filing Accuracy | B33: 0.6 | C33: ≥90% | G33: =IF(COUNTA(D33:F33)=0,"",AVERAGE(D33:F33)) | H33: =IF(G33="","—",IF(G33>=0.9,"✓","✗")) -> — | I33: =IF(H33="✓",B33*$C$9,0) -> 0
A34: LeaseLock Claims Recovery | B34: 0.4 | C34: 100% filed + >60% | G34: =IF(COUNTA(D34:F34)=0,"",AVERAGE(D34:F34)) | H34: =IF(G34="","—",IF(G34>0.6,"✓","✗")) -> — | I34: =IF(H34="✓",B34*$C$9,0) -> 0
B35: =SUM(B33:B34) -> 1 | H35: Total Payout → | I35: =SUM(I33:I34) -> 0
A37: JUSTIN — Leasing Administrative Manager | G37: Pool: $5,000
A38: Metric | B38: Weight | C38: Base Target | D38: July | E38: August | F38: September | G38: Q3 Result | H38: Base Met? | I38: Payout
A39: Net Lease Generation | B39: 0.6 | C39: ≥52 avg/mo | G39: =IF(COUNTA(D39:F39)=0,"",AVERAGE(D39:F39)) | H39: =IF(G39="","—",IF(G39>=60,"✓","✗")) -> — | I39: =IF(H39="✓",B39*$C$10,0) -> 0
A40: Quality Screenings | B40: 0.4 | C40: <5 evictions avg/mo | G40: =IF(COUNTA(D40:F40)=0,"",AVERAGE(D40:F40)) | H40: =IF(G40="","—",IF(G40<5,"✓","✗")) -> — | I40: =IF(H40="✓",B40*$C$10,0) -> 0
B41: =SUM(B39:B40) -> 1 | H41: Total Payout → | I41: =SUM(I39:I40) -> 0
A43: PAYOUT MECHANICS & GOVERNANCE
A44: Weighted Payout: Each metric earns its weighted share of the participant's total pool independently. No all-or-nothing gate — missing one metric does not forfeit the other.
A45: No Outperform Bonus: There is no outperform tier. Hit the base target → earn that metric's weighted share. Miss → $0 on that metric.
A46: Blue cells (Jul/Aug/Sep and Q3 Result columns) are input placeholders. Enter actuals from Entrata and base reports as the quarter progresses.
A47: Mid-Quarter Check-In: ~August 15, 2026 (coaching checkpoint only, no payments). Final measurement: September 30, 2026.
A48: Data Sources: Entrata (system of record), RSI, Nationwide, Arlast Capital weekly metrics workbook, CAF V2 budget. Entrata governs in case of discrepancy.
A49: Pending Confirmation: Yellow-highlighted targets (Nylsa KPI #1 & #2, Avery KPI #1 & #2) are awaiting final sign-off from Sergio per the Q3 incentive memo.

Sheet Dashboard_1
B1: AVA APARTMENTS
B2: Weekly Performance Dashboard
B3: Reporting Week: | C3: 32 | D3: ← Enter week # (1-24) | F3: =IFERROR(VLOOKUP(C3,Targets!A:B,2,FALSE()),"") -> 46244
B5: KPI | C5: Target | D5: Actual | E5: Var | F5: Prior Wk | G5: WoW Δ | H5: Status
B6: OCCUPANCY
B7: Occupancy % | C7: =IFERROR(INDEX(Targets!$A$5:$O$100,$C$3,3),"—") -> 0.73522727 | D7: {=IFERROR(INDEX(Data_2!$D$6:$CW$6,1,$C$3+2),"")} -> 0.73509174 | E7: =IFERROR(D7-C7,"—") -> -0.00013552961 | F7: {=IFERROR(INDEX(Data_2!$D$6:$CW$6,1,$C$3+1),"")} -> 0.73165138 | G7: =IFERROR(D7-F7,"—") -> 0.003440367 | H7: =IF(AND(ISNUMBER(D7),ISNUMBER(C7)),IF(D7>=C7,"✓","✗"),"") -> ✗
B8: Occupied Units | C8: =IFERROR(INDEX(Targets!$A$5:C:C,$C$3,4),"—") -> — | D8: {=IFERROR(INDEX(Data_2!$D$7:$CW$7,1,$C$3+2),"")} -> 641 | E8: =IFERROR(D8-C8,"—") -> — | F8: {=IFERROR(INDEX(Data_2!$D$7:$CW$7,1,$C$3+1),"")} -> 638 | G8: =IFERROR(D8-F8,"—") -> 3 | H8: =IF(AND(ISNUMBER(D8),ISNUMBER(C8)),IF(D8>=C8,"✓","✗"),"")
B9: Exposure % | C9: — | D9: {=IFERROR(INDEX(Data_2!$D$13:$CW$13,1,$C$3+2),"")} -> 0.24885321 | E9: — | F9: {=IFERROR(INDEX(Data_2!$D$13:$CW$13,1,$C$3+1),"")} -> 0.24655963 | G9: =IFERROR(D9-F9,"—") -> 0.002293578
B10: Move Outs (weekly) | C10: =IFERROR(IF(_xlfn.SINGLE(INDEX(Targets!$A$5:$W$100,$C$3,11))=0,"—",_xlfn.SINGLE(INDEX(Targets!$A$5:$W$100,$C$3,11))),"—") -> 7 | D10: {=IFERROR(INDEX(Data_2!$D$93:$CW$93,1,$C$3+2),"")} -> 5 | E10: =IF(OR(C10="—",NOT(ISNUMBER(C10))),"—",IFERROR(C10-D10,"—")) -> 2 | F10: {=IF($C$3>1,IFERROR(INDEX(Data_2!$D$93:$CW$93,1,$C$3+1),""),"")} -> 11 | G10: =IFERROR(F10-D10,"—") -> 6 | H10: =IF(AND(ISNUMBER(D10),ISNUMBER(C10)),IF(D10<=C10,"✓","✗"),"") -> ✓
B11: LEASING FUNNEL
B12: New Prospects | C12: =IFERROR(INDEX(Targets!$A$5:$O$100,$C$3,5),"—") -> 156 | D12: {=IFERROR(INDEX(Data_2!$D$15:$CW$15,1,$C$3+2),"")} -> 189 | E12: =IFERROR(D12-C12,"—") -> 33 | F12: {=IFERROR(INDEX(Data_2!$D$15:$CW$15,1,$C$3+1),"")} -> 200 | G12: =IFERROR(D12-F12,"—") -> -11 | H12: =IF(AND(ISNUMBER(D12),ISNUMBER(C12)),IF(D12>=C12,"✓","✗"),"") -> ✓
B13: Tours | C13: =IFERROR(INDEX(Targets!$A$5:$O$100,$C$3,6),"—") -> 39 | D13: {=IFERROR(INDEX(Data_2!$D$16:$CW$16,1,$C$3+2),"")} -> 29 | E13: =IFERROR(D13-C13,"—") -> -10 | F13: {=IFERROR(INDEX(Data_2!$D$16:$CW$16,1,$C$3+1),"")} -> 28 | G13: =IFERROR(D13-F13,"—") -> 1 | H13: =IF(AND(ISNUMBER(D13),ISNUMBER(C13)),IF(D13>=C13,"✓","✗"),"") -> ✗
B14: Submitted Apps | C14: =IFERROR(INDEX(Targets!$A$5:$O$100,$C$3,7),"—") -> 24 | D14: {=IFERROR(INDEX(Data_2!$D$18:$CW$18,1,$C$3+2),"")} -> 17 | E14: =IFERROR(D14-C14,"—") -> -7 | F14: {=IFERROR(INDEX(Data_2!$D$18:$CW$18,1,$C$3+1),"")} -> 23 | G14: =IFERROR(D14-F14,"—") -> -6 | H14: =IF(AND(ISNUMBER(D14),ISNUMBER(C14)),IF(D14>=C14,"✓","✗"),"") -> ✗
B15: Net Apps | C15: =IFERROR(INDEX(Targets!$A$5:$O$100,$C$3,8),"—") -> 16 | D15: {=IFERROR(INDEX(Data_2!$D$23:$CW$23,1,$C$3+2),"")} -> 5 | E15: =IFERROR(D15-C15,"—") -> -11 | F15: {=IFERROR(INDEX(Data_2!$D$23:$CW$23,1,$C$3+1),"")} -> 13 | G15: =IFERROR(D15-F15,"—") -> -8 | H15: =IF(AND(ISNUMBER(D15),ISNUMBER(C15)),IF(D15>=C15,"✓","✗"),"") -> ✗
B16: Net Leases | C16: =IFERROR(INDEX(Targets!$A$5:$O$100,$C$3,9),"—") -> 14 | D16: {=IFERROR(INDEX(Data_2!$D$26:$CW$26,1,$C$3+2),"")} -> 3 | E16: =IFERROR(D16-C16,"—") -> -11 | F16: {=IFERROR(INDEX(Data_2!$D$26:$CW$26,1,$C$3+1),"")} -> 15 | G16: =IFERROR(D16-F16,"—") -> -12 | H16: =IF(AND(ISNUMBER(D16),ISNUMBER(C16)),IF(D16>=C16,"✓","✗"),"") -> ✗
B17: APP PIPELINE
B18: Total Apps in Pipeline | C18: =IFERROR(IF(_xlfn.SINGLE(INDEX(Targets!$A$5:$W$28,$C$3,16))=0,"—",_xlfn.SINGLE(INDEX(Targets!$A$5:$W$28,$C$3,16))),"—") -> — | D18: {=IFERROR(INDEX(Data_2!$D$28:$CW$28,1,$C$3+2),"")} -> 219 | E18: =IF(OR(C18="—",NOT(ISNUMBER(C18))),"—",IFERROR(C18-D18,"—")) -> — | F18: {=IF($C$3>1,IFERROR(INDEX(Data_2!$D$28:$CW$28,1,$C$3+1),""),"")} -> 219 | G18: =IFERROR(F18-D18,"—") -> 0 | H18: =IF(AND(ISNUMBER(D18),ISNUMBER(C18)),IF(D18<=C18,"✓","✗"),"")
B19: Still Actively Open | C19: =IFERROR(IF(_xlfn.SINGLE(INDEX(Targets!$A$5:$W$28,$C$3,17))=0,"—",_xlfn.SINGLE(INDEX(Targets!$A$5:$W$28,$C$3,17))),"—") -> — | D19: {=IFERROR(INDEX(Data_2!$D$29:$CW$29,1,$C$3+2),"")} -> 48 | E19: =IF(OR(C19="—",NOT(ISNUMBER(C19))),"—",IFERROR(C19-D19,"—")) -> — | F19: {=IF($C$3>1,IFERROR(INDEX(Data_2!$D$29:$CW$29,1,$C$3+1),""),"")} -> 48 | G19: =IFERROR(F19-D19,"—") -> 0 | H19: =IF(AND(ISNUMBER(D19),ISNUMBER(C19)),IF(D19<=C19,"✓","✗"),"")
B20: Converted to Lease | C20: =C16 -> 14 | D20: {=IFERROR(INDEX(Data_2!$D$31:$CW$31,1,$C$3+2),"")} -> 3 | E20: =IF(OR(C20="—",NOT(ISNUMBER(C20))),"—",IFERROR(D20-C20,"—")) -> -11 | F20: {=IF($C$3>1,IFERROR(INDEX(Data_2!$D$31:$CW$31,1,$C$3+1),""),"")} -> 15 | G20: =IFERROR(D20-F20,"—") -> -12 | H20: =IF(AND(ISNUMBER(D20),ISNUMBER(C20)),IF(D20>=C20,"✓","✗"),"") -> ✗
B21: Cancelled / Denied | C21: =IFERROR(IF(_xlfn.SINGLE(INDEX(Targets!$A$5:$W$28,$C$3,19))=0,"—",_xlfn.SINGLE(INDEX(Targets!$A$5:$W$28,$C$3,19))),"—") -> — | D21: {=IFERROR(INDEX(Data_2!$D$32:$CW$32,1,$C$3+2),"")} -> 62 | E21: =IF(OR(C21="—",NOT(ISNUMBER(C21))),"—",IFERROR(C21-D21,"—")) -> — | F21: {=IF($C$3>1,IFERROR(INDEX(Data_2!$D$32:$CW$32,1,$C$3+1),""),"")} -> 62 | G21: =IFERROR(F21-D21,"—") -> 0 | H21: =IF(AND(ISNUMBER(D21),ISNUMBER(C21)),IF(D21<=C21,"✓","✗"),"")
B22: Conversion Rate | C22: =IFERROR(IF(_xlfn.SINGLE(INDEX(Targets!$A$5:$W$100,$C$3,20))=0,"—",_xlfn.SINGLE(INDEX(Targets!$A$5:$W$100,$C$3,20))),"—") -> 0.24615385 | D22: {=IFERROR(INDEX(Data_2!$D$33:$CW$33,1,$C$3+2),"")} -> 0.01369863 | E22: =IF(OR(C22="—",NOT(ISNUMBER(C22))),"—",IFERROR(D22-C22,"—")) -> -0.23245522 | F22: {=IF($C$3>1,IFERROR(INDEX(Data_2!$D$33:$CW$33,1,$C$3+1),""),"")} -> 0.068493151 | G22: =IFERROR(D22-F22,"—") -> -0.054794521 | H22: =IF(AND(ISNUMBER(D22),ISNUMBER(C22)),IF(D22>=C22,"✓","✗"),"") -> ✗
B23: Loss Rate | C23: =IFERROR(IF(_xlfn.SINGLE(INDEX(Targets!$A$5:$W$28,$C$3,21))=0,"—",_xlfn.SINGLE(INDEX(Targets!$A$5:$W$28,$C$3,21))),"—") -> — | D23: {=IFERROR(INDEX(Data_2!$D$34:$CW$34,1,$C$3+2),"")} -> 0.28310502 | E23: =IF(OR(C23="—",NOT(ISNUMBER(C23))),"—",IFERROR(C23-D23,"—")) -> — | F23: {=IF($C$3>1,IFERROR(INDEX(Data_2!$D$34:$CW$34,1,$C$3+1),""),"")} -> 0.28310502 | G23: =IFERROR(F23-D23,"—") -> 0 | H23: =IF(AND(ISNUMBER(D23),ISNUMBER(C23)),IF(D23<=C23,"✓","✗"),"")
B24: Apps 15+ Days Old | C24: =IFERROR(IF(_xlfn.SINGLE(INDEX(Targets!$A$5:$W$100,$C$3,22))=0,"—",_xlfn.SINGLE(INDEX(Targets!$A$5:$W$100,$C$3,22))),"—") -> 5 | D24: {=IFERROR(INDEX(Data_2!$D$35:$CW$35,1,$C$3+2),"")} -> 48 | E24: =IF(OR(C24="—",NOT(ISNUMBER(C24))),"—",IFERROR(C24-D24,"—")) -> -43 | F24: {=IF($C$3>1,IFERROR(INDEX(Data_2!$D$35:$CW$35,1,$C$3+1),""),"")} -> 48 | G24: =IFERROR(F24-D24,"—") -> 0 | H24: =IF(AND(ISNUMBER(D24),ISNUMBER(C24)),IF(D24<=C24,"✓","✗"),"") -> ✗
B25: Avg Days to Decision | C25: =IFERROR(IF(_xlfn.SINGLE(INDEX(Targets!$A$5:$W$28,$C$3,23))=0,"—",_xlfn.SINGLE(INDEX(Targets!$A$5:$W$28,$C$3,23))),"—") -> — | D25: {=IFERROR(INDEX(Data_2!$D$36:$CW$36,1,$C$3+2),"")} -> 10.4 | E25: =IF(OR(C25="—",NOT(ISNUMBER(C25))),"—",IFERROR(C25-D25,"—")) -> — | F25: {=IF($C$3>1,IFERROR(INDEX(Data_2!$D$36:$CW$36,1,$C$3+1),""),"")} -> 10.4 | G25: =IFERROR(F25-D25,"—") -> 0 | H25: =IF(AND(ISNUMBER(D25),ISNUMBER(C25)),IF(D25<=C25,"✓","✗"),"")
B26: RENEWALS & RETENTION
B27: July
B28: Expirations | C28: — | D28: {=IFERROR(INDEX(Data_2!$D$62:$CW$62,1,$C$3+2),"")} -> 74 | E28: =IF(OR(C28="—",NOT(ISNUMBER(C28))),"—",IFERROR(D28-C28,"—")) -> — | F28: {=IF($C$3>1,IFERROR(INDEX(Data_2!$D$62:$CW$62,1,$C$3+1),""),"")} -> 74 | G28: =IFERROR(D28-F28,"—") -> 0
B29: Non-Renewals | C29: =IFERROR(INDEX(Targets!$A$5:$R$28,$C$3,11),"—") -> — | D29: {=IFERROR(INDEX(Data_2!$D$63:$CW$63,1,$C$3+2),"")} -> 17 | E29: =IF(OR(C29="—",NOT(ISNUMBER(C29))),"—",IFERROR(D29-C29,"—")) -> — | F29: {=IF($C$3>1,IFERROR(INDEX(Data_2!$D$63:$CW$63,1,$C$3+1),""),"")} -> 17 | G29: =IFERROR(D29-F29,"—") -> 0
B30: Skips (Evictions) | C30: — | D30: {=IFERROR(INDEX(Data_2!$D$66:$CW$66,1,$C$3+2),"")} -> 0 | E30: — | F30: {=IF($C$3>1,IFERROR(INDEX(Data_2!$D$66:$CW$66,1,$C$3+1),""),"")} -> 0 | G30: — | H30: —
B31: NTV | C31: — | D31: {=IFERROR(INDEX(Data_2!$D$64:$CW$64,1,$C$3+2),"")} -> 16 | E31: =IF(OR(C31="—",NOT(ISNUMBER(C31))),"—",IFERROR(D31-C31,"—")) -> — | F31: {=IF($C$3>1,IFERROR(INDEX(Data_2!$D$64:$CW$64,1,$C$3+1),""),"")} -> 16 | G31: =IFERROR(D31-F31,"—") -> 0 | H31: —
B32: Pending Renewals | C32: — | D32: =IFERROR(INDEX('Resident Retention -12 months'!$I$2:$I$16,MATCH(Data_2!$A$62,'Resident Retention -12 months'!$B$2:$B$16,0)),"") -> 6 | E32: — | F32: — | G32: — | H32: —
B33: Renewal % | C33: =IFERROR(INDEX(Targets!$A$5:$W$100,$C$3,10),"—") -> 0.65 | D33: {=IFERROR(INDEX(Data_2!$D$65:$CW$65,1,$C$3+2),"")} -> 0.47297297 | E33: =IFERROR(D33-C33,"—") -> -0.17702703 | F33: {=IF($C$3>1,IFERROR(INDEX(Data_2!$D$65:$CW$65,1,$C$3+1),""),"")} -> 0.47297297 | G33: =IFERROR(D33-F33,"—") -> 0 | H33: =IF(AND(ISNUMBER(D33),ISNUMBER(C33)),IF(D33>=C33,"✓","✗"),"") -> ✗
B34: Max Renewal % Possible | C34: — | D34: {=IFERROR(INDEX(Data_2!$D$67:$CW$67,1,$C$3+2),"")} -> 0.55405405 | E34: — | F34: {=IF($C$3>1,IFERROR(INDEX(Data_2!$D$67:$CW$67,1,$C$3+1),""),"")} -> 0.55405405 | G34: — | H34: —
B35: August
B36: Expirations | C36: — | D36: {=IFERROR(INDEX(Data_2!$D$69:$CW$69,1,$C$3+2),"")} -> 51 | E36: =IF(OR(C36="—",NOT(ISNUMBER(C36))),"—",IFERROR(D36-C36,"—")) -> — | F36: {=IF($C$3>1,IFERROR(INDEX(Data_2!$D$69:$CW$69,1,$C$3+1),""),"")} -> 51 | G36: =IFERROR(D36-F36,"—") -> 0
B37: Non-Renewals | C37: =IFERROR(INDEX(Targets!$A$5:$R$28,$C$3,11),"—") -> — | D37: {=IFERROR(INDEX(Data_2!$D$70:$CW$70,1,$C$3+2),"")} -> 8 | E37: =IF(OR(C37="—",NOT(ISNUMBER(C37))),"—",IFERROR(D37-C37,"—")) -> — | F37: {=IF($C$3>1,IFERROR(INDEX(Data_2!$D$70:$CW$70,1,$C$3+1),""),"")} -> 8 | G37: =IFERROR(D37-F37,"—") -> 0
B38: Skips (Evictions) | C38: — | D38: {=IFERROR(INDEX(Data_2!$D$73:$CW$73,1,$C$3+2),"")} -> 0 | E38: — | F38: {=IF($C$3>1,IFERROR(INDEX(Data_2!$D$73:$CW$73,1,$C$3+1),""),"")} -> 0 | G38: — | H38: —
B39: NTV | C39: — | D39: {=IFERROR(INDEX(Data_2!$D$71:$CW$71,1,$C$3+2),"")} -> 12 | E39: =IF(OR(C39="—",NOT(ISNUMBER(C39))),"—",IFERROR(D39-C39,"—")) -> — | F39: {=IF($C$3>1,IFERROR(INDEX(Data_2!$D$71:$CW$71,1,$C$3+1),""),"")} -> 12 | G39: =IFERROR(D39-F39,"—") -> 0 | H39: —
B40: Pending Renewals | C40: — | D40: =IFERROR(INDEX('Resident Retention -12 months'!$I$2:$I$16,MATCH(Data_2!$A$69,'Resident Retention -12 months'!$B$2:$B$16,0)),"") -> 0 | E40: — | F40: — | G40: — | H40: —
B41: Renewal % | C41: =IFERROR(INDEX(Targets!$A$5:$W$100,$C$3,10),"—") -> 0.65 | D41: {=IFERROR(INDEX(Data_2!$D$72:$CW$72,1,$C$3+2),"")} -> 0.60784314 | E41: =IFERROR(D41-C41,"—") -> -0.042156863 | F41: {=IF($C$3>1,IFERROR(INDEX(Data_2!$D$72:$CW$72,1,$C$3+1),""),"")} -> 0.60784314 | G41: =IFERROR(D41-F41,"—") -> 0 | H41: =IF(AND(ISNUMBER(D41),ISNUMBER(C41)),IF(D41>=C41,"✓","✗"),"") -> ✗
B42: Max Renewal % Possible | C42: — | D42: {=IFERROR(INDEX(Data_2!$D$74:$CW$74,1,$C$3+2),"")} -> 0.60784314 | E42: — | F42: {=IF($C$3>1,IFERROR(INDEX(Data_2!$D$74:$CW$74,1,$C$3+1),""),"")} -> 0.60784314 | G42: — | H42: —
B43: September
B44: Expirations | C44: — | D44: {=IFERROR(INDEX(Data_2!$D$76:$CW$76,1,$C$3+2),"")} -> 53 | E44: =IF(OR(C44="—",NOT(ISNUMBER(C44))),"—",IFERROR(D44-C44,"—")) -> — | F44: {=IF($C$3>1,IFERROR(INDEX(Data_2!$D$76:$CW$76,1,$C$3+1),""),"")} -> 53 | G44: =IFERROR(D44-F44,"—") -> 0
B45: Non-Renewals | C45: =IFERROR(INDEX(Targets!$A$5:$R$28,$C$3,11),"—") -> — | D45: {=IFERROR(INDEX(Data_2!$D$77:$CW$77,1,$C$3+2),"")} -> 9 | E45: =IF(OR(C45="—",NOT(ISNUMBER(C45))),"—",IFERROR(D45-C45,"—")) -> — | F45: {=IF($C$3>1,IFERROR(INDEX(Data_2!$D$77:$CW$77,1,$C$3+1),""),"")} -> 9 | G45: =IFERROR(D45-F45,"—") -> 0
B46: Skips (Evictions) | C46: — | D46: {=IFERROR(INDEX(Data_2!$D$80:$CW$80,1,$C$3+2),"")} -> 0 | E46: — | F46: {=IF($C$3>1,IFERROR(INDEX(Data_2!$D$80:$CW$80,1,$C$3+1),""),"")} -> 0 | G46: — | H46: —
B47: NTV | C47: — | D47: {=IFERROR(INDEX(Data_2!$D$78:$CW$78,1,$C$3+2),"")} -> 14 | E47: =IF(OR(C47="—",NOT(ISNUMBER(C47))),"—",IFERROR(D47-C47,"—")) -> — | F47: {=IF($C$3>1,IFERROR(INDEX(Data_2!$D$78:$CW$78,1,$C$3+1),""),"")} -> 14 | G47: =IFERROR(D47-F47,"—") -> 0 | H47: —
B48: Pending Renewals | C48: — | D48: =IFERROR(INDEX('Resident Retention -12 months'!$I$2:$I$16,MATCH(Data_2!$A$76,'Resident Retention -12 months'!$B$2:$B$16,0)),"") -> 6 | E48: — | F48: — | G48: — | H48: —
B49: Renewal % | C49: =IFERROR(INDEX(Targets!$A$5:$W$100,$C$3,10),"—") -> 0.65 | D49: {=IFERROR(INDEX(Data_2!$D$79:$CW$79,1,$C$3+2),"")} -> 0.45283019 | E49: =IFERROR(D49-C49,"—") -> -0.19716981 | F49: {=IF($C$3>1,IFERROR(INDEX(Data_2!$D$79:$CW$79,1,$C$3+1),""),"")} -> 0.41509434 | G49: =IFERROR(D49-F49,"—") -> 0.037735849 | H49: =IF(AND(ISNUMBER(D49),ISNUMBER(C49)),IF(D49>=C49,"✓","✗"),"") -> ✗
B50: Max Renewal % Possible | C50: — | D50: {=IFERROR(INDEX(Data_2!$D$81:$CW$81,1,$C$3+2),"")} -> 0.56603774 | E50: — | F50: {=IF($C$3>1,IFERROR(INDEX(Data_2!$D$81:$CW$81,1,$C$3+1),""),"")} -> 0.56603774 | G50: — | H50: —
B51: October
B52: Expirations | C52: — | D52: {=IFERROR(INDEX(Data_2!$D$83:$CW$83,1,$C$3+2),"")} -> 39 | E52: =IF(OR(C52="—",NOT(ISNUMBER(C52))),"—",IFERROR(D52-C52,"—")) -> — | F52: {=IF($C$3>1,IF(INDEX(Data_2!$D$83:$CW$83,1,$C$3+1)="","",INDEX(Data_2!$D$83:$CW$83,1,$C$3+1)),"")} -> 39 | G52: =IFERROR(D52-F52,"—") -> 0
B53: Non-Renewals | C53: =IFERROR(INDEX(Targets!$A$5:$R$28,$C$3,11),"—") -> — | D53: {=IFERROR(INDEX(Data_2!$D$84:$CW$84,1,$C$3+2),"")} -> 6 | E53: =IF(OR(C53="—",NOT(ISNUMBER(C53))),"—",IFERROR(D53-C53,"—")) -> — | F53: {=IF($C$3>1,IF(INDEX(Data_2!$D$84:$CW$84,1,$C$3+1)="","",INDEX(Data_2!$D$84:$CW$84,1,$C$3+1)),"")} -> 6 | G53: =IFERROR(D53-F53,"—") -> 0
B54: Skips (Evictions) | C54: — | D54: {=IFERROR(INDEX(Data_2!$D$87:$CW$87,1,$C$3+2),"")} -> 0 | E54: — | F54: {=IF($C$3>1,IF(INDEX(Data_2!$D$87:$CW$87,1,$C$3+1)="","",INDEX(Data_2!$D$87:$CW$87,1,$C$3+1)),"")} -> 0 | G54: — | H54: —
B55: NTV | C55: — | D55: {=IFERROR(INDEX(Data_2!$D$85:$CW$85,1,$C$3+2),"")} -> 3 | E55: =IF(OR(C55="—",NOT(ISNUMBER(C55))),"—",IFERROR(D55-C55,"—")) -> — | F55: {=IF($C$3>1,IF(INDEX(Data_2!$D$85:$CW$85,1,$C$3+1)="","",INDEX(Data_2!$D$85:$CW$85,1,$C$3+1)),"")} -> 1 | G55: =IFERROR(D55-F55,"—") -> 2 | H55: —
B56: Pending Renewals | C56: — | D56: =IFERROR(INDEX('Resident Retention -12 months'!$I$2:$I$16,MATCH(Data_2!$A$83,'Resident Retention -12 months'!$B$2:$B$16,0)),"") -> 15 | E56: — | F56: — | G56: — | H56: —
B57: Renewal % | C57: =IFERROR(INDEX(Targets!$A$5:$W$100,$C$3,10),"—") -> 0.65 | D57: {=IFERROR(INDEX(Data_2!$D$86:$CW$86,1,$C$3+2),"")} -> 0.38461538 | E57: =IFERROR(D57-C57,"—") -> -0.26538462 | F57: {=IF($C$3>1,IF(INDEX(Data_2!$D$86:$CW$86,1,$C$3+1)="","",INDEX(Data_2!$D$86:$CW$86,1,$C$3+1)),"")} -> 0.12820513 | G57: =IFERROR(D57-F57,"—") -> 0.25641026 | H57: =IF(AND(ISNUMBER(D57),ISNUMBER(C57)),IF(D57>=C57,"✓","✗"),"") -> ✗
B58: Max Renewal % Possible | C58: — | D58: {=IFERROR(INDEX(Data_2!$D$88:$CW$88,1,$C$3+2),"")} -> 0.76923077 | E58: — | F58: {=IF($C$3>1,IF(INDEX(Data_2!$D$88:$CW$88,1,$C$3+1)="","",INDEX(Data_2!$D$88:$CW$88,1,$C$3+1)),"")} -> 0.82051282 | G58: — | H58: —
B59: Total MTM Leases | C59: — | D59: {=IFERROR(INDEX(Data_2!$D$90:$CW$90,1,$C$3+2),"")} -> 25 | E59: — | F59: {=IF($C$3>1,IFERROR(INDEX(Data_2!$D$90:$CW$90,1,$C$3+1),""),"")} -> 26 | G59: =IFERROR(D59-F59,"—") -> -1
B60: COLLECTIONS
B61: Gross Charges | C61: =IFERROR(INDEX(Targets!$A$5:$O$100,$C$3,12),"—") -> 873000 | D61: {=IFERROR(INDEX(Data_2!$D$98:$CW$98,1,$C$3+2),"")} -> 761341.09 | E61: =IFERROR(D61-C61,"—") -> -111658.91 | F61: {=IF($C$3>1,IFERROR(INDEX(Data_2!$D$98:$CW$98,1,$C$3+1),""),"")} -> 733729.79 | G61: =IFERROR(D61-F61,"—") -> 27611.3 | H61: =IF(AND(ISNUMBER(D61),ISNUMBER(C61)),IF(D61>=C61,"✓","✗"),"") -> ✗
B62: Credits | C62: — | D62: {=IFERROR(INDEX(Data_2!$D$99:$CW$99,1,$C$3+2),"")} -> -60839.31 | E62: — | F62: {=IF($C$3>1,IFERROR(INDEX(Data_2!$D$99:$CW$99,1,$C$3+1),""),"")} -> -57994.31 | G62: =IFERROR(D62-F62,"—") -> -2845
B63: NSFs | C63: — | D63: {=IFERROR(INDEX(Data_2!$D$100:$CW$100,1,$C$3+2),"")} -> 1281.68 | E63: — | F63: {=IF($C$3>1,IFERROR(INDEX(Data_2!$D$100:$CW$100,1,$C$3+1),""),"")} -> 0 | G63: =IFERROR(D63-F63,"—") -> 1281.68
B64: Net Charges (Gross + Credits) | C64: — | D64: {=IFERROR(INDEX(Data_2!$D$101:$CW$101,1,$C$3+2),"")} -> 700501.78 | E64: — | F64: {=IF($C$3>1,IFERROR(INDEX(Data_2!$D$101:$CW$101,1,$C$3+1),""),"")} -> 675735.48 | G64: =IFERROR(D64-F64,"—") -> 24766.3
B65: Payments Received (net of NSFs) | C65: =IFERROR(INDEX(Targets!$A$5:$O$100,$C$3,13),"—") -> 674000 | D65: {=IFERROR(INDEX(Data_2!$D$102:$CW$102,1,$C$3+2),"")} -> 695906.94 | E65: =IFERROR(D65-C65,"—") -> 21906.94 | F65: {=IF($C$3>1,IFERROR(INDEX(Data_2!$D$102:$CW$102,1,$C$3+1),""),"")} -> 483329.54 | G65: =IFERROR(D65-F65,"—") -> 212577.4 | H65: =IF(AND(ISNUMBER(D65),ISNUMBER(C65)),IF(D65>=C65,"✓","✗"),"") -> ✓
B66: Collection % | C66: =IFERROR(INDEX(Targets!$A$5:$O$100,$C$3,14),"—") -> 0.772 | D66: {=IFERROR(INDEX(Data_2!$D$103:$CW$103,1,$C$3+2),"")} -> 0.99344064 | E66: =IFERROR(D66-C66,"—") -> 0.22144064 | F66: {=IF($C$3>1,IFERROR(INDEX(Data_2!$D$103:$CW$103,1,$C$3+1),""),"")} -> 0.71526441 | G66: =IFERROR(D66-F66,"—") -> 0.27817623 | H66: =IF(AND(ISNUMBER(D66),ISNUMBER(C66)),IF(D66>=C66,"✓","✗"),"") -> ✓
B67: DELINQUENCY
B68: Delinquency Balance | C68: =-IFERROR(INDEX(Targets!$A$5:$O$100,$C$3,15),"—") -> -105000 | D68: {=-IFERROR(INDEX(Data_2!$D$111:$CW$111,1,$C$3+2),"")} -> -121349.65 | E68: =IFERROR(D68-C68,"—") -> -16349.65 | F68: {=IF($C$3>1,IF(INDEX(Data_2!$D$111:$CW$111,1,$C$3+1)="","",-INDEX(Data_2!$D$111:$CW$111,1,$C$3+1)),"")} -> -311122.52 | G68: =IF(OR(F68="",NOT(ISNUMBER(F68))),"—",IFERROR(D68-F68,"—")) -> 189772.87 | H68: =IF(AND(ISNUMBER(D68),ISNUMBER(C68)),IF(D68>=C68,"✓","✗"),"") -> ✗
B69: Avg Days to Collect (prior mo) | C69: =IFERROR(INDEX(Targets!$A$5:$X$100,$C$3,24),"—") -> 10.7 | D69: {=IFERROR(INDEX(Data_2!$D$117:$CW$117,1,$C$3+2),"")} -> 4.0563779 | E69: =IF(OR(D69="—",NOT(ISNUMBER(D69))),"—",C69-D69) -> 6.6436221 | F69: {=IF($C$3>1,IFERROR(INDEX(Data_2!$D$117:$CW$117,1,$C$3+1),""),"")} -> 4.0563779 | G69: =IFERROR(F69-D69,"—") -> 0 | H69: =IF(OR(D69="—",NOT(ISNUMBER(D69))),"—",IF(D69<=C69,"✓","✗")) -> ✓
B70: Avg Days to Collect (trailing 2-mo) | C70: =IFERROR(INDEX(Targets!$A$5:$X$100,$C$3,24),"—") -> 10.7 | D70: {=IFERROR(INDEX(Data_2!$D$118:$CW$118,1,$C$3+2),"")} -> 6.0713717 | E70: =IF(OR(D70="—",NOT(ISNUMBER(D70))),"—",C70-D70) -> 4.6286283 | F70: {=IF($C$3>1,IFERROR(INDEX(Data_2!$D$118:$CW$118,1,$C$3+1),""),"")} -> 6.0713717 | G70: =IFERROR(F70-D70,"—") -> 0 | H70: =IF(OR(D70="—",NOT(ISNUMBER(D70))),"—",IF(D70<=C70,"✓","✗")) -> ✓
B71: Countback DSO (days, MTD) | C71: =IFERROR(ROUND((1-_xlfn.SINGLE(INDEX(Targets!$A$5:$W$100,$C$3,14)))*DAY(EOMONTH(_xlfn.SINGLE(INDEX(Targets!$B$5:$B$100,$C$3)),0)),1),"—") -> 7.1 | D71: {=IFERROR(INDEX(Data_2!$D$115:$CW$115,1,$C$3+2),"")} -> 0.20334001 | E71: =IF(OR(D71="—",NOT(ISNUMBER(D71))),"—",C71-D71) -> 6.89666 | F71: {=IF($C$3>1,IFERROR(INDEX(Data_2!$D$115:$CW$115,1,$C$3+1),""),"")} -> 8.8268033 | G71: =IFERROR(F71-D71,"—") -> 8.6234633 | H71: =IF(OR(D71="—",NOT(ISNUMBER(D71))),"—",IF(D71<=C71,"✓","✗")) -> ✓
B72: WORK ORDERS
B73: WO Opened | C73: — | D73: {=IFERROR(INDEX(Data_2!$D$120:$CW$120,1,$C$3+2),"")} -> 133 | E73: — | F73: {=IF($C$3>1,IFERROR(INDEX(Data_2!$D$120:$CW$120,1,$C$3+1),""),"")} -> 180 | G73: =IFERROR(D73-F73,"—") -> -47
B74: WO Completed | C74: — | D74: {=IFERROR(INDEX(Data_2!$D$121:$CW$121,1,$C$3+2),"")} -> 142 | E74: — | F74: {=IF($C$3>1,IFERROR(INDEX(Data_2!$D$121:$CW$121,1,$C$3+1),""),"")} -> 116 | G74: =IFERROR(D74-F74,"—") -> 26
B75: WO Backlog | C75: — | D75: {=IFERROR(INDEX(Data_2!$D$122:$CW$122,1,$C$3+2),"")} -> 260 | E75: — | F75: {=IF($C$3>1,IFERROR(INDEX(Data_2!$D$122:$CW$122,1,$C$3+1),""),"")} -> 282 | G75: =IFERROR(F75-D75,"—") -> 22
B76: WO Completion % | C76: — | D76: {=IFERROR(INDEX(Data_2!$D$123:$CW$123,1,$C$3+2),"")} -> 1.0676692 | E76: — | F76: {=IF($C$3>1,IFERROR(INDEX(Data_2!$D$123:$CW$123,1,$C$3+1),""),"")} -> 0.64444444 | G76: =IFERROR(D76-F76,"—") -> 0.42322473
B77: PRICING
B78: Avg Asking Rent | C78: — | D78: {=IFERROR(INDEX(Data_2!$D$126:$CW$126,1,$C$3+2),"")} -> 990.86218 | E78: — | F78: {=IF($C$3>1,IFERROR(INDEX(Data_2!$D$126:$CW$126,1,$C$3+1),""),"")} -> 990.86218 | G78: =IFERROR(D78-F78,"—") -> 0
B79: Avg NER | C79: — | D79: {=IFERROR(INDEX(Data_2!$D$127:$CW$127,1,$C$3+2),"")} -> 992.13587 | E79: — | F79: {=IF($C$3>1,IFERROR(INDEX(Data_2!$D$127:$CW$127,1,$C$3+1),""),"")} -> 992.14677 | G79: =IFERROR(D79-F79,"—") -> -0.010905126
B82: STATUS KEY
B83: ✓ On Track
B84: ✗ Off Track
B86: Enter weekly data in Data tab → Dashboard auto-updates

Sheet Data_2
B1: AVA APARTMENTS
B2: Weekly Performance Data
D3: Pre-1 | E3: Pre-2 | F3: Wk1 | G3: Wk2 | H3: Wk3 | I3: Wk4 | J3: Wk5 | K3: Wk6 | L3: Wk7 | M3: Wk8 | N3: Wk9 | O3: Wk10 | P3: Wk11 | Q3: Wk12 | R3: Wk13 | S3: Wk14 | T3: Wk15 | U3: Wk16 | V3: Wk17 | W3: Wk18 | X3: Wk19 | Y3: Wk20 | Z3: Wk21 | AA3: Wk22 | AB3: Wk23 | AC3: Wk24 | AD3: Wk25 | AE3: Wk26 | AF3: Wk27 | AG3: Wk28 | AH3: Wk29 | AI3: Wk30 | AJ3: Wk31 | AK3: Wk32
A4: Section | B4: KPI | C4: Format | D4: 46013 | E4: 46020 | F4: 46027 | G4: 46034 | H4: 46041 | I4: 46048 | J4: 46055 | K4: 46062 | L4: 46069 | M4: 46076 | N4: 46083 | O4: 46090 | P4: 46097 | Q4: 46104 | R4: 46111 | S4: 46118 | T4: 46125 | U4: 46132 | V4: 46139 | W4: 46146 | X4: 46153 | Y4: 46160 | Z4: 46167 | AA4: 46174 | AB4: 46181 | AC4: 46188 | AD4: 46195 | AE4: 46202 | AF4: 46209 | AG4: 46216 | AH4: 46223 | AI4: 46230 | AJ4: 46237 | AK4: 46244
A5: OCCUPANCY
B6: Occupancy % | C6: 0 | D6: 0.7966 | E6: 0.8 | F6: 0.8 | G6: 0.8 | H6: 0.81142857 | I6: 0.77828571 | J6: 0.7783 | K6: 0.76773455 | L6: 0.75629291 | M6: 0.75171625 | N6: 0.74828375 | O6: 0.74141876 | P6: 0.73913043 | Q6: 0.73913043 | R6: 0.74141876 | S6: 0.72883295 | T6: 0.72311213 | U6: 0.7323 | V6: 0.73112128 | W6: 0.73 | X6: 0.72654462 | Y6: 0.72425629 | Z6: 0.73340961 | AA6: 0.73112128 | AB6: 0.72852234 | AC6: 0.72623139 | AD6: 0.72821101 | AE6: 0.72591743 | AF6: 0.71788991 | AG6: 0.72133028 | AH6: 0.7190367 | AI6: 0.72591743 | AJ6: 0.73165138 | AK6: =SUM('Boxscore MMR -Availability'!$M:$M)/(SUM('Boxscore MMR -Availability'!$C:$C)-SUM('Boxscore MMR -Availability'!$F:$F)) -> 0.73509174
B7: Occupied Units | C7: #,##0 | D7: 701 | E7: 701 | F7: 704 | G7: 704 | H7: 710 | I7: 681 | J7: 681 | K7: 671 | L7: 661 | M7: 657 | N7: 654 | O7: 648 | P7: 646 | Q7: 646 | R7: 648 | S7: 637 | T7: 632 | U7: 640 | V7: 639 | W7: 638 | X7: 635 | Y7: 633 | Z7: 641 | AA7: 639 | AB7: 636 | AC7: 634 | AD7: 635 | AE7: 633 | AF7: 626 | AG7: 629 | AH7: 627 | AI7: 633 | AJ7: 638 | AK7: =SUM('Boxscore MMR -Availability'!$M:$M) -> 641
B8: Total Units | C8: #,##0 | D8: 880 | E8: 880 | F8: 880 | G8: 880 | H8: 880 | I8: 880 | J8: 880 | K8: 880 | L8: 880 | M8: 880 | N8: 880 | O8: 880 | P8: 880 | Q8: 880 | R8: 880 | S8: 880 | T8: 880 | U8: 880 | V8: 880 | W8: 880 | X8: 880 | Y8: 880 | Z8: 880 | AA8: 880 | AB8: 880 | AC8: 880 | AD8: 880 | AE8: 880 | AF8: 880 | AG8: 880 | AH8: 880 | AI8: 880 | AJ8: 880 | AK8: 880
A9: E1 | B9: Studio Occ % | C9: 0 | D9: 0.75 | E9: 0.8056 | F9: 0.8056 | G9: 0.80555556 | H9: 0.80555556 | I9: 0.77777778 | J9: 0.7778 | K9: 0.77777778 | L9: 0.77777778 | M9: 0.75 | N9: 0.75 | O9: 0.69444444 | P9: 0.72222222 | Q9: 0.72222222 | R9: 0.69444444 | S9: 0.61111111 | T9: 0.55555556 | U9: 0.5556 | V9: 0.55555556 | W9: 0.5556 | X9: 0.55555556 | Y9: 0.52777778 | Z9: 0.55555556 | AA9: 0.52777778 | AB9: 0.52777778 | AC9: 0.52777778 | AD9: 0.52777778 | AE9: 0.52777778 | AF9: 0.52777778 | AG9: 0.55555556 | AH9: 0.52777778 | AI9: 0.61111111 | AJ9: 0.63888889 | AK9: =SUMIF('Boxscore MMR -Availability'!$A:$M,Data_2!$A9,'Boxscore MMR -Availability'!$M:$M)/(SUMIF('Boxscore MMR -Availability'!$A:$M,Data_2!$A9,'Boxscore MMR -Availability'!$C:$C)-SUMIF('Boxscore MMR -Availability'!$A:$M,Data_2!$A9,'Boxscore MMR -Availability'!$F:$F)) -> 0.66666667
A10: A1, A2, A3, A4, A5, A6, A8S, A9TH, A10, A11 | B10: 1BR Occ % | C10: 0 | D10: 0.8165 | E10: 0.8339 | F10: 0.8339 | G10: 0.84469697 | H10: 0.85199241 | I10: 0.81214421 | J10: 0.8102 | K10: 0.79506641 | L10: 0.78747628 | M10: 0.78557875 | N10: 0.77798861 | O10: 0.77229602 | P10: 0.76280835 | Q10: 0.76091082 | R10: 0.76091082 | S10: 0.74383302 | T10: 0.73624288 | U10: 0.74 | V10: 0.73814042 | W10: 0.7287 | X10: 0.71157495 | Y10: 0.70967742 | Z10: 0.71347249 | AA10: 0.70777989 | AB10: 0.69829222 | AC10: 0.69639469 | AD10: 0.69639469 | AE10: 0.69829222 | AF10: 0.68500949 | AG10: 0.68311195 | AH10: 0.68311195 | AI10: 0.67931689 | AJ10: 0.67931689 | AK10: {=_xlfn.LET( _xlpm.list, TRIM(_xlfn.TEXTSPLIT(Data_2!$A10,",")), SUM(SUMIF('Boxscore MMR -Availability'!$A:$A, _xlpm.list, 'Boxscore MMR -Availability'!$M:$M)) / ( SUM(SUMIF('Boxscore MMR -Availability'!$A:$A, _xlpm.list, 'Boxscore MMR -Availability'!$C:$C)) - SUM(SUMIF('Boxscore MMR -Availability'!$A:$A, _xlpm.list, 'Boxscore MMR -Availability'!$F:$F)) ) )} -> 0.68121442
A11: B1, B2, B3, B4, B5, B6, B7TH, B8 | B11: 2BR Occ % | C11: 0 | D11: 0.7042 | E11: 0.7131 | F11: 0.7131 | G11: 0.71311475 | H11: 0.73333333 | I11: 0.7125 | J11: 0.7167 | K11: 0.71966527 | L11: 0.69456067 | M11: 0.68619247 | N11: 0.69037657 | O11: 0.68200837 | P11: 0.69874477 | Q11: 0.70292887 | R11: 0.71548117 | S11: 0.72384937 | T11: 0.72803347 | U11: 0.7573 | V11: 0.75732218 | W11: 0.7657 | X11: 0.78661088 | Y11: 0.79079498 | Z11: 0.81171548 | AA11: 0.81171548 | AB11: 0.82352941 | AC11: 0.82773109 | AD11: 0.82773109 | AE11: 0.81932773 | AF11: 0.81092437 | AG11: 0.82773109 | AH11: 0.82773109 | AI11: 0.84033613 | AJ11: 0.85294118 | AK11: {=_xlfn.LET( _xlpm.list, TRIM(_xlfn.TEXTSPLIT(Data_2!$A11,",")), SUM(SUMIF('Boxscore MMR -Availability'!$A:$A, _xlpm.list, 'Boxscore MMR -Availability'!$M:$M)) / ( SUM(SUMIF('Boxscore MMR -Availability'!$A:$A, _xlpm.list, 'Boxscore MMR -Availability'!$C:$C)) - SUM(SUMIF('Boxscore MMR -Availability'!$A:$A, _xlpm.list, 'Boxscore MMR -Availability'!$F:$F)) ) )} -> 0.85294118
A12: C1 | B12: 3BR Occ % | C12: 0 | D12: 0.875 | E12: 0.875 | F12: 0.875 | G12: 0.875 | H12: 0.875 | I12: 0.875 | J12: 0.875 | K12: 0.875 | L12: 0.875 | M12: 0.875 | N12: 0.875 | O12: 0.875 | P12: 0.875 | Q12: 0.875 | R12: 0.875 | S12: 0.8125 | T12: 0.8125 | U12: 0.8125 | V12: 0.8125 | W12: 0.875 | X12: 0.875 | Y12: 0.875 | Z12: 0.875 | AA12: 0.875 | AB12: 0.875 | AC12: 0.875 | AD12: 1 | AE12: 0.93333333 | AF12: 0.93333333 | AG12: 0.93333333 | AH12: 0.93333333 | AI12: 1 | AJ12: 1 | AK12: =SUMIF('Boxscore MMR -Availability'!$A:$M,Data_2!$A12,'Boxscore MMR -Availability'!$M:$M)/(SUMIF('Boxscore MMR -Availability'!$A:$M,Data_2!$A12,'Boxscore MMR -Availability'!$C:$C)-SUMIF('Boxscore MMR -Availability'!$A:$M,Data_2!$A12,'Boxscore MMR -Availability'!$F:$F)) -> 0.93333333
B13: Exposure % | C13: 0 | D13: 0.2295 | E13: 0.2205 | F13: 0.2125 | G13: 0.2125 | H13: 0.20571429 | I13: 0.24228571 | J13: 0.232 | K13: 0.21167048 | L13: 0.20480549 | M13: 0.22425629 | N13: 0.24713959 | O13: 0.24942792 | P13: 0.25171625 | Q13: 0.26887872 | R13: 0.26773455 | S13: 0.27688787 | T13: 0.27803204 | U13: 0.2769 | V13: 0.28489703 | W13: 0.286 | X13: 0.29748284 | Y13: 0.30549199 | Z13: 0.29633867 | AA13: 0.29633867 | AB13: 0.30927835 | AC13: 0.32416953 | AD13: 0.31077982 | AE13: 0.29931193 | AF13: 0.29243119 | AG13: 0.26834862 | AH13: 0.26146789 | AI13: 0.25114679 | AJ13: 0.24655963 | AK13: {=_xlfn.LET( _xlpm.num, SUM('Boxscore MMR -Availability'!$G:$G) + SUM('Boxscore MMR -Availability'!$K:$K), _xlpm.den, SUM('Boxscore MMR -Availability'!$C:$C) - SUM('Boxscore MMR -Availability'!$F:$F), _xlpm.num/_xlpm.den )} -> 0.24885321
A14: LEASING
B15: New Prospects | C15: #,##0 | D15: 36 | E15: 86 | F15: 141 | G15: 141 | H15: 88 | I15: 52 | J15: 83 | K15: 140 | L15: 149 | M15: 123 | N15: 103 | O15: 114 | P15: 124 | Q15: 147 | R15: 129 | S15: 119 | T15: 186 | U15: 210 | V15: 246 | W15: 211 | X15: 251 | Y15: 220 | Z15: 244 | AA15: 199 | AB15: 230 | AC15: 235 | AD15: 223 | AE15: 235 | AF15: 185 | AG15: 188 | AH15: 176 | AI15: 222 | AJ15: 200 | AK15: =SUM('Boxscore MMR -Lead Activity'!$B:$B) -> 189
B16: Tours | C16: #,##0 | D16: 13 | E16: 5 | F16: 14 | G16: 14 | H16: 26 | I16: 18 | J16: 10 | K16: 28 | L16: 26 | M16: 28 | N16: 34 | O16: 28 | P16: 39 | Q16: 38 | R16: 24 | S16: 26 | T16: 25 | U16: 19 | V16: 26 | W16: 28 | X16: 38 | Y16: 31 | Z16: 33 | AA16: 18 | AB16: 70 | AC16: 35 | AD16: 33 | AE16: 31 | AF16: 28 | AG16: 38 | AH16: 44 | AI16: 30 | AJ16: 28 | AK16: =SUM('Boxscore MMR -Lead Activity'!$N:$N) -> 29
B17: Tour Conversion % | C17: 0 | D17: =D16/D15 -> 0.36111111 | E17: =E16/E15 -> 0.058139535 | F17: =F16/F15 -> 0.09929078 | G17: 0.09929078 | H17: 0.29545455 | I17: 0.34615385 | J17: 0.1205 | K17: 0.2 | L17: 0.17449664 | M17: 0.22764228 | N17: 0.33009709 | O17: 0.24561404 | P17: 0.31451613 | Q17: 0.2585034 | R17: 0.18604651 | S17: 0.21848739 | T17: 0.1344086 | U17: 0.0905 | V17: 0.10569106 | W17: 0.1327 | X17: 0.15139442 | Y17: 0.14090909 | Z17: 0.1352459 | AA17: 0.090452261 | AB17: 0.30434783 | AC17: 0.14893617 | AD17: 0.14798206 | AE17: 0.13191489 | AF17: 0.15135135 | AG17: 0.20212766 | AH17: 0.25 | AI17: 0.13513514 | AJ17: 0.14 | AK17: =AK16/AK15 -> 0.15343915
B18: Submitted Apps | C18: #,##0 | D18: 3 | E18: 11 | F18: 9 | G18: 9 | H18: 7 | I18: 5 | J18: 12 | K18: 29 | L18: 23 | M18: 16 | N18: 13 | O18: 21 | P18: 26 | Q18: 15 | R18: 23 | S18: 12 | T18: 19 | U18: 13 | V18: 20 | W18: 15 | X18: 2 | Y18: 20 | Z18: 23 | AA18: 21 | AB18: 17 | AC18: 18 | AD18: 19 | AE18: 18 | AF18: 16 | AG18: 27 | AH18: 25 | AI18: 19 | AJ18: 23 | AK18: =SUM('Boxscore MMR- Lead Conversion'!$B:$B) -> 17
B19: Approved Apps | C19: #,##0 | D19: 0 | E19: 0 | F19: 3 | G19: 3 | H19: 5 | I19: 1 | J19: 4 | K19: 2 | L19: 2 | M19: 1 | N19: 6 | O19: 5 | P19: 11 | Q19: 8 | R19: 8 | S19: 8 | T19: 6 | U19: 13 | V19: 7 | W19: 7 | X19: 12 | Y19: 11 | Z19: 12 | AA19: 12 | AB19: 6 | AC19: 16 | AD19: 7 | AE19: 10 | AF19: 12 | AG19: 11 | AH19: 13 | AI19: 13 | AJ19: 15 | AK19: =SUM('Boxscore MMR- Lead Conversion'!$F:$F) -> 5
B20: Pending Apps | C20: #,##0 | D20: 3 | E20: 9 | F20: 5 | G20: 5 | H20: -2 | I20: -2 | J20: 5 | K20: 23 | L20: 11 | M20: -3 | N20: -19 | O20: -6 | P20: 6 | Q20: -13 | R20: 5 | S20: -10 | T20: 4 | U20: -9 | V20: 3 | W20: 4 | X20: -36 | Y20: 0 | Z20: -2 | AA20: 5 | AB20: -4 | AC20: -14 | AD20: 6 | AE20: 0 | AF20: -4 | AG20: 12 | AH20: 2 | AI20: 1 | AJ20: -2 | AK20: =AK18-AK19-AK21-AK22 -> 0
B21: Cancelled Apps | C21: #,##0 | D21: 0 | E21: 0 | F21: 0 | G21: 0 | H21: 2 | I21: 4 | J21: 2 | K21: 2 | L21: 4 | M21: 16 | N21: 21 | O21: 20 | P21: 8 | Q21: 19 | R21: 9 | S21: 14 | T21: 9 | U21: 8 | V21: 8 | W21: 4 | X21: 23 | Y21: 5 | Z21: 8 | AA21: 1 | AB21: 5 | AC21: 6 | AD21: 1 | AE21: 2 | AF21: 4 | AG21: 2 | AH21: 3 | AI21: 1 | AJ21: 0 | AK21: =SUM('Boxscore MMR- Lead Conversion'!$C:$C)+SUM('Boxscore MMR- Lead Conversion'!$G:$G) -> 0
B22: Denied Apps | C22: #,##0 | D22: 0 | E22: 2 | F22: 1 | G22: 1 | H22: 2 | I22: 2 | J22: 1 | K22: 2 | L22: 6 | M22: 2 | N22: 5 | O22: 2 | P22: 1 | Q22: 1 | R22: 1 | S22: 0 | T22: 0 | U22: 1 | V22: 2 | W22: 0 | X22: 3 | Y22: 4 | Z22: 5 | AA22: 3 | AB22: 10 | AC22: 10 | AD22: 5 | AE22: 6 | AF22: 4 | AG22: 2 | AH22: 7 | AI22: 4 | AJ22: 10 | AK22: =SUM('Boxscore MMR- Lead Conversion'!$E:$E) -> 12
B23: Net Apps | C23: #,##0 | D23: =D18-D22-D21 -> 3 | E23: =E18-E22-E21 -> 9 | F23: =F18-F22-F21 -> 8 | G23: 8 | H23: 3 | I23: -1 | J23: 9 | K23: 25 | L23: 13 | M23: -2 | N23: -13 | O23: -1 | P23: 17 | Q23: -5 | R23: 13 | S23: -2 | T23: 10 | U23: 4 | V23: 10 | W23: 11 | X23: -24 | Y23: 11 | Z23: 10 | AA23: 17 | AB23: 2 | AC23: 2 | AD23: 13 | AE23: 10 | AF23: 8 | AG23: 23 | AH23: 15 | AI23: 14 | AJ23: 13 | AK23: =AK18-AK22-AK21 -> 5
B24: App Approval % | C24: 0 | D24: =D23/D18 -> 1 | E24: =E23/E18 -> 0.81818182 | F24: =F23/F18 -> 0.88888889 | G24: 0.88888889 | H24: 0.42857143 | I24: -0.2 | J24: 0.75 | K24: 0.86206897 | L24: 0.56521739 | M24: -0.125 | N24: -1 | O24: -0.047619048 | P24: 0.65384615 | Q24: -0.33333333 | R24: 0.56521739 | S24: -0.16666667 | T24: 0.52631579 | U24: 0.3077 | V24: 0.5 | W24: 0.7333 | X24: -12 | Y24: 0.55 | Z24: 0.43478261 | AA24: 0.80952381 | AB24: 0.11764706 | AC24: 0.11111111 | AD24: 0.68421053 | AE24: 0.55555556 | AF24: 0.5 | AG24: 0.85185185 | AH24: 0.6 | AI24: 0.73684211 | AJ24: 0.56521739 | AK24: =AK23/AK18 -> 0.29411765
B25: New Leases | C25: #,##0 | D25: 0 | E25: 0 | F25: 0 | G25: 3 | H25: 5 | I25: 2 | J25: 5 | K25: 2 | L25: 1 | M25: 1 | N25: 3 | O25: 7 | P25: 11 | Q25: 7 | R25: 8 | S25: 8 | T25: 3 | U25: 14 | V25: 7 | W25: 8 | X25: 14 | Y25: 11 | Z25: 11 | AA25: 12 | AB25: 5 | AC25: 14 | AD25: 7 | AE25: 10 | AF25: 12 | AG25: 11 | AH25: 13 | AI25: 12 | AJ25: 16 | AK25: =SUM('Boxscore MMR- Lead Conversion'!$H:$H) -> 3
B26: Net Leases | C26: #,##0 | D26: 0 | E26: 0 | F26: 0 | G26: 3 | H26: 4 | I26: 2 | J26: 5 | K26: 2 | L26: 1 | M26: 1 | N26: 3 | O26: 7 | P26: 11 | Q26: 7 | R26: 8 | S26: 7 | T26: 3 | U26: 14 | V26: 7 | W26: 7 | X26: 11 | Y26: 11 | Z26: 11 | AA26: 12 | AB26: 5 | AC26: 14 | AD26: 7 | AE26: 9 | AF26: 12 | AG26: 11 | AH26: 12 | AI26: 11 | AJ26: 15 | AK26: =SUM('Boxscore MMR- Lead Conversion'!$H:$H)-SUM('Boxscore MMR- Lead Conversion'!$I:$I) -> 3
A27: APP PIPELINE
B28: Total Apps in Pipeline | C28: #,##0 | N28: 90 | O28: 103 | P28: 113 | Q28: 116 | R28: 126 | S28: 136 | T28: 141 | U28: 145 | V28: 168 | W28: 181 | X28: 190 | Y28: 198 | Z28: 205 | AA28: 219 | AB28: 204 | AC28: 219 | AD28: 219 | AE28: 219 | AF28: 219 | AG28: 219 | AH28: 219 | AI28: 219 | AJ28: 219 | AK28: =App_Pipeline_Intel_4!$C$5 -> 219
B29: Still Actively Open | C29: #,##0 | N29: 59 | O29: 53 | P29: 52 | Q29: 51 | R29: 56 | S29: 34 | T29: 37 | U29: 36 | V29: 46 | W29: 53 | X29: 53 | Y29: 38 | Z29: 42 | AA29: 48 | AB29: 69 | AC29: 48 | AD29: 48 | AE29: 48 | AF29: 48 | AG29: 48 | AH29: 48 | AI29: 48 | AJ29: 48 | AK29: =App_Pipeline_Intel_4!$C$6 -> 48
B31: Converted to Lease | C31: #,##0 | N31: 5 | O31: 7 | P31: 11 | Q31: 7 | R31: 8 | S31: 7 | T31: 3 | U31: 14 | V31: 7 | W31: 7 | X31: 11 | Y31: 11 | Z31: 11 | AA31: 12 | AB31: 5 | AC31: 14 | AD31: 7 | AE31: 9 | AF31: 12 | AG31: 11 | AH31: 12 | AI31: 11 | AJ31: 15 | AK31: =SUM('Boxscore MMR- Lead Conversion'!$H:$H)-SUM('Boxscore MMR- Lead Conversion'!$I:$I) -> 3
B32: Cancelled / Denied | C32: #,##0 | N32: 26 | O32: 38 | P32: 42 | Q32: 40 | R32: 40 | S32: 73 | T32: 75 | U32: 74 | V32: 80 | W32: 72 | X32: 66 | Y32: 72 | Z32: 69 | AA32: 62 | AB32: 44 | AC32: 63 | AD32: 63 | AE32: 63 | AF32: 64 | AG32: 64 | AH32: 62 | AI32: 62 | AJ32: 62 | AK32: =App_Pipeline_Intel_4!$C$7 -> 62
B33: Conversion Rate | C33: 0 | N33: 0.055555556 | O33: 0.067961165 | P33: 0.097345133 | Q33: 0.060344828 | R33: 0.063492063 | S33: 0.051470588 | T33: 0.021276596 | U33: 0.097 | V33: 0.041666667 | W33: 0.039 | X33: 0.057894737 | Y33: 0.055555556 | Z33: 0.053658537 | AA33: 0.054794521 | AB33: 0.024509804 | AC33: 0.063926941 | AD33: 0.03196347 | AE33: 0.04109589 | AF33: 0.054794521 | AG33: 0.050228311 | AH33: 0.054794521 | AI33: 0.050228311 | AJ33: 0.068493151 | AK33: =IFERROR(AK31/AK28,0) -> 0.01369863
B34: Loss Rate | C34: 0 | N34: 0.28888889 | O34: 0.36893204 | P34: 0.37168142 | Q34: 0.34482759 | R34: 0.31746032 | S34: 0.53676471 | T34: 0.53191489 | U34: 0.51 | V34: 0.47619048 | W34: 0.398 | X34: 0.34736842 | Y34: 0.36363636 | Z34: 0.33658537 | AA34: 0.28310502 | AB34: 0.21568627 | AC34: 0.28767123 | AD34: 0.28767123 | AE34: 0.28767123 | AF34: 0.29223744 | AG34: 0.29223744 | AH34: 0.28310502 | AI34: 0.28310502 | AJ34: 0.28310502 | AK34: =IFERROR(AK32/AK28,0) -> 0.28310502
B35: Apps 15+ Days Old | C35: #,##0 | N35: 21 | O35: 25 | P35: 20 | Q35: 25 | R35: 30 | S35: 11 | T35: 13 | U35: 18 | V35: 21 | W35: 22 | X35: 17 | Y35: 13 | Z35: 16 | AA35: 21 | AB35: 58 | AC35: 48 | AD35: 48 | AE35: 48 | AF35: 48 | AG35: 48 | AH35: 48 | AI35: 48 | AJ35: 48 | AK35: =App_Pipeline_Intel_4!$H$7+App_Pipeline_Intel_4!$H$8+App_Pipeline_Intel_4!$H$9 -> 48
B36: Avg Days to Decision | C36: 0 | N36: 11 | O36: 11.9 | P36: 11.2 | Q36: 18.1 | R36: 11.8 | S36: 9.8 | T36: 12.8 | U36: 18.1 | V36: 15.8 | W36: 8.4 | X36: 9.5 | Y36: 10.5 | Z36: 10.2 | AA36: 10.4 | AB36: 9.9 | AC36: 10.4 | AD36: 10.4 | AE36: 10.4 | AF36: 10.4 | AG36: 10.4 | AH36: 10.4 | AI36: 10.4 | AJ36: 10.4 | AK36: =IFERROR(VALUE(LEFT(App_Pipeline_Intel_4!$C$16,FIND(" ",App_Pipeline_Intel_4!$C$16)-1)),0) -> 10.4
A37: RENEWALS - MARCH
A38: 46082 | B38: Expirations | C38: #,##0 | N38: 68 | O38: 65 | P38: 66 | Q38: 66 | R38: 64 | S38: 64 | T38: 58 | U38: 58 | V38: 58 | W38: 58 | X38: 58 | Y38: 58 | Z38: 58 | AA38: 58 | AB38: 58 | AC38: 58 | AD38: 58 | AE38: 58 | AF38: 58 | AG38: 58 | AH38: 58 | AI38: 58 | AJ38: 58 | AK38: =SUMIF('Resident Retention -12 months'!$B:$J,Data_2!$A$38,'Resident Retention -12 months'!$C:$C)-SUMIF('Resident Retention -12 months'!$B:$J,Data_2!$A$38,'Resident Retention -12 months'!$J:$J) -> 58
B39: Early Move Outs | C39: #,##0 | N39: 6 | O39: 6 | P39: 6 | Q39: 6 | R39: 6 | S39: 6 | T39: 6 | U39: 6 | V39: 6 | W39: 6 | X39: 6 | Y39: 6 | Z39: 6 | AA39: 6 | AB39: 6 | AC39: 6 | AD39: 6 | AE39: 6 | AF39: 6 | AG39: 6 | AH39: 6 | AI39: 6 | AJ39: 6 | AK39: =SUMIF('Resident Retention -12 months'!$B:$J,Data_2!$A$38,'Resident Retention -12 months'!$D:$D) -> 6
B40: NTV | C40: #,##0 | N40: 8 | O40: 7 | P40: 9 | Q40: 10 | R40: 11 | S40: 11 | T40: 14 | U40: 14 | V40: 14 | W40: 14 | X40: 14 | Y40: 14 | Z40: 14 | AA40: 14 | AB40: 14 | AC40: 14 | AD40: 14 | AE40: 14 | AF40: 14 | AG40: 14 | AH40: 14 | AI40: 14 | AJ40: 14 | AK40: =SUMIF('Resident Retention -12 months'!$B:$J,Data_2!$A$38,'Resident Retention -12 months'!$E:$E) -> 14
B41: Renewal % | C41: 0 | N41: 0.1746 | O41: 0.18461538 | P41: 0.28787879 | Q41: 0.39393939 | R41: 0.453125 | S41: 0.453125 | T41: 0.65517241 | U41: 0.655 | V41: 0.65517241 | W41: 0.655 | X41: 0.63333333 | Y41: 0.63333333 | Z41: 0.63333333 | AA41: 0.63333333 | AB41: 0.63333333 | AC41: 0.63333333 | AD41: 0.63333333 | AE41: 0.63333333 | AF41: 0.63333333 | AG41: 0.63333333 | AH41: 0.63333333 | AI41: 0.63333333 | AJ41: 0.63333333 | AK41: =(SUMIF('Resident Retention -12 months'!$B:$J,$A$38,'Resident Retention -12 months'!$F:$F)+SUMIF('Resident Retention -12 months'!$B:$J,$A$38,'Resident Retention -12 months'!$H:$H))/AK43 -> 0.63333333
A42: RENEWALS - APRIL
A43: 46113 | B43: Expirations | C43: #,##0 | N43: 62 | O43: 62 | P43: 62 | Q43: 62 | R43: 62 | S43: 62 | T43: 62 | U43: 62 | V43: 60 | W43: 60 | X43: 60 | Y43: 60 | Z43: 60 | AA43: 60 | AB43: 60 | AC43: 60 | AD43: 60 | AE43: 60 | AF43: 60 | AG43: 60 | AH43: 60 | AI43: 60 | AJ43: 60 | AK43: =SUMIF('Resident Retention -12 months'!$B:$J,Data_2!$A$43,'Resident Retention -12 months'!$C:$C)-SUMIF('Resident Retention -12 months'!$B:$J,Data_2!$A$43,'Resident Retention -12 months'!$J:$J) -> 60
B44: Early Move Outs | C44: #,##0 | N44: 3 | O44: 4 | P44: 4 | Q44: 4 | R44: 4 | S44: 4 | T44: 5 | U44: 5 | V44: 6 | W44: 6 | X44: 6 | Y44: 6 | Z44: 6 | AA44: 6 | AB44: 6 | AC44: 6 | AD44: 6 | AE44: 6 | AF44: 6 | AG44: 6 | AH44: 6 | AI44: 6 | AJ44: 6 | AK44: =SUMIF('Resident Retention -12 months'!$B:$J,Data_2!$A$43,'Resident Retention -12 months'!$D:$D) -> 6
B45: NTV | C45: #,##0 | N45: 7 | O45: 7 | P45: 10 | Q45: 10 | R45: 12 | S45: 13 | T45: 15 | U45: 15 | V45: 18 | W45: 18 | X45: 18 | Y45: 18 | Z45: 18 | AA45: 18 | AB45: 18 | AC45: 18 | AD45: 18 | AE45: 18 | AF45: 18 | AG45: 18 | AH45: 18 | AI45: 18 | AJ45: 18 | AK45: =SUMIF('Resident Retention -12 months'!$B:$J,Data_2!$A$43,'Resident Retention -12 months'!$E:$E) -> 18
B46: Renewal % | C46: 0 | N46: 0.0678 | O46: 0.096774194 | P46: 0.24193548 | Q46: 0.25806452 | R46: 0.29032258 | S46: 0.38709677 | T46: 0.40322581 | U46: 0.403 | V46: 0.48333333 | W46: 0.517 | X46: 0.54385965 | Y46: 0.54385965 | Z46: 0.55357143 | AA46: 0.55357143 | AB46: 0.55357143 | AC46: 0.55357143 | AD46: 0.55357143 | AE46: 0.55357143 | AF46: 0.55357143 | AG46: 0.55357143 | AH46: 0.55357143 | AI46: 0.55357143 | AJ46: 0.55357143 | AK46: =(SUMIF('Resident Retention -12 months'!$B:$J,$A$43,'Resident Retention -12 months'!$F:$F)+SUMIF('Resident Retention -12 months'!$B:$J,$A$43,'Resident Retention -12 months'!$H:$H))/AK48 -> 0.55357143
A47: RENEWALS - MAY
A48: 46143 | B48: Expirations | C48: #,##0 | N48: 55 | O48: 55 | P48: 55 | Q48: 55 | R48: 55 | S48: 55 | T48: 56 | U48: 56 | V48: 56 | W48: 57 | X48: 57 | Y48: 57 | Z48: 56 | AA48: 56 | AB48: 56 | AC48: 56 | AD48: 56 | AE48: 56 | AF48: 56 | AG48: 56 | AH48: 56 | AI48: 56 | AJ48: 56 | AK48: =SUMIF('Resident Retention -12 months'!$B:$J,Data_2!$A$48,'Resident Retention -12 months'!$C:$C)-SUMIF('Resident Retention -12 months'!$B:$J,Data_2!$A$48,'Resident Retention -12 months'!$J:$J) -> 56
B49: Early Move Outs | C49: #,##0 | N49: 4 | O49: 4 | P49: 4 | Q49: 4 | R49: 4 | S49: 6 | T49: 6 | U49: 6 | V49: 6 | W49: 8 | X49: 9 | Y49: 10 | Z49: 10 | AA49: 10 | AB49: 10 | AC49: 10 | AD49: 10 | AE49: 10 | AF49: 10 | AG49: 10 | AH49: 10 | AI49: 10 | AJ49: 10 | AK49: =SUMIF('Resident Retention -12 months'!$B:$J,Data_2!$A$48,'Resident Retention -12 months'!$D:$D) -> 10
B50: NTV | C50: #,##0 | N50: 4 | O50: 4 | P50: 8 | Q50: 9 | R50: 9 | S50: 10 | T50: 11 | U50: 11 | V50: 11 | W50: 9 | X50: 9 | Y50: 9 | Z50: 10 | AA50: 10 | AB50: 10 | AC50: 10 | AD50: 10 | AE50: 10 | AF50: 10 | AG50: 10 | AH50: 10 | AI50: 10 | AJ50: 10 | AK50: =SUMIF('Resident Retention -12 months'!$B:$J,Data_2!$A$48,'Resident Retention -12 months'!$E:$E) -> 10
B51: Renewal % | C51: 0 | N51: 0.0392 | O51: 0.054545455 | P51: 0.10909091 | Q51: 0.18181818 | R51: 0.2 | S51: 0.23636364 | T51: 0.26785714 | U51: 0.304 | V51: 0.33928571 | W51: 0.509 | X51: 0.56363636 | Y51: 0.6 | Z51: 0.64814815 | AA51: 0.64814815 | AB51: 0.64814815 | AC51: 0.64814815 | AD51: 0.625 | AE51: 0.625 | AF51: 0.625 | AG51: 0.625 | AH51: 0.625 | AI51: 0.625 | AJ51: 0.625 | AK51: =IFERROR((SUMIF('Resident Retention -12 months'!$B:$B,$A$48,'Resident Retention -12 months'!$F:$F)+SUMIF('Resident Retention -12 months'!$B:$B,$A$48,'Resident Retention -12 months'!$H:$H))/(SUMIF('Resident Retention -12 months'!$B:$B,$A$48,'Resident Retention -12 months'!$C:$C)-SUMIF('Resident Retention -12 months'!$B:$B,$A$48,'Resident Retention -12 months'!$J:$J)),0) -> 0.625
B52: Skips (Evictions) | C52: #,##0 | D52: {=SUMPRODUCT(((Move_Out_Reasons!H2:H1000="Skipped Without Notice")+(Move_Out_Reasons!H2:H1000="Skipped During Eviction")+(Move_Out_Reasons!H2:H1000="Eviction")+(Move_Out_Reasons!H2:H1000="Failure To Pay"))*(Move_Out_Reasons!F2:F1000>=$A$48)*(Move_Out_Reasons!F2:F1000<=EOMONTH($A$48,0)))} -> 19 | E52: {=SUMPRODUCT(((Move_Out_Reasons!H2:H1000="Skipped Without Notice")+(Move_Out_Reasons!H2:H1000="Skipped During Eviction")+(Move_Out_Reasons!H2:H1000="Eviction")+(Move_Out_Reasons!H2:H1000="Failure To Pay"))*(Move_Out_Reasons!F2:F1000>=$A$48)*(Move_Out_Reasons!F2:F1000<=EOMONTH($A$48,0)))} -> 19 | F52: {=SUMPRODUCT(((Move_Out_Reasons!H2:H1000="Skipped Without Notice")+(Move_Out_Reasons!H2:H1000="Skipped During Eviction")+(Move_Out_Reasons!H2:H1000="Eviction")+(Move_Out_Reasons!H2:H1000="Failure To Pay"))*(Move_Out_Reasons!F2:F1000>=$A$48)*(Move_Out_Reasons!F2:F1000<=EOMONTH($A$48,0)))} -> 19 | G52: {=SUMPRODUCT(((Move_Out_Reasons!H2:H1000="Skipped Without Notice")+(Move_Out_Reasons!H2:H1000="Skipped During Eviction")+(Move_Out_Reasons!H2:H1000="Eviction")+(Move_Out_Reasons!H2:H1000="Failure To Pay"))*(Move_Out_Reasons!F2:F1000>=$A$48)*(Move_Out_Reasons!F2:F1000<=EOMONTH($A$48,0)))} -> 19 | H52: {=SUMPRODUCT(((Move_Out_Reasons!H2:H1000="Skipped Without Notice")+(Move_Out_Reasons!H2:H1000="Skipped During Eviction")+(Move_Out_Reasons!H2:H1000="Eviction")+(Move_Out_Reasons!H2:H1000="Failure To Pay"))*(Move_Out_Reasons!F2:F1000>=$A$48)*(Move_Out_Reasons!F2:F1000<=EOMONTH($A$48,0)))} -> 19 | I52: {=SUMPRODUCT(((Move_Out_Reasons!H2:H1000="Skipped Without Notice")+(Move_Out_Reasons!H2:H1000="Skipped During Eviction")+(Move_Out_Reasons!H2:H1000="Eviction")+(Move_Out_Reasons!H2:H1000="Failure To Pay"))*(Move_Out_Reasons!F2:F1000>=$A$48)*(Move_Out_Reasons!F2:F1000<=EOMONTH($A$48,0)))} -> 19 | J52: {=SUMPRODUCT(((Move_Out_Reasons!H2:H1000="Skipped Without Notice")+(Move_Out_Reasons!H2:H1000="Skipped During Eviction")+(Move_Out_Reasons!H2:H1000="Eviction")+(Move_Out_Reasons!H2:H1000="Failure To Pay"))*(Move_Out_Reasons!F2:F1000>=$A$48)*(Move_Out_Reasons!F2:F1000<=EOMONTH($A$48,0)))} -> 19 | K52: {=SUMPRODUCT(((Move_Out_Reasons!H2:H1000="Skipped Without Notice")+(Move_Out_Reasons!H2:H1000="Skipped During Eviction")+(Move_Out_Reasons!H2:H1000="Eviction")+(Move_Out_Reasons!H2:H1000="Failure To Pay"))*(Move_Out_Reasons!F2:F1000>=$A$48)*(Move_Out_Reasons!F2:F1000<=EOMONTH($A$48,0)))} -> 19 | L52: {=SUMPRODUCT(((Move_Out_Reasons!H2:H1000="Skipped Without Notice")+(Move_Out_Reasons!H2:H1000="Skipped During Eviction")+(Move_Out_Reasons!H2:H1000="Eviction")+(Move_Out_Reasons!H2:H1000="Failure To Pay"))*(Move_Out_Reasons!F2:F1000>=$A$48)*(Move_Out_Reasons!F2:F1000<=EOMONTH($A$48,0)))} -> 19 | M52: {=SUMPRODUCT(((Move_Out_Reasons!H2:H1000="Skipped Without Notice")+(Move_Out_Reasons!H2:H1000="Skipped During Eviction")+(Move_Out_Reasons!H2:H1000="Eviction")+(Move_Out_Reasons!H2:H1000="Failure To Pay"))*(Move_Out_Reasons!F2:F1000>=$A$48)*(Move_Out_Reasons!F2:F1000<=EOMONTH($A$48,0)))} -> 19 | N52: {=SUMPRODUCT(((Move_Out_Reasons!H2:H1000="Skipped Without Notice")+(Move_Out_Reasons!H2:H1000="Skipped During Eviction")+(Move_Out_Reasons!H2:H1000="Eviction")+(Move_Out_Reasons!H2:H1000="Failure To Pay"))*(Move_Out_Reasons!F2:F1000>=$A$48)*(Move_Out_Reasons!F2:F1000<=EOMONTH($A$48,0)))} -> 19 | O52: {=SUMPRODUCT(((Move_Out_Reasons!H2:H1000="Skipped Without Notice")+(Move_Out_Reasons!H2:H1000="Skipped During Eviction")+(Move_Out_Reasons!H2:H1000="Eviction")+(Move_Out_Reasons!H2:H1000="Failure To Pay"))*(Move_Out_Reasons!F2:F1000>=$A$48)*(Move_Out_Reasons!F2:F1000<=EOMONTH($A$48,0)))} -> 19 | P52: {=SUMPRODUCT(((Move_Out_Reasons!H2:H1000="Skipped Without Notice")+(Move_Out_Reasons!H2:H1000="Skipped During Eviction")+(Move_Out_Reasons!H2:H1000="Eviction")+(Move_Out_Reasons!H2:H1000="Failure To Pay"))*(Move_Out_Reasons!F2:F1000>=$A$48)*(Move_Out_Reasons!F2:F1000<=EOMONTH($A$48,0)))} -> 19 | Q52: {=SUMPRODUCT(((Move_Out_Reasons!H2:H1000="Skipped Without Notice")+(Move_Out_Reasons!H2:H1000="Skipped During Eviction")+(Move_Out_Reasons!H2:H1000="Eviction")+(Move_Out_Reasons!H2:H1000="Failure To Pay"))*(Move_Out_Reasons!F2:F1000>=$A$48)*(Move_Out_Reasons!F2:F1000<=EOMONTH($A$48,0)))} -> 19 | R52: {=SUMPRODUCT(((Move_Out_Reasons!H2:H1000="Skipped Without Notice")+(Move_Out_Reasons!H2:H1000="Skipped During Eviction")+(Move_Out_Reasons!H2:H1000="Eviction")+(Move_Out_Reasons!H2:H1000="Failure To Pay"))*(Move_Out_Reasons!F2:F1000>=$A$48)*(Move_Out_Reasons!F2:F1000<=EOMONTH($A$48,0)))} -> 19 | S52: {=SUMPRODUCT(((Move_Out_Reasons!H2:H1000="Skipped Without Notice")+(Move_Out_Reasons!H2:H1000="Skipped During Eviction")+(Move_Out_Reasons!H2:H1000="Eviction")+(Move_Out_Reasons!H2:H1000="Failure To Pay"))*(Move_Out_Reasons!F2:F1000>=$A$48)*(Move_Out_Reasons!F2:F1000<=EOMONTH($A$48,0)))} -> 19 | T52: {=SUMPRODUCT(((Move_Out_Reasons!H2:H1000="Skipped Without Notice")+(Move_Out_Reasons!H2:H1000="Skipped During Eviction")+(Move_Out_Reasons!H2:H1000="Eviction")+(Move_Out_Reasons!H2:H1000="Failure To Pay"))*(Move_Out_Reasons!F2:F1000>=$A$48)*(Move_Out_Reasons!F2:F1000<=EOMONTH($A$48,0)))} -> 19 | U52: {=SUMPRODUCT(((Move_Out_Reasons!H2:H1000="Skipped Without Notice")+(Move_Out_Reasons!H2:H1000="Skipped During Eviction")+(Move_Out_Reasons!H2:H1000="Eviction")+(Move_Out_Reasons!H2:H1000="Failure To Pay"))*(Move_Out_Reasons!F2:F1000>=$A$48)*(Move_Out_Reasons!F2:F1000<=EOMONTH($A$48,0)))} -> 19 | V52: {=SUMPRODUCT(((Move_Out_Reasons!H2:H1000="Skipped Without Notice")+(Move_Out_Reasons!H2:H1000="Skipped During Eviction")+(Move_Out_Reasons!H2:H1000="Eviction")+(Move_Out_Reasons!H2:H1000="Failure To Pay"))*(Move_Out_Reasons!F2:F1000>=$A$48)*(Move_Out_Reasons!F2:F1000<=EOMONTH($A$48,0)))} -> 19 | W52: {=SUMPRODUCT(((Move_Out_Reasons!H2:H1000="Skipped Without Notice")+(Move_Out_Reasons!H2:H1000="Skipped During Eviction")+(Move_Out_Reasons!H2:H1000="Eviction")+(Move_Out_Reasons!H2:H1000="Failure To Pay"))*(Move_Out_Reasons!F2:F1000>=$A$48)*(Move_Out_Reasons!F2:F1000<=EOMONTH($A$48,0)))} -> 19 | X52: {=SUMPRODUCT(((Move_Out_Reasons!H2:H1000="Skipped Without Notice")+(Move_Out_Reasons!H2:H1000="Skipped During Eviction")+(Move_Out_Reasons!H2:H1000="Eviction")+(Move_Out_Reasons!H2:H1000="Failure To Pay"))*(Move_Out_Reasons!F2:F1000>=$A$48)*(Move_Out_Reasons!F2:F1000<=EOMONTH($A$48,0)))} -> 19 | Y52: {=SUMPRODUCT(((Move_Out_Reasons!H2:H1000="Skipped Without Notice")+(Move_Out_Reasons!H2:H1000="Skipped During Eviction")+(Move_Out_Reasons!H2:H1000="Eviction")+(Move_Out_Reasons!H2:H1000="Failure To Pay"))*(Move_Out_Reasons!F2:F1000>=$A$48)*(Move_Out_Reasons!F2:F1000<=EOMONTH($A$48,0)))} -> 19 | Z52: {=SUMPRODUCT(((Move_Out_Reasons!H2:H1000="Skipped Without Notice")+(Move_Out_Reasons!H2:H1000="Skipped During Eviction")+(Move_Out_Reasons!H2:H1000="Eviction")+(Move_Out_Reasons!H2:H1000="Failure To Pay"))*(Move_Out_Reasons!F2:F1000>=$A$48)*(Move_Out_Reasons!F2:F1000<=EOMONTH($A$48,0)))} -> 19 | AA52: {=SUMPRODUCT(((Move_Out_Reasons!H2:H1000="Skipped Without Notice")+(Move_Out_Reasons!H2:H1000="Skipped During Eviction")+(Move_Out_Reasons!H2:H1000="Eviction")+(Move_Out_Reasons!H2:H1000="Failure To Pay"))*(Move_Out_Reasons!F2:F1000>=$A$48)*(Move_Out_Reasons!F2:F1000<=EOMONTH($A$48,0)))} -> 19 | AB52: {=SUMPRODUCT(((Move_Out_Reasons!H2:H1000="Skipped Without Notice")+(Move_Out_Reasons!H2:H1000="Skipped During Eviction")+(Move_Out_Reasons!H2:H1000="Eviction")+(Move_Out_Reasons!H2:H1000="Failure To Pay"))*(Move_Out_Reasons!F2:F1000>=$A$48)*(Move_Out_Reasons!F2:F1000<=EOMONTH($A$48,0)))} -> 19 | AC52: {=SUMPRODUCT(((Move_Out_Reasons!H2:H1000="Skipped Without Notice")+(Move_Out_Reasons!H2:H1000="Skipped During Eviction")+(Move_Out_Reasons!H2:H1000="Eviction")+(Move_Out_Reasons!H2:H1000="Failure To Pay"))*(Move_Out_Reasons!F2:F1000>=$A$48)*(Move_Out_Reasons!F2:F1000<=EOMONTH($A$48,0)))} -> 19 | AD52: 19 | AE52: 19 | AF52: 0 | AG52: 0 | AH52: 0 | AI52: 0 | AJ52: 0 | AK52: {=SUMPRODUCT(((Move_Out_Reasons!N2:N1000="Skipped Without Notice")+(Move_Out_Reasons!N2:N1000="Skipped During Eviction")+(Move_Out_Reasons!N2:N1000="Eviction")+(Move_Out_Reasons!N2:N1000="Failure To Pay"))*(Move_Out_Reasons!L2:L1000>=$A$48)*(Move_Out_Reasons!L2:L1000<=EOMONTH($A$48,0)))} -> 0
B53: Max Renewal % Possible | C53: 0 | D53: =IFERROR((SUMIF('Resident Retention -12 months'!$B:$B,$A$48,'Resident Retention -12 months'!$F:$F)+SUMIF('Resident Retention -12 months'!$B:$B,$A$48,'Resident Retention -12 months'!$H:$H)+SUMIF('Resident Retention -12 months'!$B:$B,$A$48,'Resident Retention -12 months'!$I:$I))/(SUMIF('Resident Retention -12 months'!$B:$B,$A$48,'Resident Retention -12 months'!$C:$C)-SUMIF('Resident Retention -12 months'!$B:$B,$A$48,'Resident Retention -12 months'!$J:$J)),0) -> 0.64285714 | E53: =IFERROR((SUMIF('Resident Retention -12 months'!$B:$B,$A$48,'Resident Retention -12 months'!$F:$F)+SUMIF('Resident Retention -12 months'!$B:$B,$A$48,'Resident Retention -12 months'!$H:$H)+SUMIF('Resident Retention -12 months'!$B:$B,$A$48,'Resident Retention -12 months'!$I:$I))/(SUMIF('Resident Retention -12 months'!$B:$B,$A$48,'Resident Retention -12 months'!$C:$C)-SUMIF('Resident Retention -12 months'!$B:$B,$A$48,'Resident Retention -12 months'!$J:$J)),0) -> 0.64285714 | F53: =IFERROR((SUMIF('Resident Retention -12 months'!$B:$B,$A$48,'Resident Retention -12 months'!$F:$F)+SUMIF('Resident Retention -12 months'!$B:$B,$A$48,'Resident Retention -12 months'!$H:$H)+SUMIF('Resident Retention -12 months'!$B:$B,$A$48,'Resident Retention -12 months'!$I:$I))/(SUMIF('Resident Retention -12 months'!$B:$B,$A$48,'Resident Retention -12 months'!$C:$C)-SUMIF('Resident Retention -12 months'!$B:$B,$A$48,'Resident Retention -12 months'!$J:$J)),0) -> 0.64285714 | G53: =IFERROR((SUMIF('Resident Retention -12 months'!$B:$B,$A$48,'Resident Retention -12 months'!$F:$F)+SUMIF('Resident Retention -12 months'!$B:$B,$A$48,'Resident Retention -12 months'!$H:$H)+SUMIF('Resident Retention -12 months'!$B:$B,$A$48,'Resident Retention -12 months'!$I:$I))/(SUMIF('Resident Retention -12 months'!$B:$B,$A$48,'Resident Retention -12 months'!$C:$C)-SUMIF('Resident Retention -12 months'!$B:$B,$A$48,'Resident Retention -12 months'!$J:$J)),0) -> 0.64285714 | H53: =IFERROR((SUMIF('Resident Retention -12 months'!$B:$B,$A$48,'Resident Retention -12 months'!$F:$F)+SUMIF('Resident Retention -12 months'!$B:$B,$A$48,'Resident Retention -12 months'!$H:$H)+SUMIF('Resident Retention -12 months'!$B:$B,$A$48,'Resident Retention -12 months'!$I:$I))/(SUMIF('Resident Retention -12 months'!$B:$B,$A$48,'Resident Retention -12 months'!$C:$C)-SUMIF('Resident Retention -12 months'!$B:$B,$A$48,'Resident Retention -12 months'!$J:$J)),0) -> 0.64285714 | I53: =IFERROR((SUMIF('Resident Retention -12 months'!$B:$B,$A$48,'Resident Retention -12 months'!$F:$F)+SUMIF('Resident Retention -12 months'!$B:$B,$A$48,'Resident Retention -12 months'!$H:$H)+SUMIF('Resident Retention -12 months'!$B:$B,$A$48,'Resident Retention -12 months'!$I:$I))/(SUMIF('Resident Retention -12 months'!$B:$B,$A$48,'Resident Retention -12 months'!$C:$C)-SUMIF('Resident Retention -12 months'!$B:$B,$A$48,'Resident Retention -12 months'!$J:$J)),0) -> 0.64285714 | J53: =IFERROR((SUMIF('Resident Retention -12 months'!$B:$B,$A$48,'Resident Retention -12 months'!$F:$F)+SUMIF('Resident Retention -12 months'!$B:$B,$A$48,'Resident Retention -12 months'!$H:$H)+SUMIF('Resident Retention -12 months'!$B:$B,$A$48,'Resident Retention -12 months'!$I:$I))/(SUMIF('Resident Retention -12 months'!$B:$B,$A$48,'Resident Retention -12 months'!$C:$C)-SUMIF('Resident Retention -12 months'!$B:$B,$A$48,'Resident Retention -12 months'!$J:$J)),0) -> 0.64285714 | K53: =IFERROR((SUMIF('Resident Retention -12 months'!$B:$B,$A$48,'Resident Retention -12 months'!$F:$F)+SUMIF('Resident Retention -12 months'!$B:$B,$A$48,'Resident Retention -12 months'!$H:$H)+SUMIF('Resident Retention -12 months'!$B:$B,$A$48,'Resident Retention -12 months'!$I:$I))/(SUMIF('Resident Retention -12 months'!$B:$B,$A$48,'Resident Retention -12 months'!$C:$C)-SUMIF('Resident Retention -12 months'!$B:$B,$A$48,'Resident Retention -12 months'!$J:$J)),0) -> 0.64285714 | ... AC53: =IFERROR((SUMIF('Resident Retention -12 months'!$B:$B,$A$48,'Resident Retention -12 months'!$F:$F)+SUMIF('Resident Retention -12 months'!$B:$B,$A$48,'Resident Retention -12 months'!$H:$H)+SUMIF('Resident Retention -12 months'!$B:$B,$A$48,'Resident Retention -12 months'!$I:$I))/(SUMIF('Resident Retention -12 months'!$B:$B,$A$48,'Resident Retention -12 months'!$C:$C)-SUMIF('Resident Retention -12 months'!$B:$B,$A$48,'Resident Retention -12 months'!$J:$J)),0) -> 0.64285714 | AD53: 0.64285714 | AE53: 0.64285714 | AF53: 0.64285714 | AG53: 0.64285714 | AH53: 0.64285714 | AI53: 0.64285714 | AJ53: 0.64285714 | AK53: =IFERROR((SUMIF('Resident Retention -12 months'!$B:$B,$A$48,'Resident Retention -12 months'!$F:$F)+SUMIF('Resident Retention -12 months'!$B:$B,$A$48,'Resident Retention -12 months'!$H:$H)+SUMIF('Resident Retention -12 months'!$B:$B,$A$48,'Resident Retention -12 months'!$I:$I))/(SUMIF('Resident Retention -12 months'!$B:$B,$A$48,'Resident Retention -12 months'!$C:$C)-SUMIF('Resident Retention -12 months'!$B:$B,$A$48,'Resident Retention -12 months'!$J:$J)),0) -> 0.64285714
A54: RENEWALS - JUNE
A55: 46174 | B55: Expirations | C55: #,##0 | S55: 54 | T55: 54 | U55: 54 | V55: 55 | W55: 55 | X55: 55 | Y55: 55 | Z55: 54 | AA55: 54 | AB55: 54 | AC55: 54 | AD55: 54 | AE55: 54 | AF55: 54 | AG55: 54 | AH55: 54 | AI55: 54 | AJ55: 54 | AK55: =SUMIF('Resident Retention -12 months'!$B:$J,Data_2!$A$55,'Resident Retention -12 months'!$C:$C)-SUMIF('Resident Retention -12 months'!$B:$J,Data_2!$A$55,'Resident Retention -12 months'!$J:$J) -> 54
B56: Early Move Outs | C56: #,##0 | S56: 10 | T56: 10 | U56: 10 | V56: 11 | W56: 14 | X56: 14 | Y56: 15 | Z56: 15 | AA56: 17 | AB56: 17 | AC56: 17 | AD56: 17 | AE56: 18 | AF56: 18 | AG56: 18 | AH56: 18 | AI56: 18 | AJ56: 18 | AK56: =SUMIF('Resident Retention -12 months'!$B:$J,Data_2!$A$55,'Resident Retention -12 months'!$D:$D) -> 18
B57: NTV | C57: #,##0 | S57: 1 | T57: 2 | U57: 6 | V57: 7 | W57: 8 | X57: 8 | Y57: 7 | Z57: 9 | AA57: 10 | AB57: 10 | AC57: 10 | AD57: 11 | AE57: 10 | AF57: 10 | AG57: 10 | AH57: 10 | AI57: 10 | AJ57: 10 | AK57: =SUMIF('Resident Retention -12 months'!$B:$J,Data_2!$A$55,'Resident Retention -12 months'!$E:$E) -> 10
B58: Renewal % | C58: 0 | S58: 0.018518519 | T58: 0.074074074 | U58: 0.148 | V58: 0.25454545 | W58: 0.345 | X58: 0.34482759 | Y58: 0.39655172 | Z58: 0.39655172 | AA58: 0.39655172 | AB58: 0.39655172 | AC58: 0.39655172 | AD58: 0.42592593 | AE58: 0.44444444 | AF58: 0.44444444 | AG58: 0.44444444 | AH58: 0.44444444 | AI58: 0.44444444 | AJ58: 0.44444444 | AK58: =IFERROR((SUMIF('Resident Retention -12 months'!$B:$B,$A$55,'Resident Retention -12 months'!$F:$F)+SUMIF('Resident Retention -12 months'!$B:$B,$A$55,'Resident Retention -12 months'!$H:$H))/(SUMIF('Resident Retention -12 months'!$B:$B,$A$55,'Resident Retention -12 months'!$C:$C)-SUMIF('Resident Retention -12 months'!$B:$B,$A$55,'Resident Retention -12 months'!$J:$J)),0) -> 0.44444444
B59: Skips (Evictions) | C59: #,##0 | D59: {=SUMPRODUCT(((Move_Out_Reasons!H2:H1000="Skipped Without Notice")+(Move_Out_Reasons!H2:H1000="Skipped During Eviction")+(Move_Out_Reasons!H2:H1000="Eviction")+(Move_Out_Reasons!H2:H1000="Failure To Pay"))*(Move_Out_Reasons!F2:F1000>=$A$55)*(Move_Out_Reasons!F2:F1000<=EOMONTH($A$55,0)))} -> 8 | E59: {=SUMPRODUCT(((Move_Out_Reasons!H2:H1000="Skipped Without Notice")+(Move_Out_Reasons!H2:H1000="Skipped During Eviction")+(Move_Out_Reasons!H2:H1000="Eviction")+(Move_Out_Reasons!H2:H1000="Failure To Pay"))*(Move_Out_Reasons!F2:F1000>=$A$55)*(Move_Out_Reasons!F2:F1000<=EOMONTH($A$55,0)))} -> 8 | F59: {=SUMPRODUCT(((Move_Out_Reasons!H2:H1000="Skipped Without Notice")+(Move_Out_Reasons!H2:H1000="Skipped During Eviction")+(Move_Out_Reasons!H2:H1000="Eviction")+(Move_Out_Reasons!H2:H1000="Failure To Pay"))*(Move_Out_Reasons!F2:F1000>=$A$55)*(Move_Out_Reasons!F2:F1000<=EOMONTH($A$55,0)))} -> 8 | G59: {=SUMPRODUCT(((Move_Out_Reasons!H2:H1000="Skipped Without Notice")+(Move_Out_Reasons!H2:H1000="Skipped During Eviction")+(Move_Out_Reasons!H2:H1000="Eviction")+(Move_Out_Reasons!H2:H1000="Failure To Pay"))*(Move_Out_Reasons!F2:F1000>=$A$55)*(Move_Out_Reasons!F2:F1000<=EOMONTH($A$55,0)))} -> 8 | H59: {=SUMPRODUCT(((Move_Out_Reasons!H2:H1000="Skipped Without Notice")+(Move_Out_Reasons!H2:H1000="Skipped During Eviction")+(Move_Out_Reasons!H2:H1000="Eviction")+(Move_Out_Reasons!H2:H1000="Failure To Pay"))*(Move_Out_Reasons!F2:F1000>=$A$55)*(Move_Out_Reasons!F2:F1000<=EOMONTH($A$55,0)))} -> 8 | I59: {=SUMPRODUCT(((Move_Out_Reasons!H2:H1000="Skipped Without Notice")+(Move_Out_Reasons!H2:H1000="Skipped During Eviction")+(Move_Out_Reasons!H2:H1000="Eviction")+(Move_Out_Reasons!H2:H1000="Failure To Pay"))*(Move_Out_Reasons!F2:F1000>=$A$55)*(Move_Out_Reasons!F2:F1000<=EOMONTH($A$55,0)))} -> 8 | J59: {=SUMPRODUCT(((Move_Out_Reasons!H2:H1000="Skipped Without Notice")+(Move_Out_Reasons!H2:H1000="Skipped During Eviction")+(Move_Out_Reasons!H2:H1000="Eviction")+(Move_Out_Reasons!H2:H1000="Failure To Pay"))*(Move_Out_Reasons!F2:F1000>=$A$55)*(Move_Out_Reasons!F2:F1000<=EOMONTH($A$55,0)))} -> 8 | K59: {=SUMPRODUCT(((Move_Out_Reasons!H2:H1000="Skipped Without Notice")+(Move_Out_Reasons!H2:H1000="Skipped During Eviction")+(Move_Out_Reasons!H2:H1000="Eviction")+(Move_Out_Reasons!H2:H1000="Failure To Pay"))*(Move_Out_Reasons!F2:F1000>=$A$55)*(Move_Out_Reasons!F2:F1000<=EOMONTH($A$55,0)))} -> 8 | L59: {=SUMPRODUCT(((Move_Out_Reasons!H2:H1000="Skipped Without Notice")+(Move_Out_Reasons!H2:H1000="Skipped During Eviction")+(Move_Out_Reasons!H2:H1000="Eviction")+(Move_Out_Reasons!H2:H1000="Failure To Pay"))*(Move_Out_Reasons!F2:F1000>=$A$55)*(Move_Out_Reasons!F2:F1000<=EOMONTH($A$55,0)))} -> 8 | M59: {=SUMPRODUCT(((Move_Out_Reasons!H2:H1000="Skipped Without Notice")+(Move_Out_Reasons!H2:H1000="Skipped During Eviction")+(Move_Out_Reasons!H2:H1000="Eviction")+(Move_Out_Reasons!H2:H1000="Failure To Pay"))*(Move_Out_Reasons!F2:F1000>=$A$55)*(Move_Out_Reasons!F2:F1000<=EOMONTH($A$55,0)))} -> 8 | N59: {=SUMPRODUCT(((Move_Out_Reasons!H2:H1000="Skipped Without Notice")+(Move_Out_Reasons!H2:H1000="Skipped During Eviction")+(Move_Out_Reasons!H2:H1000="Eviction")+(Move_Out_Reasons!H2:H1000="Failure To Pay"))*(Move_Out_Reasons!F2:F1000>=$A$55)*(Move_Out_Reasons!F2:F1000<=EOMONTH($A$55,0)))} -> 8 | O59: {=SUMPRODUCT(((Move_Out_Reasons!H2:H1000="Skipped Without Notice")+(Move_Out_Reasons!H2:H1000="Skipped During Eviction")+(Move_Out_Reasons!H2:H1000="Eviction")+(Move_Out_Reasons!H2:H1000="Failure To Pay"))*(Move_Out_Reasons!F2:F1000>=$A$55)*(Move_Out_Reasons!F2:F1000<=EOMONTH($A$55,0)))} -> 8 | P59: {=SUMPRODUCT(((Move_Out_Reasons!H2:H1000="Skipped Without Notice")+(Move_Out_Reasons!H2:H1000="Skipped During Eviction")+(Move_Out_Reasons!H2:H1000="Eviction")+(Move_Out_Reasons!H2:H1000="Failure To Pay"))*(Move_Out_Reasons!F2:F1000>=$A$55)*(Move_Out_Reasons!F2:F1000<=EOMONTH($A$55,0)))} -> 8 | Q59: {=SUMPRODUCT(((Move_Out_Reasons!H2:H1000="Skipped Without Notice")+(Move_Out_Reasons!H2:H1000="Skipped During Eviction")+(Move_Out_Reasons!H2:H1000="Eviction")+(Move_Out_Reasons!H2:H1000="Failure To Pay"))*(Move_Out_Reasons!F2:F1000>=$A$55)*(Move_Out_Reasons!F2:F1000<=EOMONTH($A$55,0)))} -> 8 | R59: {=SUMPRODUCT(((Move_Out_Reasons!H2:H1000="Skipped Without Notice")+(Move_Out_Reasons!H2:H1000="Skipped During Eviction")+(Move_Out_Reasons!H2:H1000="Eviction")+(Move_Out_Reasons!H2:H1000="Failure To Pay"))*(Move_Out_Reasons!F2:F1000>=$A$55)*(Move_Out_Reasons!F2:F1000<=EOMONTH($A$55,0)))} -> 8 | S59: {=SUMPRODUCT(((Move_Out_Reasons!H2:H1000="Skipped Without Notice")+(Move_Out_Reasons!H2:H1000="Skipped During Eviction")+(Move_Out_Reasons!H2:H1000="Eviction")+(Move_Out_Reasons!H2:H1000="Failure To Pay"))*(Move_Out_Reasons!F2:F1000>=$A$55)*(Move_Out_Reasons!F2:F1000<=EOMONTH($A$55,0)))} -> 8 | T59: {=SUMPRODUCT(((Move_Out_Reasons!H2:H1000="Skipped Without Notice")+(Move_Out_Reasons!H2:H1000="Skipped During Eviction")+(Move_Out_Reasons!H2:H1000="Eviction")+(Move_Out_Reasons!H2:H1000="Failure To Pay"))*(Move_Out_Reasons!F2:F1000>=$A$55)*(Move_Out_Reasons!F2:F1000<=EOMONTH($A$55,0)))} -> 8 | U59: {=SUMPRODUCT(((Move_Out_Reasons!H2:H1000="Skipped Without Notice")+(Move_Out_Reasons!H2:H1000="Skipped During Eviction")+(Move_Out_Reasons!H2:H1000="Eviction")+(Move_Out_Reasons!H2:H1000="Failure To Pay"))*(Move_Out_Reasons!F2:F1000>=$A$55)*(Move_Out_Reasons!F2:F1000<=EOMONTH($A$55,0)))} -> 8 | V59: {=SUMPRODUCT(((Move_Out_Reasons!H2:H1000="Skipped Without Notice")+(Move_Out_Reasons!H2:H1000="Skipped During Eviction")+(Move_Out_Reasons!H2:H1000="Eviction")+(Move_Out_Reasons!H2:H1000="Failure To Pay"))*(Move_Out_Reasons!F2:F1000>=$A$55)*(Move_Out_Reasons!F2:F1000<=EOMONTH($A$55,0)))} -> 8 | W59: {=SUMPRODUCT(((Move_Out_Reasons!H2:H1000="Skipped Without Notice")+(Move_Out_Reasons!H2:H1000="Skipped During Eviction")+(Move_Out_Reasons!H2:H1000="Eviction")+(Move_Out_Reasons!H2:H1000="Failure To Pay"))*(Move_Out_Reasons!F2:F1000>=$A$55)*(Move_Out_Reasons!F2:F1000<=EOMONTH($A$55,0)))} -> 8 | X59: {=SUMPRODUCT(((Move_Out_Reasons!H2:H1000="Skipped Without Notice")+(Move_Out_Reasons!H2:H1000="Skipped During Eviction")+(Move_Out_Reasons!H2:H1000="Eviction")+(Move_Out_Reasons!H2:H1000="Failure To Pay"))*(Move_Out_Reasons!F2:F1000>=$A$55)*(Move_Out_Reasons!F2:F1000<=EOMONTH($A$55,0)))} -> 8 | Y59: {=SUMPRODUCT(((Move_Out_Reasons!H2:H1000="Skipped Without Notice")+(Move_Out_Reasons!H2:H1000="Skipped During Eviction")+(Move_Out_Reasons!H2:H1000="Eviction")+(Move_Out_Reasons!H2:H1000="Failure To Pay"))*(Move_Out_Reasons!F2:F1000>=$A$55)*(Move_Out_Reasons!F2:F1000<=EOMONTH($A$55,0)))} -> 8 | Z59: {=SUMPRODUCT(((Move_Out_Reasons!H2:H1000="Skipped Without Notice")+(Move_Out_Reasons!H2:H1000="Skipped During Eviction")+(Move_Out_Reasons!H2:H1000="Eviction")+(Move_Out_Reasons!H2:H1000="Failure To Pay"))*(Move_Out_Reasons!F2:F1000>=$A$55)*(Move_Out_Reasons!F2:F1000<=EOMONTH($A$55,0)))} -> 8 | AA59: {=SUMPRODUCT(((Move_Out_Reasons!H2:H1000="Skipped Without Notice")+(Move_Out_Reasons!H2:H1000="Skipped During Eviction")+(Move_Out_Reasons!H2:H1000="Eviction")+(Move_Out_Reasons!H2:H1000="Failure To Pay"))*(Move_Out_Reasons!F2:F1000>=$A$55)*(Move_Out_Reasons!F2:F1000<=EOMONTH($A$55,0)))} -> 8 | AB59: {=SUMPRODUCT(((Move_Out_Reasons!H2:H1000="Skipped Without Notice")+(Move_Out_Reasons!H2:H1000="Skipped During Eviction")+(Move_Out_Reasons!H2:H1000="Eviction")+(Move_Out_Reasons!H2:H1000="Failure To Pay"))*(Move_Out_Reasons!F2:F1000>=$A$55)*(Move_Out_Reasons!F2:F1000<=EOMONTH($A$55,0)))} -> 8 | AC59: {=SUMPRODUCT(((Move_Out_Reasons!H2:H1000="Skipped Without Notice")+(Move_Out_Reasons!H2:H1000="Skipped During Eviction")+(Move_Out_Reasons!H2:H1000="Eviction")+(Move_Out_Reasons!H2:H1000="Failure To Pay"))*(Move_Out_Reasons!F2:F1000>=$A$55)*(Move_Out_Reasons!F2:F1000<=EOMONTH($A$55,0)))} -> 8 | AD59: 8 | AE59: 8 | AF59: 0 | AG59: 0 | AH59: 0 | AI59: 0 | AJ59: 0 | AK59: {=SUMPRODUCT(((Move_Out_Reasons!N2:N1000="Skipped Without Notice")+(Move_Out_Reasons!N2:N1000="Skipped During Eviction")+(Move_Out_Reasons!N2:N1000="Eviction")+(Move_Out_Reasons!N2:N1000="Failure To Pay"))*(Move_Out_Reasons!L2:L1000>=$A$55)*(Move_Out_Reasons!L2:L1000<=EOMONTH($A$55,0)))} -> 0
B60: Max Renewal % Possible | C60: 0 | D60: =IFERROR((SUMIF('Resident Retention -12 months'!$B:$B,$A$55,'Resident Retention -12 months'!$F:$F)+SUMIF('Resident Retention -12 months'!$B:$B,$A$55,'Resident Retention -12 months'!$H:$H)+SUMIF('Resident Retention -12 months'!$B:$B,$A$55,'Resident Retention -12 months'!$I:$I))/(SUMIF('Resident Retention -12 months'!$B:$B,$A$55,'Resident Retention -12 months'!$C:$C)-SUMIF('Resident Retention -12 months'!$B:$B,$A$55,'Resident Retention -12 months'!$J:$J)),0) -> 0.48148148 | E60: =IFERROR((SUMIF('Resident Retention -12 months'!$B:$B,$A$55,'Resident Retention -12 months'!$F:$F)+SUMIF('Resident Retention -12 months'!$B:$B,$A$55,'Resident Retention -12 months'!$H:$H)+SUMIF('Resident Retention -12 months'!$B:$B,$A$55,'Resident Retention -12 months'!$I:$I))/(SUMIF('Resident Retention -12 months'!$B:$B,$A$55,'Resident Retention -12 months'!$C:$C)-SUMIF('Resident Retention -12 months'!$B:$B,$A$55,'Resident Retention -12 months'!$J:$J)),0) -> 0.48148148 | F60: =IFERROR((SUMIF('Resident Retention -12 months'!$B:$B,$A$55,'Resident Retention -12 months'!$F:$F)+SUMIF('Resident Retention -12 months'!$B:$B,$A$55,'Resident Retention -12 months'!$H:$H)+SUMIF('Resident Retention -12 months'!$B:$B,$A$55,'Resident Retention -12 months'!$I:$I))/(SUMIF('Resident Retention -12 months'!$B:$B,$A$55,'Resident Retention -12 months'!$C:$C)-SUMIF('Resident Retention -12 months'!$B:$B,$A$55,'Resident Retention -12 months'!$J:$J)),0) -> 0.48148148 | G60: =IFERROR((SUMIF('Resident Retention -12 months'!$B:$B,$A$55,'Resident Retention -12 months'!$F:$F)+SUMIF('Resident Retention -12 months'!$B:$B,$A$55,'Resident Retention -12 months'!$H:$H)+SUMIF('Resident Retention -12 months'!$B:$B,$A$55,'Resident Retention -12 months'!$I:$I))/(SUMIF('Resident Retention -12 months'!$B:$B,$A$55,'Resident Retention -12 months'!$C:$C)-SUMIF('Resident Retention -12 months'!$B:$B,$A$55,'Resident Retention -12 months'!$J:$J)),0) -> 0.48148148 | H60: =IFERROR((SUMIF('Resident Retention -12 months'!$B:$B,$A$55,'Resident Retention -12 months'!$F:$F)+SUMIF('Resident Retention -12 months'!$B:$B,$A$55,'Resident Retention -12 months'!$H:$H)+SUMIF('Resident Retention -12 months'!$B:$B,$A$55,'Resident Retention -12 months'!$I:$I))/(SUMIF('Resident Retention -12 months'!$B:$B,$A$55,'Resident Retention -12 months'!$C:$C)-SUMIF('Resident Retention -12 months'!$B:$B,$A$55,'Resident Retention -12 months'!$J:$J)),0) -> 0.48148148 | I60: =IFERROR((SUMIF('Resident Retention -12 months'!$B:$B,$A$55,'Resident Retention -12 months'!$F:$F)+SUMIF('Resident Retention -12 months'!$B:$B,$A$55,'Resident Retention -12 months'!$H:$H)+SUMIF('Resident Retention -12 months'!$B:$B,$A$55,'Resident Retention -12 months'!$I:$I))/(SUMIF('Resident Retention -12 months'!$B:$B,$A$55,'Resident Retention -12 months'!$C:$C)-SUMIF('Resident Retention -12 months'!$B:$B,$A$55,'Resident Retention -12 months'!$J:$J)),0) -> 0.48148148 | J60: =IFERROR((SUMIF('Resident Retention -12 months'!$B:$B,$A$55,'Resident Retention -12 months'!$F:$F)+SUMIF('Resident Retention -12 months'!$B:$B,$A$55,'Resident Retention -12 months'!$H:$H)+SUMIF('Resident Retention -12 months'!$B:$B,$A$55,'Resident Retention -12 months'!$I:$I))/(SUMIF('Resident Retention -12 months'!$B:$B,$A$55,'Resident Retention -12 months'!$C:$C)-SUMIF('Resident Retention -12 months'!$B:$B,$A$55,'Resident Retention -12 months'!$J:$J)),0) -> 0.48148148 | K60: =IFERROR((SUMIF('Resident Retention -12 months'!$B:$B,$A$55,'Resident Retention -12 months'!$F:$F)+SUMIF('Resident Retention -12 months'!$B:$B,$A$55,'Resident Retention -12 months'!$H:$H)+SUMIF('Resident Retention -12 months'!$B:$B,$A$55,'Resident Retention -12 months'!$I:$I))/(SUMIF('Resident Retention -12 months'!$B:$B,$A$55,'Resident Retention -12 months'!$C:$C)-SUMIF('Resident Retention -12 months'!$B:$B,$A$55,'Resident Retention -12 months'!$J:$J)),0) -> 0.48148148 | ... AC60: =IFERROR((SUMIF('Resident Retention -12 months'!$B:$B,$A$55,'Resident Retention -12 months'!$F:$F)+SUMIF('Resident Retention -12 months'!$B:$B,$A$55,'Resident Retention -12 months'!$H:$H)+SUMIF('Resident Retention -12 months'!$B:$B,$A$55,'Resident Retention -12 months'!$I:$I))/(SUMIF('Resident Retention -12 months'!$B:$B,$A$55,'Resident Retention -12 months'!$C:$C)-SUMIF('Resident Retention -12 months'!$B:$B,$A$55,'Resident Retention -12 months'!$J:$J)),0) -> 0.48148148 | AD60: 0.48148148 | AE60: 0.48148148 | AF60: 0.48148148 | AG60: 0.48148148 | AH60: 0.48148148 | AI60: 0.48148148 | AJ60: 0.48148148 | AK60: =IFERROR((SUMIF('Resident Retention -12 months'!$B:$B,$A$55,'Resident Retention -12 months'!$F:$F)+SUMIF('Resident Retention -12 months'!$B:$B,$A$55,'Resident Retention -12 months'!$H:$H)+SUMIF('Resident Retention -12 months'!$B:$B,$A$55,'Resident Retention -12 months'!$I:$I))/(SUMIF('Resident Retention -12 months'!$B:$B,$A$55,'Resident Retention -12 months'!$C:$C)-SUMIF('Resident Retention -12 months'!$B:$B,$A$55,'Resident Retention -12 months'!$J:$J)),0) -> 0.48148148
A61: RENEWALS - JULY
A62: 46204 | B62: Expirations | C62: #,##0 | X62: 73 | Y62: 73 | Z62: 74 | AA62: 74 | AB62: 74 | AC62: 74 | AD62: 74 | AE62: 74 | AF62: 74 | AG62: 74 | AH62: 74 | AI62: 74 | AJ62: 74 | AK62: =SUMIF('Resident Retention -12 months'!$B:$J,Data_2!$A$62,'Resident Retention -12 months'!$C:$C)-SUMIF('Resident Retention -12 months'!$B:$J,Data_2!$A$62,'Resident Retention -12 months'!$J:$J) -> 74
B63: Early Move Outs | C63: #,##0 | X63: 7 | Y63: 8 | Z63: 8 | AA63: 9 | AB63: 9 | AC63: 10 | AD63: 10 | AE63: 11 | AF63: 15 | AG63: 15 | AH63: 16 | AI63: 17 | AJ63: 17 | AK63: =SUMIF('Resident Retention -12 months'!$B:$J,Data_2!$A$62,'Resident Retention -12 months'!$D:$D) -> 17
B64: NTV | C64: #,##0 | X64: 11 | Y64: 15 | Z64: 17 | AA64: 21 | AB64: 24 | AC64: 27 | AD64: 27 | AE64: 22 | AF64: 18 | AG64: 17 | AH64: 16 | AI64: 16 | AJ64: 16 | AK64: =SUMIF('Resident Retention -12 months'!$B:$J,Data_2!$A$62,'Resident Retention -12 months'!$E:$E) -> 16
B65: Renewal % | C65: 0 | X65: 0.02739726 | Y65: 0.02739726 | Z65: 0.067567568 | AA65: 0.14864865 | AB65: 0.22972973 | AC65: 0.27027027 | AD65: 0.28378378 | AE65: 0.40540541 | AF65: 0.45945946 | AG65: 0.45945946 | AH65: 0.47297297 | AI65: 0.47297297 | AJ65: 0.47297297 | AK65: =IFERROR((SUMIF('Resident Retention -12 months'!$B:$B,$A$62,'Resident Retention -12 months'!$F:$F)+SUMIF('Resident Retention -12 months'!$B:$B,$A$62,'Resident Retention -12 months'!$H:$H))/(SUMIF('Resident Retention -12 months'!$B:$B,$A$62,'Resident Retention -12 months'!$C:$C)-SUMIF('Resident Retention -12 months'!$B:$B,$A$62,'Resident Retention -12 months'!$J:$J)),0) -> 0.47297297
B66: Skips (Evictions) | C66: #,##0 | D66: {=SUMPRODUCT(((Move_Out_Reasons!H2:H1000="Skipped Without Notice")+(Move_Out_Reasons!H2:H1000="Skipped During Eviction")+(Move_Out_Reasons!H2:H1000="Eviction")+(Move_Out_Reasons!H2:H1000="Failure To Pay"))*(Move_Out_Reasons!F2:F1000>=$A$62)*(Move_Out_Reasons!F2:F1000<=EOMONTH($A$62,0)))} -> 9 | E66: {=SUMPRODUCT(((Move_Out_Reasons!H2:H1000="Skipped Without Notice")+(Move_Out_Reasons!H2:H1000="Skipped During Eviction")+(Move_Out_Reasons!H2:H1000="Eviction")+(Move_Out_Reasons!H2:H1000="Failure To Pay"))*(Move_Out_Reasons!F2:F1000>=$A$62)*(Move_Out_Reasons!F2:F1000<=EOMONTH($A$62,0)))} -> 9 | F66: {=SUMPRODUCT(((Move_Out_Reasons!H2:H1000="Skipped Without Notice")+(Move_Out_Reasons!H2:H1000="Skipped During Eviction")+(Move_Out_Reasons!H2:H1000="Eviction")+(Move_Out_Reasons!H2:H1000="Failure To Pay"))*(Move_Out_Reasons!F2:F1000>=$A$62)*(Move_Out_Reasons!F2:F1000<=EOMONTH($A$62,0)))} -> 9 | G66: {=SUMPRODUCT(((Move_Out_Reasons!H2:H1000="Skipped Without Notice")+(Move_Out_Reasons!H2:H1000="Skipped During Eviction")+(Move_Out_Reasons!H2:H1000="Eviction")+(Move_Out_Reasons!H2:H1000="Failure To Pay"))*(Move_Out_Reasons!F2:F1000>=$A$62)*(Move_Out_Reasons!F2:F1000<=EOMONTH($A$62,0)))} -> 9 | H66: {=SUMPRODUCT(((Move_Out_Reasons!H2:H1000="Skipped Without Notice")+(Move_Out_Reasons!H2:H1000="Skipped During Eviction")+(Move_Out_Reasons!H2:H1000="Eviction")+(Move_Out_Reasons!H2:H1000="Failure To Pay"))*(Move_Out_Reasons!F2:F1000>=$A$62)*(Move_Out_Reasons!F2:F1000<=EOMONTH($A$62,0)))} -> 9 | I66: {=SUMPRODUCT(((Move_Out_Reasons!H2:H1000="Skipped Without Notice")+(Move_Out_Reasons!H2:H1000="Skipped During Eviction")+(Move_Out_Reasons!H2:H1000="Eviction")+(Move_Out_Reasons!H2:H1000="Failure To Pay"))*(Move_Out_Reasons!F2:F1000>=$A$62)*(Move_Out_Reasons!F2:F1000<=EOMONTH($A$62,0)))} -> 9 | J66: {=SUMPRODUCT(((Move_Out_Reasons!H2:H1000="Skipped Without Notice")+(Move_Out_Reasons!H2:H1000="Skipped During Eviction")+(Move_Out_Reasons!H2:H1000="Eviction")+(Move_Out_Reasons!H2:H1000="Failure To Pay"))*(Move_Out_Reasons!F2:F1000>=$A$62)*(Move_Out_Reasons!F2:F1000<=EOMONTH($A$62,0)))} -> 9 | K66: {=SUMPRODUCT(((Move_Out_Reasons!H2:H1000="Skipped Without Notice")+(Move_Out_Reasons!H2:H1000="Skipped During Eviction")+(Move_Out_Reasons!H2:H1000="Eviction")+(Move_Out_Reasons!H2:H1000="Failure To Pay"))*(Move_Out_Reasons!F2:F1000>=$A$62)*(Move_Out_Reasons!F2:F1000<=EOMONTH($A$62,0)))} -> 9 | L66: {=SUMPRODUCT(((Move_Out_Reasons!H2:H1000="Skipped Without Notice")+(Move_Out_Reasons!H2:H1000="Skipped During Eviction")+(Move_Out_Reasons!H2:H1000="Eviction")+(Move_Out_Reasons!H2:H1000="Failure To Pay"))*(Move_Out_Reasons!F2:F1000>=$A$62)*(Move_Out_Reasons!F2:F1000<=EOMONTH($A$62,0)))} -> 9 | M66: {=SUMPRODUCT(((Move_Out_Reasons!H2:H1000="Skipped Without Notice")+(Move_Out_Reasons!H2:H1000="Skipped During Eviction")+(Move_Out_Reasons!H2:H1000="Eviction")+(Move_Out_Reasons!H2:H1000="Failure To Pay"))*(Move_Out_Reasons!F2:F1000>=$A$62)*(Move_Out_Reasons!F2:F1000<=EOMONTH($A$62,0)))} -> 9 | N66: {=SUMPRODUCT(((Move_Out_Reasons!H2:H1000="Skipped Without Notice")+(Move_Out_Reasons!H2:H1000="Skipped During Eviction")+(Move_Out_Reasons!H2:H1000="Eviction")+(Move_Out_Reasons!H2:H1000="Failure To Pay"))*(Move_Out_Reasons!F2:F1000>=$A$62)*(Move_Out_Reasons!F2:F1000<=EOMONTH($A$62,0)))} -> 9 | O66: {=SUMPRODUCT(((Move_Out_Reasons!H2:H1000="Skipped Without Notice")+(Move_Out_Reasons!H2:H1000="Skipped During Eviction")+(Move_Out_Reasons!H2:H1000="Eviction")+(Move_Out_Reasons!H2:H1000="Failure To Pay"))*(Move_Out_Reasons!F2:F1000>=$A$62)*(Move_Out_Reasons!F2:F1000<=EOMONTH($A$62,0)))} -> 9 | P66: {=SUMPRODUCT(((Move_Out_Reasons!H2:H1000="Skipped Without Notice")+(Move_Out_Reasons!H2:H1000="Skipped During Eviction")+(Move_Out_Reasons!H2:H1000="Eviction")+(Move_Out_Reasons!H2:H1000="Failure To Pay"))*(Move_Out_Reasons!F2:F1000>=$A$62)*(Move_Out_Reasons!F2:F1000<=EOMONTH($A$62,0)))} -> 9 | Q66: {=SUMPRODUCT(((Move_Out_Reasons!H2:H1000="Skipped Without Notice")+(Move_Out_Reasons!H2:H1000="Skipped During Eviction")+(Move_Out_Reasons!H2:H1000="Eviction")+(Move_Out_Reasons!H2:H1000="Failure To Pay"))*(Move_Out_Reasons!F2:F1000>=$A$62)*(Move_Out_Reasons!F2:F1000<=EOMONTH($A$62,0)))} -> 9 | R66: {=SUMPRODUCT(((Move_Out_Reasons!H2:H1000="Skipped Without Notice")+(Move_Out_Reasons!H2:H1000="Skipped During Eviction")+(Move_Out_Reasons!H2:H1000="Eviction")+(Move_Out_Reasons!H2:H1000="Failure To Pay"))*(Move_Out_Reasons!F2:F1000>=$A$62)*(Move_Out_Reasons!F2:F1000<=EOMONTH($A$62,0)))} -> 9 | S66: {=SUMPRODUCT(((Move_Out_Reasons!H2:H1000="Skipped Without Notice")+(Move_Out_Reasons!H2:H1000="Skipped During Eviction")+(Move_Out_Reasons!H2:H1000="Eviction")+(Move_Out_Reasons!H2:H1000="Failure To Pay"))*(Move_Out_Reasons!F2:F1000>=$A$62)*(Move_Out_Reasons!F2:F1000<=EOMONTH($A$62,0)))} -> 9 | T66: {=SUMPRODUCT(((Move_Out_Reasons!H2:H1000="Skipped Without Notice")+(Move_Out_Reasons!H2:H1000="Skipped During Eviction")+(Move_Out_Reasons!H2:H1000="Eviction")+(Move_Out_Reasons!H2:H1000="Failure To Pay"))*(Move_Out_Reasons!F2:F1000>=$A$62)*(Move_Out_Reasons!F2:F1000<=EOMONTH($A$62,0)))} -> 9 | U66: {=SUMPRODUCT(((Move_Out_Reasons!H2:H1000="Skipped Without Notice")+(Move_Out_Reasons!H2:H1000="Skipped During Eviction")+(Move_Out_Reasons!H2:H1000="Eviction")+(Move_Out_Reasons!H2:H1000="Failure To Pay"))*(Move_Out_Reasons!F2:F1000>=$A$62)*(Move_Out_Reasons!F2:F1000<=EOMONTH($A$62,0)))} -> 9 | V66: {=SUMPRODUCT(((Move_Out_Reasons!H2:H1000="Skipped Without Notice")+(Move_Out_Reasons!H2:H1000="Skipped During Eviction")+(Move_Out_Reasons!H2:H1000="Eviction")+(Move_Out_Reasons!H2:H1000="Failure To Pay"))*(Move_Out_Reasons!F2:F1000>=$A$62)*(Move_Out_Reasons!F2:F1000<=EOMONTH($A$62,0)))} -> 9 | W66: {=SUMPRODUCT(((Move_Out_Reasons!H2:H1000="Skipped Without Notice")+(Move_Out_Reasons!H2:H1000="Skipped During Eviction")+(Move_Out_Reasons!H2:H1000="Eviction")+(Move_Out_Reasons!H2:H1000="Failure To Pay"))*(Move_Out_Reasons!F2:F1000>=$A$62)*(Move_Out_Reasons!F2:F1000<=EOMONTH($A$62,0)))} -> 9 | X66: {=SUMPRODUCT(((Move_Out_Reasons!H2:H1000="Skipped Without Notice")+(Move_Out_Reasons!H2:H1000="Skipped During Eviction")+(Move_Out_Reasons!H2:H1000="Eviction")+(Move_Out_Reasons!H2:H1000="Failure To Pay"))*(Move_Out_Reasons!F2:F1000>=$A$62)*(Move_Out_Reasons!F2:F1000<=EOMONTH($A$62,0)))} -> 9 | Y66: {=SUMPRODUCT(((Move_Out_Reasons!H2:H1000="Skipped Without Notice")+(Move_Out_Reasons!H2:H1000="Skipped During Eviction")+(Move_Out_Reasons!H2:H1000="Eviction")+(Move_Out_Reasons!H2:H1000="Failure To Pay"))*(Move_Out_Reasons!F2:F1000>=$A$62)*(Move_Out_Reasons!F2:F1000<=EOMONTH($A$62,0)))} -> 9 | Z66: {=SUMPRODUCT(((Move_Out_Reasons!H2:H1000="Skipped Without Notice")+(Move_Out_Reasons!H2:H1000="Skipped During Eviction")+(Move_Out_Reasons!H2:H1000="Eviction")+(Move_Out_Reasons!H2:H1000="Failure To Pay"))*(Move_Out_Reasons!F2:F1000>=$A$62)*(Move_Out_Reasons!F2:F1000<=EOMONTH($A$62,0)))} -> 9 | AA66: {=SUMPRODUCT(((Move_Out_Reasons!H2:H1000="Skipped Without Notice")+(Move_Out_Reasons!H2:H1000="Skipped During Eviction")+(Move_Out_Reasons!H2:H1000="Eviction")+(Move_Out_Reasons!H2:H1000="Failure To Pay"))*(Move_Out_Reasons!F2:F1000>=$A$62)*(Move_Out_Reasons!F2:F1000<=EOMONTH($A$62,0)))} -> 9 | AB66: {=SUMPRODUCT(((Move_Out_Reasons!H2:H1000="Skipped Without Notice")+(Move_Out_Reasons!H2:H1000="Skipped During Eviction")+(Move_Out_Reasons!H2:H1000="Eviction")+(Move_Out_Reasons!H2:H1000="Failure To Pay"))*(Move_Out_Reasons!F2:F1000>=$A$62)*(Move_Out_Reasons!F2:F1000<=EOMONTH($A$62,0)))} -> 9 | AC66: {=SUMPRODUCT(((Move_Out_Reasons!H2:H1000="Skipped Without Notice")+(Move_Out_Reasons!H2:H1000="Skipped During Eviction")+(Move_Out_Reasons!H2:H1000="Eviction")+(Move_Out_Reasons!H2:H1000="Failure To Pay"))*(Move_Out_Reasons!F2:F1000>=$A$62)*(Move_Out_Reasons!F2:F1000<=EOMONTH($A$62,0)))} -> 9 | AD66: 3 | AE66: 4 | AF66: 0 | AG66: 0 | AH66: 0 | AI66: 0 | AJ66: 0 | AK66: {=SUMPRODUCT(((Move_Out_Reasons!N2:N1000="Skipped Without Notice")+(Move_Out_Reasons!N2:N1000="Skipped During Eviction")+(Move_Out_Reasons!N2:N1000="Eviction")+(Move_Out_Reasons!N2:N1000="Failure To Pay"))*(Move_Out_Reasons!L2:L1000>=$A$62)*(Move_Out_Reasons!L2:L1000<=EOMONTH($A$62,0)))} -> 0
B67: Max Renewal % Possible | C67: 0 | D67: =IFERROR((SUMIF('Resident Retention -12 months'!$B:$B,$A$62,'Resident Retention -12 months'!$F:$F)+SUMIF('Resident Retention -12 months'!$B:$B,$A$62,'Resident Retention -12 months'!$H:$H)+SUMIF('Resident Retention -12 months'!$B:$B,$A$62,'Resident Retention -12 months'!$I:$I))/(SUMIF('Resident Retention -12 months'!$B:$B,$A$62,'Resident Retention -12 months'!$C:$C)-SUMIF('Resident Retention -12 months'!$B:$B,$A$62,'Resident Retention -12 months'!$J:$J)),0) -> 0.55405405 | E67: =IFERROR((SUMIF('Resident Retention -12 months'!$B:$B,$A$62,'Resident Retention -12 months'!$F:$F)+SUMIF('Resident Retention -12 months'!$B:$B,$A$62,'Resident Retention -12 months'!$H:$H)+SUMIF('Resident Retention -12 months'!$B:$B,$A$62,'Resident Retention -12 months'!$I:$I))/(SUMIF('Resident Retention -12 months'!$B:$B,$A$62,'Resident Retention -12 months'!$C:$C)-SUMIF('Resident Retention -12 months'!$B:$B,$A$62,'Resident Retention -12 months'!$J:$J)),0) -> 0.55405405 | F67: =IFERROR((SUMIF('Resident Retention -12 months'!$B:$B,$A$62,'Resident Retention -12 months'!$F:$F)+SUMIF('Resident Retention -12 months'!$B:$B,$A$62,'Resident Retention -12 months'!$H:$H)+SUMIF('Resident Retention -12 months'!$B:$B,$A$62,'Resident Retention -12 months'!$I:$I))/(SUMIF('Resident Retention -12 months'!$B:$B,$A$62,'Resident Retention -12 months'!$C:$C)-SUMIF('Resident Retention -12 months'!$B:$B,$A$62,'Resident Retention -12 months'!$J:$J)),0) -> 0.55405405 | G67: =IFERROR((SUMIF('Resident Retention -12 months'!$B:$B,$A$62,'Resident Retention -12 months'!$F:$F)+SUMIF('Resident Retention -12 months'!$B:$B,$A$62,'Resident Retention -12 months'!$H:$H)+SUMIF('Resident Retention -12 months'!$B:$B,$A$62,'Resident Retention -12 months'!$I:$I))/(SUMIF('Resident Retention -12 months'!$B:$B,$A$62,'Resident Retention -12 months'!$C:$C)-SUMIF('Resident Retention -12 months'!$B:$B,$A$62,'Resident Retention -12 months'!$J:$J)),0) -> 0.55405405 | H67: =IFERROR((SUMIF('Resident Retention -12 months'!$B:$B,$A$62,'Resident Retention -12 months'!$F:$F)+SUMIF('Resident Retention -12 months'!$B:$B,$A$62,'Resident Retention -12 months'!$H:$H)+SUMIF('Resident Retention -12 months'!$B:$B,$A$62,'Resident Retention -12 months'!$I:$I))/(SUMIF('Resident Retention -12 months'!$B:$B,$A$62,'Resident Retention -12 months'!$C:$C)-SUMIF('Resident Retention -12 months'!$B:$B,$A$62,'Resident Retention -12 months'!$J:$J)),0) -> 0.55405405 | I67: =IFERROR((SUMIF('Resident Retention -12 months'!$B:$B,$A$62,'Resident Retention -12 months'!$F:$F)+SUMIF('Resident Retention -12 months'!$B:$B,$A$62,'Resident Retention -12 months'!$H:$H)+SUMIF('Resident Retention -12 months'!$B:$B,$A$62,'Resident Retention -12 months'!$I:$I))/(SUMIF('Resident Retention -12 months'!$B:$B,$A$62,'Resident Retention -12 months'!$C:$C)-SUMIF('Resident Retention -12 months'!$B:$B,$A$62,'Resident Retention -12 months'!$J:$J)),0) -> 0.55405405 | J67: =IFERROR((SUMIF('Resident Retention -12 months'!$B:$B,$A$62,'Resident Retention -12 months'!$F:$F)+SUMIF('Resident Retention -12 months'!$B:$B,$A$62,'Resident Retention -12 months'!$H:$H)+SUMIF('Resident Retention -12 months'!$B:$B,$A$62,'Resident Retention -12 months'!$I:$I))/(SUMIF('Resident Retention -12 months'!$B:$B,$A$62,'Resident Retention -12 months'!$C:$C)-SUMIF('Resident Retention -12 months'!$B:$B,$A$62,'Resident Retention -12 months'!$J:$J)),0) -> 0.55405405 | K67: =IFERROR((SUMIF('Resident Retention -12 months'!$B:$B,$A$62,'Resident Retention -12 months'!$F:$F)+SUMIF('Resident Retention -12 months'!$B:$B,$A$62,'Resident Retention -12 months'!$H:$H)+SUMIF('Resident Retention -12 months'!$B:$B,$A$62,'Resident Retention -12 months'!$I:$I))/(SUMIF('Resident Retention -12 months'!$B:$B,$A$62,'Resident Retention -12 months'!$C:$C)-SUMIF('Resident Retention -12 months'!$B:$B,$A$62,'Resident Retention -12 months'!$J:$J)),0) -> 0.55405405 | ... AC67: =IFERROR((SUMIF('Resident Retention -12 months'!$B:$B,$A$62,'Resident Retention -12 months'!$F:$F)+SUMIF('Resident Retention -12 months'!$B:$B,$A$62,'Resident Retention -12 months'!$H:$H)+SUMIF('Resident Retention -12 months'!$B:$B,$A$62,'Resident Retention -12 months'!$I:$I))/(SUMIF('Resident Retention -12 months'!$B:$B,$A$62,'Resident Retention -12 months'!$C:$C)-SUMIF('Resident Retention -12 months'!$B:$B,$A$62,'Resident Retention -12 months'!$J:$J)),0) -> 0.55405405 | AD67: 0.5 | AE67: 0.55405405 | AF67: 0.55405405 | AG67: 0.56756757 | AH67: 0.56756757 | AI67: 0.55405405 | AJ67: 0.55405405 | AK67: =IFERROR((SUMIF('Resident Retention -12 months'!$B:$B,$A$62,'Resident Retention -12 months'!$F:$F)+SUMIF('Resident Retention -12 months'!$B:$B,$A$62,'Resident Retention -12 months'!$H:$H)+SUMIF('Resident Retention -12 months'!$B:$B,$A$62,'Resident Retention -12 months'!$I:$I))/(SUMIF('Resident Retention -12 months'!$B:$B,$A$62,'Resident Retention -12 months'!$C:$C)-SUMIF('Resident Retention -12 months'!$B:$B,$A$62,'Resident Retention -12 months'!$J:$J)),0) -> 0.55405405
A68: RENEWALS - AUGUST
A69: 46235 | B69: Expirations | C69: #,##0 | AD69: 51 | AE69: 51 | AF69: 51 | AG69: 51 | AH69: 51 | AI69: 51 | AJ69: 51 | AK69: =SUMIF('Resident Retention -12 months'!$B:$J,Data_2!$A$69,'Resident Retention -12 months'!$C:$C)-SUMIF('Resident Retention -12 months'!$B:$J,Data_2!$A$69,'Resident Retention -12 months'!$J:$J) -> 51
B70: Early Move Outs | C70: #,##0 | AD70: 5 | AE70: 5 | AF70: 5 | AG70: 6 | AH70: 7 | AI70: 7 | AJ70: 8 | AK70: =SUMIF('Resident Retention -12 months'!$B:$J,Data_2!$A$69,'Resident Retention -12 months'!$D:$D) -> 8
B71: NTV | C71: #,##0 | AD71: 11 | AE71: 12 | AF71: 12 | AG71: 11 | AH71: 11 | AI71: 11 | AJ71: 12 | AK71: =SUMIF('Resident Retention -12 months'!$B:$J,Data_2!$A$69,'Resident Retention -12 months'!$E:$E) -> 12
B72: Renewal % | C72: 0 | AD72: 0.25490196 | AE72: 0.37254902 | AF72: 0.47058824 | AG72: 0.52941176 | AH72: 0.56862745 | AI72: 0.60784314 | AJ72: 0.60784314 | AK72: =IFERROR((SUMIF('Resident Retention -12 months'!$B:$B,$A$69,'Resident Retention -12 months'!$F:$F)+SUMIF('Resident Retention -12 months'!$B:$B,$A$69,'Resident Retention -12 months'!$H:$H))/(SUMIF('Resident Retention -12 months'!$B:$B,$A$69,'Resident Retention -12 months'!$C:$C)-SUMIF('Resident Retention -12 months'!$B:$B,$A$69,'Resident Retention -12 months'!$J:$J)),0) -> 0.60784314
B73: Skips (Evictions) | C73: #,##0 | D73: {=SUMPRODUCT(((Move_Out_Reasons!H2:H1000="Skipped Without Notice")+(Move_Out_Reasons!H2:H1000="Skipped During Eviction")+(Move_Out_Reasons!H2:H1000="Eviction")+(Move_Out_Reasons!H2:H1000="Failure To Pay"))*(Move_Out_Reasons!F2:F1000>=$A$69)*(Move_Out_Reasons!F2:F1000<=EOMONTH($A$69,0)))} -> 6 | E73: {=SUMPRODUCT(((Move_Out_Reasons!H2:H1000="Skipped Without Notice")+(Move_Out_Reasons!H2:H1000="Skipped During Eviction")+(Move_Out_Reasons!H2:H1000="Eviction")+(Move_Out_Reasons!H2:H1000="Failure To Pay"))*(Move_Out_Reasons!F2:F1000>=$A$69)*(Move_Out_Reasons!F2:F1000<=EOMONTH($A$69,0)))} -> 6 | F73: {=SUMPRODUCT(((Move_Out_Reasons!H2:H1000="Skipped Without Notice")+(Move_Out_Reasons!H2:H1000="Skipped During Eviction")+(Move_Out_Reasons!H2:H1000="Eviction")+(Move_Out_Reasons!H2:H1000="Failure To Pay"))*(Move_Out_Reasons!F2:F1000>=$A$69)*(Move_Out_Reasons!F2:F1000<=EOMONTH($A$69,0)))} -> 6 | G73: {=SUMPRODUCT(((Move_Out_Reasons!H2:H1000="Skipped Without Notice")+(Move_Out_Reasons!H2:H1000="Skipped During Eviction")+(Move_Out_Reasons!H2:H1000="Eviction")+(Move_Out_Reasons!H2:H1000="Failure To Pay"))*(Move_Out_Reasons!F2:F1000>=$A$69)*(Move_Out_Reasons!F2:F1000<=EOMONTH($A$69,0)))} -> 6 | H73: {=SUMPRODUCT(((Move_Out_Reasons!H2:H1000="Skipped Without Notice")+(Move_Out_Reasons!H2:H1000="Skipped During Eviction")+(Move_Out_Reasons!H2:H1000="Eviction")+(Move_Out_Reasons!H2:H1000="Failure To Pay"))*(Move_Out_Reasons!F2:F1000>=$A$69)*(Move_Out_Reasons!F2:F1000<=EOMONTH($A$69,0)))} -> 6 | I73: {=SUMPRODUCT(((Move_Out_Reasons!H2:H1000="Skipped Without Notice")+(Move_Out_Reasons!H2:H1000="Skipped During Eviction")+(Move_Out_Reasons!H2:H1000="Eviction")+(Move_Out_Reasons!H2:H1000="Failure To Pay"))*(Move_Out_Reasons!F2:F1000>=$A$69)*(Move_Out_Reasons!F2:F1000<=EOMONTH($A$69,0)))} -> 6 | J73: {=SUMPRODUCT(((Move_Out_Reasons!H2:H1000="Skipped Without Notice")+(Move_Out_Reasons!H2:H1000="Skipped During Eviction")+(Move_Out_Reasons!H2:H1000="Eviction")+(Move_Out_Reasons!H2:H1000="Failure To Pay"))*(Move_Out_Reasons!F2:F1000>=$A$69)*(Move_Out_Reasons!F2:F1000<=EOMONTH($A$69,0)))} -> 6 | K73: {=SUMPRODUCT(((Move_Out_Reasons!H2:H1000="Skipped Without Notice")+(Move_Out_Reasons!H2:H1000="Skipped During Eviction")+(Move_Out_Reasons!H2:H1000="Eviction")+(Move_Out_Reasons!H2:H1000="Failure To Pay"))*(Move_Out_Reasons!F2:F1000>=$A$69)*(Move_Out_Reasons!F2:F1000<=EOMONTH($A$69,0)))} -> 6 | L73: {=SUMPRODUCT(((Move_Out_Reasons!H2:H1000="Skipped Without Notice")+(Move_Out_Reasons!H2:H1000="Skipped During Eviction")+(Move_Out_Reasons!H2:H1000="Eviction")+(Move_Out_Reasons!H2:H1000="Failure To Pay"))*(Move_Out_Reasons!F2:F1000>=$A$69)*(Move_Out_Reasons!F2:F1000<=EOMONTH($A$69,0)))} -> 6 | M73: {=SUMPRODUCT(((Move_Out_Reasons!H2:H1000="Skipped Without Notice")+(Move_Out_Reasons!H2:H1000="Skipped During Eviction")+(Move_Out_Reasons!H2:H1000="Eviction")+(Move_Out_Reasons!H2:H1000="Failure To Pay"))*(Move_Out_Reasons!F2:F1000>=$A$69)*(Move_Out_Reasons!F2:F1000<=EOMONTH($A$69,0)))} -> 6 | N73: {=SUMPRODUCT(((Move_Out_Reasons!H2:H1000="Skipped Without Notice")+(Move_Out_Reasons!H2:H1000="Skipped During Eviction")+(Move_Out_Reasons!H2:H1000="Eviction")+(Move_Out_Reasons!H2:H1000="Failure To Pay"))*(Move_Out_Reasons!F2:F1000>=$A$69)*(Move_Out_Reasons!F2:F1000<=EOMONTH($A$69,0)))} -> 6 | O73: {=SUMPRODUCT(((Move_Out_Reasons!H2:H1000="Skipped Without Notice")+(Move_Out_Reasons!H2:H1000="Skipped During Eviction")+(Move_Out_Reasons!H2:H1000="Eviction")+(Move_Out_Reasons!H2:H1000="Failure To Pay"))*(Move_Out_Reasons!F2:F1000>=$A$69)*(Move_Out_Reasons!F2:F1000<=EOMONTH($A$69,0)))} -> 6 | P73: {=SUMPRODUCT(((Move_Out_Reasons!H2:H1000="Skipped Without Notice")+(Move_Out_Reasons!H2:H1000="Skipped During Eviction")+(Move_Out_Reasons!H2:H1000="Eviction")+(Move_Out_Reasons!H2:H1000="Failure To Pay"))*(Move_Out_Reasons!F2:F1000>=$A$69)*(Move_Out_Reasons!F2:F1000<=EOMONTH($A$69,0)))} -> 6 | Q73: {=SUMPRODUCT(((Move_Out_Reasons!H2:H1000="Skipped Without Notice")+(Move_Out_Reasons!H2:H1000="Skipped During Eviction")+(Move_Out_Reasons!H2:H1000="Eviction")+(Move_Out_Reasons!H2:H1000="Failure To Pay"))*(Move_Out_Reasons!F2:F1000>=$A$69)*(Move_Out_Reasons!F2:F1000<=EOMONTH($A$69,0)))} -> 6 | R73: {=SUMPRODUCT(((Move_Out_Reasons!H2:H1000="Skipped Without Notice")+(Move_Out_Reasons!H2:H1000="Skipped During Eviction")+(Move_Out_Reasons!H2:H1000="Eviction")+(Move_Out_Reasons!H2:H1000="Failure To Pay"))*(Move_Out_Reasons!F2:F1000>=$A$69)*(Move_Out_Reasons!F2:F1000<=EOMONTH($A$69,0)))} -> 6 | S73: {=SUMPRODUCT(((Move_Out_Reasons!H2:H1000="Skipped Without Notice")+(Move_Out_Reasons!H2:H1000="Skipped During Eviction")+(Move_Out_Reasons!H2:H1000="Eviction")+(Move_Out_Reasons!H2:H1000="Failure To Pay"))*(Move_Out_Reasons!F2:F1000>=$A$69)*(Move_Out_Reasons!F2:F1000<=EOMONTH($A$69,0)))} -> 6 | T73: {=SUMPRODUCT(((Move_Out_Reasons!H2:H1000="Skipped Without Notice")+(Move_Out_Reasons!H2:H1000="Skipped During Eviction")+(Move_Out_Reasons!H2:H1000="Eviction")+(Move_Out_Reasons!H2:H1000="Failure To Pay"))*(Move_Out_Reasons!F2:F1000>=$A$69)*(Move_Out_Reasons!F2:F1000<=EOMONTH($A$69,0)))} -> 6 | U73: {=SUMPRODUCT(((Move_Out_Reasons!H2:H1000="Skipped Without Notice")+(Move_Out_Reasons!H2:H1000="Skipped During Eviction")+(Move_Out_Reasons!H2:H1000="Eviction")+(Move_Out_Reasons!H2:H1000="Failure To Pay"))*(Move_Out_Reasons!F2:F1000>=$A$69)*(Move_Out_Reasons!F2:F1000<=EOMONTH($A$69,0)))} -> 6 | V73: {=SUMPRODUCT(((Move_Out_Reasons!H2:H1000="Skipped Without Notice")+(Move_Out_Reasons!H2:H1000="Skipped During Eviction")+(Move_Out_Reasons!H2:H1000="Eviction")+(Move_Out_Reasons!H2:H1000="Failure To Pay"))*(Move_Out_Reasons!F2:F1000>=$A$69)*(Move_Out_Reasons!F2:F1000<=EOMONTH($A$69,0)))} -> 6 | W73: {=SUMPRODUCT(((Move_Out_Reasons!H2:H1000="Skipped Without Notice")+(Move_Out_Reasons!H2:H1000="Skipped During Eviction")+(Move_Out_Reasons!H2:H1000="Eviction")+(Move_Out_Reasons!H2:H1000="Failure To Pay"))*(Move_Out_Reasons!F2:F1000>=$A$69)*(Move_Out_Reasons!F2:F1000<=EOMONTH($A$69,0)))} -> 6 | X73: {=SUMPRODUCT(((Move_Out_Reasons!H2:H1000="Skipped Without Notice")+(Move_Out_Reasons!H2:H1000="Skipped During Eviction")+(Move_Out_Reasons!H2:H1000="Eviction")+(Move_Out_Reasons!H2:H1000="Failure To Pay"))*(Move_Out_Reasons!F2:F1000>=$A$69)*(Move_Out_Reasons!F2:F1000<=EOMONTH($A$69,0)))} -> 6 | Y73: {=SUMPRODUCT(((Move_Out_Reasons!H2:H1000="Skipped Without Notice")+(Move_Out_Reasons!H2:H1000="Skipped During Eviction")+(Move_Out_Reasons!H2:H1000="Eviction")+(Move_Out_Reasons!H2:H1000="Failure To Pay"))*(Move_Out_Reasons!F2:F1000>=$A$69)*(Move_Out_Reasons!F2:F1000<=EOMONTH($A$69,0)))} -> 6 | Z73: {=SUMPRODUCT(((Move_Out_Reasons!H2:H1000="Skipped Without Notice")+(Move_Out_Reasons!H2:H1000="Skipped During Eviction")+(Move_Out_Reasons!H2:H1000="Eviction")+(Move_Out_Reasons!H2:H1000="Failure To Pay"))*(Move_Out_Reasons!F2:F1000>=$A$69)*(Move_Out_Reasons!F2:F1000<=EOMONTH($A$69,0)))} -> 6 | AA73: {=SUMPRODUCT(((Move_Out_Reasons!H2:H1000="Skipped Without Notice")+(Move_Out_Reasons!H2:H1000="Skipped During Eviction")+(Move_Out_Reasons!H2:H1000="Eviction")+(Move_Out_Reasons!H2:H1000="Failure To Pay"))*(Move_Out_Reasons!F2:F1000>=$A$69)*(Move_Out_Reasons!F2:F1000<=EOMONTH($A$69,0)))} -> 6 | AB73: {=SUMPRODUCT(((Move_Out_Reasons!H2:H1000="Skipped Without Notice")+(Move_Out_Reasons!H2:H1000="Skipped During Eviction")+(Move_Out_Reasons!H2:H1000="Eviction")+(Move_Out_Reasons!H2:H1000="Failure To Pay"))*(Move_Out_Reasons!F2:F1000>=$A$69)*(Move_Out_Reasons!F2:F1000<=EOMONTH($A$69,0)))} -> 6 | AC73: {=SUMPRODUCT(((Move_Out_Reasons!H2:H1000="Skipped Without Notice")+(Move_Out_Reasons!H2:H1000="Skipped During Eviction")+(Move_Out_Reasons!H2:H1000="Eviction")+(Move_Out_Reasons!H2:H1000="Failure To Pay"))*(Move_Out_Reasons!F2:F1000>=$A$69)*(Move_Out_Reasons!F2:F1000<=EOMONTH($A$69,0)))} -> 6 | AD73: 2 | AE73: 2 | AF73: 0 | AG73: 0 | AH73: 0 | AI73: 0 | AJ73: 0 | AK73: {=SUMPRODUCT(((Move_Out_Reasons!N2:N1000="Skipped Without Notice")+(Move_Out_Reasons!N2:N1000="Skipped During Eviction")+(Move_Out_Reasons!N2:N1000="Eviction")+(Move_Out_Reasons!N2:N1000="Failure To Pay"))*(Move_Out_Reasons!L2:L1000>=$A$69)*(Move_Out_Reasons!L2:L1000<=EOMONTH($A$69,0)))} -> 0
B74: Max Renewal % Possible | C74: 0 | D74: =IFERROR((SUMIF('Resident Retention -12 months'!$B:$B,$A$69,'Resident Retention -12 months'!$F:$F)+SUMIF('Resident Retention -12 months'!$B:$B,$A$69,'Resident Retention -12 months'!$H:$H)+SUMIF('Resident Retention -12 months'!$B:$B,$A$69,'Resident Retention -12 months'!$I:$I))/(SUMIF('Resident Retention -12 months'!$B:$B,$A$69,'Resident Retention -12 months'!$C:$C)-SUMIF('Resident Retention -12 months'!$B:$B,$A$69,'Resident Retention -12 months'!$J:$J)),0) -> 0.60784314 | E74: =IFERROR((SUMIF('Resident Retention -12 months'!$B:$B,$A$69,'Resident Retention -12 months'!$F:$F)+SUMIF('Resident Retention -12 months'!$B:$B,$A$69,'Resident Retention -12 months'!$H:$H)+SUMIF('Resident Retention -12 months'!$B:$B,$A$69,'Resident Retention -12 months'!$I:$I))/(SUMIF('Resident Retention -12 months'!$B:$B,$A$69,'Resident Retention -12 months'!$C:$C)-SUMIF('Resident Retention -12 months'!$B:$B,$A$69,'Resident Retention -12 months'!$J:$J)),0) -> 0.60784314 | F74: =IFERROR((SUMIF('Resident Retention -12 months'!$B:$B,$A$69,'Resident Retention -12 months'!$F:$F)+SUMIF('Resident Retention -12 months'!$B:$B,$A$69,'Resident Retention -12 months'!$H:$H)+SUMIF('Resident Retention -12 months'!$B:$B,$A$69,'Resident Retention -12 months'!$I:$I))/(SUMIF('Resident Retention -12 months'!$B:$B,$A$69,'Resident Retention -12 months'!$C:$C)-SUMIF('Resident Retention -12 months'!$B:$B,$A$69,'Resident Retention -12 months'!$J:$J)),0) -> 0.60784314 | G74: =IFERROR((SUMIF('Resident Retention -12 months'!$B:$B,$A$69,'Resident Retention -12 months'!$F:$F)+SUMIF('Resident Retention -12 months'!$B:$B,$A$69,'Resident Retention -12 months'!$H:$H)+SUMIF('Resident Retention -12 months'!$B:$B,$A$69,'Resident Retention -12 months'!$I:$I))/(SUMIF('Resident Retention -12 months'!$B:$B,$A$69,'Resident Retention -12 months'!$C:$C)-SUMIF('Resident Retention -12 months'!$B:$B,$A$69,'Resident Retention -12 months'!$J:$J)),0) -> 0.60784314 | H74: =IFERROR((SUMIF('Resident Retention -12 months'!$B:$B,$A$69,'Resident Retention -12 months'!$F:$F)+SUMIF('Resident Retention -12 months'!$B:$B,$A$69,'Resident Retention -12 months'!$H:$H)+SUMIF('Resident Retention -12 months'!$B:$B,$A$69,'Resident Retention -12 months'!$I:$I))/(SUMIF('Resident Retention -12 months'!$B:$B,$A$69,'Resident Retention -12 months'!$C:$C)-SUMIF('Resident Retention -12 months'!$B:$B,$A$69,'Resident Retention -12 months'!$J:$J)),0) -> 0.60784314 | I74: =IFERROR((SUMIF('Resident Retention -12 months'!$B:$B,$A$69,'Resident Retention -12 months'!$F:$F)+SUMIF('Resident Retention -12 months'!$B:$B,$A$69,'Resident Retention -12 months'!$H:$H)+SUMIF('Resident Retention -12 months'!$B:$B,$A$69,'Resident Retention -12 months'!$I:$I))/(SUMIF('Resident Retention -12 months'!$B:$B,$A$69,'Resident Retention -12 months'!$C:$C)-SUMIF('Resident Retention -12 months'!$B:$B,$A$69,'Resident Retention -12 months'!$J:$J)),0) -> 0.60784314 | J74: =IFERROR((SUMIF('Resident Retention -12 months'!$B:$B,$A$69,'Resident Retention -12 months'!$F:$F)+SUMIF('Resident Retention -12 months'!$B:$B,$A$69,'Resident Retention -12 months'!$H:$H)+SUMIF('Resident Retention -12 months'!$B:$B,$A$69,'Resident Retention -12 months'!$I:$I))/(SUMIF('Resident Retention -12 months'!$B:$B,$A$69,'Resident Retention -12 months'!$C:$C)-SUMIF('Resident Retention -12 months'!$B:$B,$A$69,'Resident Retention -12 months'!$J:$J)),0) -> 0.60784314 | K74: =IFERROR((SUMIF('Resident Retention -12 months'!$B:$B,$A$69,'Resident Retention -12 months'!$F:$F)+SUMIF('Resident Retention -12 months'!$B:$B,$A$69,'Resident Retention -12 months'!$H:$H)+SUMIF('Resident Retention -12 months'!$B:$B,$A$69,'Resident Retention -12 months'!$I:$I))/(SUMIF('Resident Retention -12 months'!$B:$B,$A$69,'Resident Retention -12 months'!$C:$C)-SUMIF('Resident Retention -12 months'!$B:$B,$A$69,'Resident Retention -12 months'!$J:$J)),0) -> 0.60784314 | ... AC74: =IFERROR((SUMIF('Resident Retention -12 months'!$B:$B,$A$69,'Resident Retention -12 months'!$F:$F)+SUMIF('Resident Retention -12 months'!$B:$B,$A$69,'Resident Retention -12 months'!$H:$H)+SUMIF('Resident Retention -12 months'!$B:$B,$A$69,'Resident Retention -12 months'!$I:$I))/(SUMIF('Resident Retention -12 months'!$B:$B,$A$69,'Resident Retention -12 months'!$C:$C)-SUMIF('Resident Retention -12 months'!$B:$B,$A$69,'Resident Retention -12 months'!$J:$J)),0) -> 0.60784314 | AD74: 0.68627451 | AE74: 0.66666667 | AF74: 0.66666667 | AG74: 0.66666667 | AH74: 0.64705882 | AI74: 0.64705882 | AJ74: 0.60784314 | AK74: =IFERROR((SUMIF('Resident Retention -12 months'!$B:$B,$A$69,'Resident Retention -12 months'!$F:$F)+SUMIF('Resident Retention -12 months'!$B:$B,$A$69,'Resident Retention -12 months'!$H:$H)+SUMIF('Resident Retention -12 months'!$B:$B,$A$69,'Resident Retention -12 months'!$I:$I))/(SUMIF('Resident Retention -12 months'!$B:$B,$A$69,'Resident Retention -12 months'!$C:$C)-SUMIF('Resident Retention -12 months'!$B:$B,$A$69,'Resident Retention -12 months'!$J:$J)),0) -> 0.60784314
A75: RENEWALS - SEPTEMBER
A76: 46266 | B76: Expirations | C76: #,##0 | AG76: 53 | AH76: 53 | AI76: 53 | AJ76: 53 | AK76: =SUMIF('Resident Retention -12 months'!$B:$J,Data_2!$A$76,'Resident Retention -12 months'!$C:$C)-SUMIF('Resident Retention -12 months'!$B:$J,Data_2!$A$76,'Resident Retention -12 months'!$J:$J) -> 53
B77: Early Move Outs | C77: #,##0 | AG77: 8 | AH77: 8 | AI77: 9 | AJ77: 9 | AK77: =SUMIF('Resident Retention -12 months'!$B:$J,Data_2!$A$76,'Resident Retention -12 months'!$D:$D) -> 9
B78: NTV | C78: #,##0 | AG78: 8 | AH78: 12 | AI78: 12 | AJ78: 14 | AK78: =SUMIF('Resident Retention -12 months'!$B:$J,Data_2!$A$76,'Resident Retention -12 months'!$E:$E) -> 14
B79: Renewal % | C79: 0 | AG79: 0.24528302 | AH79: 0.32075472 | AI79: 0.35849057 | AJ79: 0.41509434 | AK79: =IFERROR((SUMIF('Resident Retention -12 months'!$B:$B,$A$76,'Resident Retention -12 months'!$F:$F)+SUMIF('Resident Retention -12 months'!$B:$B,$A$76,'Resident Retention -12 months'!$H:$H))/(SUMIF('Resident Retention -12 months'!$B:$B,$A$76,'Resident Retention -12 months'!$C:$C)-SUMIF('Resident Retention -12 months'!$B:$B,$A$76,'Resident Retention -12 months'!$J:$J)),0) -> 0.45283019
B80: Skips (Evictions) | C80: #,##0 | AG80: 0 | AH80: 0 | AI80: 0 | AJ80: 0 | AK80: {=SUMPRODUCT(((Move_Out_Reasons!N2:N1000="Skipped Without Notice")+(Move_Out_Reasons!N2:N1000="Skipped During Eviction")+(Move_Out_Reasons!N2:N1000="Eviction")+(Move_Out_Reasons!N2:N1000="Failure To Pay"))*(Move_Out_Reasons!L2:L1000>=$A$76)*(Move_Out_Reasons!L2:L1000<=EOMONTH($A$76,0)))} -> 0
B81: Max Renewal % Possible | C81: 0 | AG81: 0.69811321 | AH81: 0.62264151 | AI81: 0.60377358 | AJ81: 0.56603774 | AK81: =IFERROR((SUMIF('Resident Retention -12 months'!$B:$B,$A$76,'Resident Retention -12 months'!$F:$F)+SUMIF('Resident Retention -12 months'!$B:$B,$A$76,'Resident Retention -12 months'!$H:$H)+SUMIF('Resident Retention -12 months'!$B:$B,$A$76,'Resident Retention -12 months'!$I:$I))/(SUMIF('Resident Retention -12 months'!$B:$B,$A$76,'Resident Retention -12 months'!$C:$C)-SUMIF('Resident Retention -12 months'!$B:$B,$A$76,'Resident Retention -12 months'!$J:$J)),0) -> 0.56603774
A82: RENEWALS - OCTOBER
A83: 46296 | B83: Expirations | C83: #,##0 | AI83: 39 | AJ83: 39 | AK83: =SUMIF('Resident Retention -12 months'!$B:$J,Data_2!$A$83,'Resident Retention -12 months'!$C:$C)-SUMIF('Resident Retention -12 months'!$B:$J,Data_2!$A$83,'Resident Retention -12 months'!$J:$J) -> 39
B84: Early Move Outs | C84: #,##0 | AI84: 6 | AJ84: 6 | AK84: =SUMIF('Resident Retention -12 months'!$B:$J,Data_2!$A$83,'Resident Retention -12 months'!$D:$D) -> 6
B85: NTV | C85: #,##0 | AI85: 0 | AJ85: 1 | AK85: =SUMIF('Resident Retention -12 months'!$B:$J,Data_2!$A$83,'Resident Retention -12 months'!$E:$E) -> 3
B86: Renewal % | C86: 0 | AI86: 0 | AJ86: 0.12820513 | AK86: =IFERROR((SUMIF('Resident Retention -12 months'!$B:$B,$A$83,'Resident Retention -12 months'!$F:$F)+SUMIF('Resident Retention -12 months'!$B:$B,$A$83,'Resident Retention -12 months'!$H:$H))/(SUMIF('Resident Retention -12 months'!$B:$B,$A$83,'Resident Retention -12 months'!$C:$C)-SUMIF('Resident Retention -12 months'!$B:$B,$A$83,'Resident Retention -12 months'!$J:$J)),0) -> 0.38461538
B87: Skips (Evictions) | C87: #,##0 | AI87: 0 | AJ87: 0 | AK87: {=SUMPRODUCT(((Move_Out_Reasons!N2:N1000="Skipped Without Notice")+(Move_Out_Reasons!N2:N1000="Skipped During Eviction")+(Move_Out_Reasons!N2:N1000="Eviction")+(Move_Out_Reasons!N2:N1000="Failure To Pay"))*(Move_Out_Reasons!L2:L1000>=$A$83)*(Move_Out_Reasons!L2:L1000<=EOMONTH($A$83,0)))} -> 0
B88: Max Renewal % Possible | C88: 0 | AI88: 0.84615385 | AJ88: 0.82051282 | AK88: =IFERROR((SUMIF('Resident Retention -12 months'!$B:$B,$A$83,'Resident Retention -12 months'!$F:$F)+SUMIF('Resident Retention -12 months'!$B:$B,$A$83,'Resident Retention -12 months'!$H:$H)+SUMIF('Resident Retention -12 months'!$B:$B,$A$83,'Resident Retention -12 months'!$I:$I))/(SUMIF('Resident Retention -12 months'!$B:$B,$A$83,'Resident Retention -12 months'!$C:$C)-SUMIF('Resident Retention -12 months'!$B:$B,$A$83,'Resident Retention -12 months'!$J:$J)),0) -> 0.76923077
A89: MTM LEASES
B90: Total MTM | C90: #,##0 | N90: 98 | O90: 93 | P90: 88 | Q90: 82 | R90: 79 | S90: 79 | T90: 79 | U90: 79 | V90: 65 | W90: 54 | X90: 47 | Y90: 45 | Z90: 45 | AA90: 49 | AB90: 47 | AC90: 36 | AD90: 35 | AE90: 32 | AF90: 30 | AG90: 29 | AH90: 27 | AI90: 26 | AJ90: 26 | AK90: =SUMPRODUCT((Res_Retention!$O$2:$O$14)) -> 25
A91: MOVE ACTIVITY
B92: Move Ins | C92: #,##0 | D92: 0 | E92: 0 | F92: 3 | G92: 3 | H92: 4 | I92: 2 | J92: 3 | K92: 2 | L92: 0 | M92: 1 | N92: 3 | O92: 7 | P92: 8 | Q92: 6 | R92: 5 | S92: 5 | T92: 3 | U92: 9 | V92: 5 | W92: 14 | X92: 8 | Y92: 6 | Z92: 9 | AA92: 15 | AB92: 4 | AC92: 8 | AD92: 6 | AE92: 8 | AF92: 7 | AG92: 10 | AH92: 7 | AI92: 10 | AJ92: 16 | AK92: =SUM('Boxscore MMR-Property Pulse'!$B:$B) -> 7
B93: Move Outs | C93: #,##0 | D93: 4 | E93: 1 | F93: 7 | G93: 0 | H93: 0 | I93: 14 | J93: 1 | K93: 2 | L93: 5 | M93: 4 | N93: 6 | O93: 2 | P93: 6 | Q93: 7 | R93: 2 | S93: 14 | T93: 6 | U93: 2 | V93: 4 | W93: 12 | X93: 8 | Y93: 4 | Z93: 1 | AA93: 17 | AB93: 5 | AC93: 7 | AD93: 5 | AE93: 10 | AF93: 11 | AG93: 6 | AH93: 7 | AI93: 4 | AJ93: 11 | AK93: =SUM('Boxscore MMR-Property Pulse'!$G:$G) -> 5
B94: Net Absorption | C94: #,##0 | D94: =D92-D93 -> -4 | E94: =E92-E93 -> -1 | F94: =F92-F93 -> -4 | G94: 3 | H94: 4 | I94: -12 | J94: 2 | K94: 0 | L94: -5 | M94: -3 | N94: -3 | O94: 5 | P94: 2 | Q94: -1 | R94: 3 | S94: -9 | T94: -3 | U94: 7 | V94: 1 | W94: 2 | X94: 0 | Y94: 2 | Z94: 8 | AA94: -2 | AB94: -1 | AC94: 1 | AD94: 1 | AE94: -2 | AF94: -4 | AG94: 4 | AH94: 0 | AI94: 6 | AJ94: 5 | AK94: =AK92-AK93 -> 2
B95: Controllable MO | C95: #,##0 | D95: 2 | E95: 1 | F95: 4 | G95: 0 | H95: 1 | I95: 7 | J95: 3 | K95: 2 | L95: 1 | M95: 2 | N95: 2 | O95: 1 | P95: 2 | Q95: 0 | R95: 2 | S95: 5 | T95: 1 | U95: 1 | V95: 2 | W95: 8 | X95: 7 | Y95: 4 | Z95: 1 | AA95: 17 | AB95: 4 | AC95: 5 | AD95: 3 | AE95: 9 | AF95: 10 | AG95: 6 | AH95: 4 | AI95: 3 | AJ95: 11 | AK95: =SUM('Boxscore MMR-Property Pulse'!$G:$G)-SUM('Boxscore MMR-Property Pulse'!$H:$H) -> 3
B96: Uncontrollable MO | C96: #,##0 | D96: 2 | E96: 0 | F96: 3 | G96: 0 | H96: -1 | I96: 7 | J96: -2 | K96: 0 | L96: 4 | M96: 2 | N96: 4 | O96: 1 | P96: 4 | Q96: 7 | R96: 0 | S96: 9 | T96: 5 | U96: 1 | V96: 2 | W96: 4 | X96: 1 | Y96: 0 | Z96: 0 | AA96: 0 | AB96: 1 | AC96: 2 | AD96: 2 | AE96: 1 | AF96: 1 | AG96: 0 | AH96: 3 | AI96: 1 | AJ96: 0 | AK96: =SUM('Boxscore MMR-Property Pulse'!$H:$H) -> 2
A97: COLLECTIONS
A98: all charges | B98: Gross Charges | C98: $#,##0 | D98: 815386.07 | E98: 815386.07 | F98: 816812.07 | G98: 933650.76 | H98: 938719.71 | I98: 921538.96 | J98: 794136 | K98: 877767.02 | L98: 866547.02 | M98: 863028.1 | N98: 755822 | O98: 849001.95 | P98: 862037.95 | Q98: 896996.31 | R98: 919957.46 | S98: 801098.4 | T98: 859616.05 | U98: 877250 | V98: 890341.69 | W98: 767074 | X98: 798082.64 | Y98: 845309.62 | Z98: 863137.27 | AA98: 735979.17 | AB98: 752447.62 | AC98: 823572.66 | AD98: 881238.6 | AE98: 888017.92 | AF98: 749313.93 | AG98: 785785.5 | AH98: 794499.11 | AI98: 853502.41 | AJ98: 733729.79 | AK98: =SUM('receipts by charge code-AVA'!$C:$C) -> 761341.09
B99: Credits | C99: $#,##0 | D99: -13618.19 | E99: -10377 | F99: -1750.26 | G99: -16513 | H99: -17183 | I99: -17023 | J99: -4625 | K99: -7749 | L99: -9579 | M99: -12426.42 | N99: -15171.74 | O99: -15446.74 | P99: -15303.42 | Q99: -18575.74 | R99: -19371.74 | S99: -23309.88 | T99: -25409.88 | U99: -25481 | V99: -27839.47 | W99: -44235 | X99: -47312.82 | Y99: -48738.85 | Z99: -49676.35 | AA99: -38358.87 | AB99: -42309.61 | AC99: -43381.28 | AD99: -45074.54 | AE99: -45374.54 | AF99: -78136.57 | AG99: -78286.57 | AH99: -78984.52 | AI99: -81323.52 | AJ99: -57994.31 | AK99: =SUMIF('receipts by charge code-AVA'!$G:$G,"<0") -> -60839.31
B100: NSFs | C100: $#,##0 | D100: 0 | E100: 0 | F100: 0 | G100: 5882.06 | H100: 5882.06 | I100: 6056.82 | J100: 0 | K100: 9637.42 | L100: 14287.21 | M100: 14287.21 | N100: 0 | O100: 5708.56 | P100: 8679.76 | Q100: 8960.81 | R100: 9210.81 | S100: 4126.88 | T100: 10205.67 | U100: 10206 | V100: 10205.67 | W100: 0 | X100: 8775.24 | Y100: 8775.24 | Z100: 8775.24 | AA100: 8775.24 | AB100: 5654.74 | AC100: 7635.74 | AD100: 7635.74 | AE100: 7635.74 | AF100: 2950.94 | AG100: 9576.93 | AH100: 9886.34 | AI100: 9886.34 | AJ100: 0 | AK100: =SUM('NSF -AVA'!$F:$F) -> 1281.68
B101: Net Charges | C101: $#,##0 | D101: =D98+D99 -> 801767.88 | E101: =E98+E99 -> 805009.07 | F101: =F98+F99 -> 815061.81 | G101: =G98+G99 -> 917137.76 | H101: =H98+H99 -> 921536.71 | I101: =I98+I99 -> 904515.96 | J101: =J98+J99 -> 789511 | K101: =K98+K99 -> 870018.02 | ... AD101: =AD98+AD99 -> 836164.06 | AE101: 842643.38 | AF101: 671177.36 | AG101: 707498.93 | AH101: 715514.59 | AI101: 772178.89 | AJ101: 675735.48 | AK101: =AK98+AK99 -> 700501.78
...

Sheet Delinquency_Detail_3
B1: AVA APARTMENTS | N1: MOVED OUT OVERRIDE | P1: CURRENT OVERRIDE
B2: Delinquency Detail | N2: (Add resident names here to force into Former section) | P2: (On rent roll -> force into Current section, exclude from Former)
B3: As of: | C3: =Dashboard_1!F3 -> 46244 | G3: Min Bal Filter: | H3: 200 | I3: ← Adjust current threshold | N3: Smiley, Brianca | P3: Simpson, William
B4: DELINQUENCY SUMMARY | N4: Perez, Jocelyn | P4: Brown, Rayquain
B5: Total Delinquency | C5: =SUMIF('resident aged receivable'!I:I,">0",'resident aged receivable'!I:I) -> 678540.74 | G5: 0-30 Days | H5: =SUMIF('resident aged receivable'!J:J,">0",'resident aged receivable'!J:J) -> 69897.57 | N5: Means, Alexxis | P5: Lagunas, Francisco
B6: Delinquent Accounts | C6: =COUNTIF('resident aged receivable'!I:I,">0") -> 181 | G6: 31-60 Days | H6: =SUMIF('resident aged receivable'!K:K,">0",'resident aged receivable'!K:K) -> 134876.6 | N6: Cetz, Manuel | P6: Barr, Ebony
B7: Evictions | C7: =COUNTIF('resident aged receivable'!E:E,"Past - Eviction")+COUNTIF('resident aged receivable'!E:E,"Current - Eviction") -> 36 | G7: Eviction Exposure | H7: =SUMIFS('resident aged receivable'!I:I,'resident aged receivable'!E:E,"Past - Eviction")+SUMIFS('resident aged receivable'!I:I,'resident aged receivable'!E:E,"Current - Eviction") -> 395614.88 | N7: Elhakim, Ahmed | P7: Johnson, Scott
B8: Skips | C8: =COUNTIF('resident aged receivable'!E:E,"Past - Skip") -> 20 | G8: Skip Exposure | H8: =SUMIFS('resident aged receivable'!I:I,'resident aged receivable'!E:E,"Past - Skip") -> 108529.99 | N8: Sanders, Dwayne | P8: Avila, Marcos
B9: Pending Eviction $ | C9: =SUMIFS('resident aged receivable'!I:I,'resident aged receivable'!E:E,"Current - Grace Period")+SUMIFS('resident aged receivable'!I:I,'resident aged receivable'!E:E,"Notice - Grace Period")+SUMIFS('resident aged receivable'!I:I,'resident aged receivable'!E:E,"Current - Eviction") -> 814.34 | G9: Current Delinq $ | H9: =SUMIFS('resident aged receivable'!I:I,'resident aged receivable'!E:E,"Current")+SUMIFS('resident aged receivable'!I:I,'resident aged receivable'!E:E,"Current - Month To Month") -> 53820.46 | N9: Meraz, Elvira | P9: Rocha, Luis
B10: LEASELOCK SUMMARY | N10: Allen, Quentin | P10: Nwabunor, Stanley (Stanley)
B11: Total Claimed | C11: =SUM(LeaseLock!L2:L500) -> 624444.33 | D11: Open Claims | E11: =COUNTIF(LeaseLock!F2:F500,"Open") -> 8 | G11: Total Recovery Rate | H11: =IFERROR(SUM(LeaseLock!M2:M500)/SUM(LeaseLock!L2:L500),0) -> 0.14971716 | J11: Claim Rec. % | K11: =IFERROR(SUM(LeaseLock!M2:M500)/SUM(LeaseLock!W2:W500),0) -> 0.62358997 | N11: Coronado, Iram
B12: Total Paid | C12: =SUM(LeaseLock!M2:M500) -> 93490.03 | D12: Unfiled Claims | E12: =SUM('resident aged receivable'!N2:N460) -> 78 | G12: Net Loss | H12: =SUM(LeaseLock!L2:L500)-SUM(LeaseLock!M2:M500) -> 530954.3 | N12: Alvarez, Nixon
B13: Claims Filed | C13: =COUNTA(LeaseLock!A2:A500) -> 206 | D13: Est. Recovery (unfiled) | E13: =E12*1500 -> 117000 | G13: Claims Denied | H13: =COUNTIF(LeaseLock!F2:F500,"Claim Denied")&" ("&TEXT(IFERROR(COUNTIF(LeaseLock!F2:F500,"Claim Denied")/COUNTA(LeaseLock!A2:A500),0),"0%")&")" -> 34 (17%) | N13: NJENDU, MARTIN
B14: Max Claimed $750 | D14: Est. Recovery (total) | E14: =SUMIFS(LeaseLock!L2:L500,LeaseLock!F2:F500,"Open")+E12*1500 -> 162276.1 | G14: Avg Recovery | H14: =IFERROR(SUM(LeaseLock!M2:M500)/COUNTA(LeaseLock!A2:A500),0) -> 453.8351 | N14: Fudge, Alicia
B15: EVICTIONS & FORMER RESIDENTS | N15: Cooks, Tatiana
B16: Unit | C16: Resident | D16: Move-In Date | E16: Move-Out Date | F16: IPS/CAF | G16: Status | H16: Total Bal. | I16: 0-30 | J16: 31-60 | K16: LeaseLock/RSI | L16: Collection/Leaselock/RSI Notes | N16: Branch, Maria
A17: {=IFERROR(_xlfn.LET(_xlpm.n,ROW()-16,_xlpm.adj,IF((((ISNUMBER(SEARCH("Eviction",'resident aged receivable'!$E$2:$E$460)))+(ISNUMBER(SEARCH("Past",'resident aged receivable'!$E$2:$E$460)))+(ISNUMBER(SEARCH("Skip",'resident aged receivable'!$E$2:$E$460)))+(ISNUMBER(SEARCH("Collections",'resident aged receivable'!$E$2:$E$460)))+(COUNTIF($N$3:$N$24,'resident aged receivable'!$D$2:$D$460)>0))>0)*(((((LEFT('resident aged receivable'!$E$2:$E$460,7)="Current")+(LEFT('resident aged receivable'!$E$2:$E$460,6)="Notice"))=0)+(COUNTIF($N$3:$N$24,'resident aged receivable'!$D$2:$D$460)>0))>0)*(COUNTIF($P$3:$P$24,'resident aged receivable'!$D$2:$D$460)=0)*('resident aged receivable'!$I$2:$I$460>0),'resident aged receivable'!$I$2:$I$460-ROW('resident aged receivable'!$I$2:$I$460)/1000000),_xlpm.tgt,LARGE(_xlpm.adj,_xlpm.n),MATCH(_xlpm.tgt,_xlpm.adj,0)+1),"")} -> 131 | B17: {=IF($A17="","",INDEX('resident aged receivable'!$B:$B,$A17))} -> W12-1-1202 | C17: {=IF($A17="","",INDEX('resident aged receivable'!$D:$D,$A17))} -> Harris, Mahogany | D17: {=IF($A17="","",INDEX('resident aged receivable'!$F:$F,$A17))} -> 45569 | E17: {=IF($A17="","",_xlfn.LET(_xlpm.leaseEnd,INDEX('resident aged receivable'!$H:$H,$A17),_xlpm.moLookup,IFERROR(_xlfn.LET(_xlpm.lastFirst,C17,_xlpm.lastName,IFERROR(TRIM(LEFT(_xlpm.lastFirst,FIND(",",_xlpm.lastFirst)-1)),_xlpm.lastFirst),_xlpm.firstName,IFERROR(TRIM(MID(_xlpm.lastFirst,FIND(",",_xlpm.lastFirst)+1,100)),""),_xlpm.matches,IF((ISNUMBER(SEARCH(_xlpm.lastName,Move_Outs_ResMan!$C$8:$C$500)))*(ISNUMBER(SEARCH(_xlpm.firstName,Move_Outs_ResMan!$C$8:$C$500))),Move_Outs_ResMan!$G$8:$G$500),_xlpm.maxDate,MAX(_xlpm.matches),IF(_xlpm.maxDate=0,"",_xlpm.maxDate)),""),IF(ISNUMBER(_xlpm.leaseEnd),_xlpm.leaseEnd,IF(_xlpm.moLookup="","",_xlpm.moLookup))))} -> 46169 | F17: =IF(D17="","",IF(D17<DATE(2025,12,15),"IPS","CAF")) -> IPS | G17: {=IF($A17="","",IF(COUNTIF($N$3:$N$24,C17)>0,"Former",_xlfn.LET(_xlpm.s,INDEX('resident aged receivable'!$E:$E,$A17),IF(ISNUMBER(SEARCH("Eviction",_xlpm.s)),"Eviction",IF(ISNUMBER(SEARCH("Skip",_xlpm.s)),"Skip",IF(ISNUMBER(SEARCH("Past",_xlpm.s))+ISNUMBER(SEARCH("Collections",_xlpm.s)),"Former",_xlpm.s))))))} -> Eviction | H17: {=IF($A17="","",INDEX('resident aged receivable'!$I:$I,$A17))} -> 42277.71 | I17: {=IF($A17="","",INDEX('resident aged receivable'!$J:$J,$A17))} -> 0 | J17: {=IF($A17="","",INDEX('resident aged receivable'!$K:$K,$A17))} -> 0 | K17: {=IF($C17="","",IFERROR(_xlfn.LET(_xlpm.unit,B17,_xlpm.resident,C17,_xlpm.lastName,IFERROR(LEFT(_xlpm.resident,FIND(",",_xlpm.resident)-1),_xlpm.resident),_xlpm.llMatch,(LeaseLock!$D$2:$D$500=_xlpm.unit)*ISNUMBER(SEARCH(_xlpm.lastName,LeaseLock!$C$2:$C$500)),_xlpm.hasLL,SUMPRODUCT(_xlpm.llMatch)>0,_xlpm.llStatus,IF(_xlpm.hasLL,_xlfn.LET(_xlpm.stat,LOOKUP(2,1/_xlpm.llMatch,LeaseLock!$F$2:$F$500),_xlpm.sub,LOOKUP(2,1/_xlpm.llMatch,LeaseLock!$G$2:$G$500),_xlpm.paid,LOOKUP(2,1/_xlpm.llMatch,LeaseLock!$M$2:$M$500),IF(_xlpm.stat="Claim Denied","Claim Denied ("&_xlpm.sub&")",IF(_xlpm.stat="Open","Open - "&_xlpm.sub,IF(_xlpm.paid>0,_xlpm.stat&" - $"&TEXT(_xlpm.paid,"#,##0.00")&" paid",_xlpm.stat&" - no payment")))),""),_xlpm.rsiMatches,ISNUMBER(SEARCH(_xlpm.lastName,Evictions_RSI!$B$3:$B$200))*(Evictions_RSI!$B$3:$B$200<>""),_xlpm.hasRSI,SUMPRODUCT(_xlpm.rsiMatches)>0,_xlpm.rsiStatus,IF(_xlpm.hasRSI,_xlfn.LET(_xlpm.dates,IF(_xlpm.rsiMatches,IFERROR(DATEVALUE(SUBSTITUTE(Evictions_RSI!$A$3:$A$200,_xlfn.UNICHAR(8204),"")),0),0),_xlpm.latestRow,MATCH(MAX(_xlpm.dates),_xlpm.dates,0),TRIM(SUBSTITUTE(INDEX(Evictions_RSI!$I$3:$I$200,_xlpm.latestRow),_xlfn.UNICHAR(8204),""))),""),IF(AND(_xlpm.llStatus="",_xlpm.rsiStatus=""),"",IF(_xlpm.llStatus="","RSI: "&_xlpm.rsiStatus,IF(_xlpm.rsiStatus="","LL: "&_xlpm.llStatus,"LL: "&_xlpm.llStatus&" | RSI: "&_xlpm.rsiStatus)))),""))} -> LL: Claim Denied () | RSI: COC - JOA Pending (Notes) | N17: Jackson, Tamia
A18: {=IFERROR(_xlfn.LET(_xlpm.n,ROW()-16,_xlpm.adj,IF((((ISNUMBER(SEARCH("Eviction",'resident aged receivable'!$E$2:$E$460)))+(ISNUMBER(SEARCH("Past",'resident aged receivable'!$E$2:$E$460)))+(ISNUMBER(SEARCH("Skip",'resident aged receivable'!$E$2:$E$460)))+(ISNUMBER(SEARCH("Collections",'resident aged receivable'!$E$2:$E$460)))+(COUNTIF($N$3:$N$24,'resident aged receivable'!$D$2:$D$460)>0))>0)*(((((LEFT('resident aged receivable'!$E$2:$E$460,7)="Current")+(LEFT('resident aged receivable'!$E$2:$E$460,6)="Notice"))=0)+(COUNTIF($N$3:$N$24,'resident aged receivable'!$D$2:$D$460)>0))>0)*(COUNTIF($P$3:$P$24,'resident aged receivable'!$D$2:$D$460)=0)*('resident aged receivable'!$I$2:$I$460>0),'resident aged receivable'!$I$2:$I$460-ROW('resident aged receivable'!$I$2:$I$460)/1000000),_xlpm.tgt,LARGE(_xlpm.adj,_xlpm.n),MATCH(_xlpm.tgt,_xlpm.adj,0)+1),"")} -> 161 | B18: {=IF($A18="","",INDEX('resident aged receivable'!$B:$B,$A18))} -> W19-2-2067 | C18: {=IF($A18="","",INDEX('resident aged receivable'!$D:$D,$A18))} -> Taylor, Talika | D18: {=IF($A18="","",INDEX('resident aged receivable'!$F:$F,$A18))} -> 45818 | E18: {=IF($A18="","",_xlfn.LET(_xlpm.leaseEnd,INDEX('resident aged receivable'!$H:$H,$A18),_xlpm.moLookup,IFERROR(_xlfn.LET(_xlpm.lastFirst,C18,_xlpm.lastName,IFERROR(TRIM(LEFT(_xlpm.lastFirst,FIND(",",_xlpm.lastFirst)-1)),_xlpm.lastFirst),_xlpm.firstName,IFERROR(TRIM(MID(_xlpm.lastFirst,FIND(",",_xlpm.lastFirst)+1,100)),""),_xlpm.matches,IF((ISNUMBER(SEARCH(_xlpm.lastName,Move_Outs_ResMan!$C$8:$C$500)))*(ISNUMBER(SEARCH(_xlpm.firstName,Move_Outs_ResMan!$C$8:$C$500))),Move_Outs_ResMan!$G$8:$G$500),_xlpm.maxDate,MAX(_xlpm.matches),IF(_xlpm.maxDate=0,"",_xlpm.maxDate)),""),IF(ISNUMBER(_xlpm.leaseEnd),_xlpm.leaseEnd,IF(_xlpm.moLookup="","",_xlpm.moLookup))))} -> 46182 | F18: =IF(D18="","",IF(D18<DATE(2025,12,15),"IPS","CAF")) -> IPS | G18: {=IF($A18="","",IF(COUNTIF($N$3:$N$24,C18)>0,"Former",_xlfn.LET(_xlpm.s,INDEX('resident aged receivable'!$E:$E,$A18),IF(ISNUMBER(SEARCH("Eviction",_xlpm.s)),"Eviction",IF(ISNUMBER(SEARCH("Skip",_xlpm.s)),"Skip",IF(ISNUMBER(SEARCH("Past",_xlpm.s))+ISNUMBER(SEARCH("Collections",_xlpm.s)),"Former",_xlpm.s))))))} -> Eviction | H18: {=IF($A18="","",INDEX('resident aged receivable'!$I:$I,$A18))} -> 22415.68 | I18: {=IF($A18="","",INDEX('resident aged receivable'!$J:$J,$A18))} -> 0 | J18: {=IF($A18="","",INDEX('resident aged receivable'!$K:$K,$A18))} -> 0 | K18: {=IF($C18="","",IFERROR(_xlfn.LET(_xlpm.unit,B18,_xlpm.resident,C18,_xlpm.lastName,IFERROR(LEFT(_xlpm.resident,FIND(",",_xlpm.resident)-1),_xlpm.resident),_xlpm.llMatch,(LeaseLock!$D$2:$D$500=_xlpm.unit)*ISNUMBER(SEARCH(_xlpm.lastName,LeaseLock!$C$2:$C$500)),_xlpm.hasLL,SUMPRODUCT(_xlpm.llMatch)>0,_xlpm.llStatus,IF(_xlpm.hasLL,_xlfn.LET(_xlpm.stat,LOOKUP(2,1/_xlpm.llMatch,LeaseLock!$F$2:$F$500),_xlpm.sub,LOOKUP(2,1/_xlpm.llMatch,LeaseLock!$G$2:$G$500),_xlpm.paid,LOOKUP(2,1/_xlpm.llMatch,LeaseLock!$M$2:$M$500),IF(_xlpm.stat="Claim Denied","Claim Denied ("&_xlpm.sub&")",IF(_xlpm.stat="Open","Open - "&_xlpm.sub,IF(_xlpm.paid>0,_xlpm.stat&" - $"&TEXT(_xlpm.paid,"#,##0.00")&" paid",_xlpm.stat&" - no payment")))),""),_xlpm.rsiMatches,ISNUMBER(SEARCH(_xlpm.lastName,Evictions_RSI!$B$3:$B$200))*(Evictions_RSI!$B$3:$B$200<>""),_xlpm.hasRSI,SUMPRODUCT(_xlpm.rsiMatches)>0,_xlpm.rsiStatus,IF(_xlpm.hasRSI,_xlfn.LET(_xlpm.dates,IF(_xlpm.rsiMatches,IFERROR(DATEVALUE(SUBSTITUTE(Evictions_RSI!$A$3:$A$200,_xlfn.UNICHAR(8204),"")),0),0),_xlpm.latestRow,MATCH(MAX(_xlpm.dates),_xlpm.dates,0),TRIM(SUBSTITUTE(INDEX(Evictions_RSI!$I$3:$I$200,_xlpm.latestRow),_xlfn.UNICHAR(8204),""))),""),IF(AND(_xlpm.llStatus="",_xlpm.rsiStatus=""),"",IF(_xlpm.llStatus="","RSI: "&_xlpm.rsiStatus,IF(_xlpm.rsiStatus="","LL: "&_xlpm.llStatus,"LL: "&_xlpm.llStatus&" | RSI: "&_xlpm.rsiStatus)))),""))} -> LL: Open - Pending Documentation | RSI: Granted (Notes) | L18: pending lease lock | N18: Howard, Ronnie
A19: {=IFERROR(_xlfn.LET(_xlpm.n,ROW()-16,_xlpm.adj,IF((((ISNUMBER(SEARCH("Eviction",'resident aged receivable'!$E$2:$E$460)))+(ISNUMBER(SEARCH("Past",'resident aged receivable'!$E$2:$E$460)))+(ISNUMBER(SEARCH("Skip",'resident aged receivable'!$E$2:$E$460)))+(ISNUMBER(SEARCH("Collections",'resident aged receivable'!$E$2:$E$460)))+(COUNTIF($N$3:$N$24,'resident aged receivable'!$D$2:$D$460)>0))>0)*(((((LEFT('resident aged receivable'!$E$2:$E$460,7)="Current")+(LEFT('resident aged receivable'!$E$2:$E$460,6)="Notice"))=0)+(COUNTIF($N$3:$N$24,'resident aged receivable'!$D$2:$D$460)>0))>0)*(COUNTIF($P$3:$P$24,'resident aged receivable'!$D$2:$D$460)=0)*('resident aged receivable'!$I$2:$I$460>0),'resident aged receivable'!$I$2:$I$460-ROW('resident aged receivable'!$I$2:$I$460)/1000000),_xlpm.tgt,LARGE(_xlpm.adj,_xlpm.n),MATCH(_xlpm.tgt,_xlpm.adj,0)+1),"")} -> 176 | B19: {=IF($A19="","",INDEX('resident aged receivable'!$B:$B,$A19))} -> W24-2-2039 | C19: {=IF($A19="","",INDEX('resident aged receivable'!$D:$D,$A19))} -> Fridia, Rodrinesha | D19: {=IF($A19="","",INDEX('resident aged receivable'!$F:$F,$A19))} -> 45590 | E19: {=IF($A19="","",_xlfn.LET(_xlpm.leaseEnd,INDEX('resident aged receivable'!$H:$H,$A19),_xlpm.moLookup,IFERROR(_xlfn.LET(_xlpm.lastFirst,C19,_xlpm.lastName,IFERROR(TRIM(LEFT(_xlpm.lastFirst,FIND(",",_xlpm.lastFirst)-1)),_xlpm.lastFirst),_xlpm.firstName,IFERROR(TRIM(MID(_xlpm.lastFirst,FIND(",",_xlpm.lastFirst)+1,100)),""),_xlpm.matches,IF((ISNUMBER(SEARCH(_xlpm.lastName,Move_Outs_ResMan!$C$8:$C$500)))*(ISNUMBER(SEARCH(_xlpm.firstName,Move_Outs_ResMan!$C$8:$C$500))),Move_Outs_ResMan!$G$8:$G$500),_xlpm.maxDate,MAX(_xlpm.matches),IF(_xlpm.maxDate=0,"",_xlpm.maxDate)),""),IF(ISNUMBER(_xlpm.leaseEnd),_xlpm.leaseEnd,IF(_xlpm.moLookup="","",_xlpm.moLookup))))} -> 46170 | F19: =IF(D19="","",IF(D19<DATE(2025,12,15),"IPS","CAF")) -> IPS | G19: {=IF($A19="","",IF(COUNTIF($N$3:$N$24,C19)>0,"Former",_xlfn.LET(_xlpm.s,INDEX('resident aged receivable'!$E:$E,$A19),IF(ISNUMBER(SEARCH("Eviction",_xlpm.s)),"Eviction",IF(ISNUMBER(SEARCH("Skip",_xlpm.s)),"Skip",IF(ISNUMBER(SEARCH("Past",_xlpm.s))+ISNUMBER(SEARCH("Collections",_xlpm.s)),"Former",_xlpm.s))))))} -> Eviction | H19: {=IF($A19="","",INDEX('resident aged receivable'!$I:$I,$A19))} -> 21493.39 | I19: {=IF($A19="","",INDEX('resident aged receivable'!$J:$J,$A19))} -> 0 | J19: {=IF($A19="","",INDEX('resident aged receivable'!$K:$K,$A19))} -> 0 | K19: {=IF($C19="","",IFERROR(_xlfn.LET(_xlpm.unit,B19,_xlpm.resident,C19,_xlpm.lastName,IFERROR(LEFT(_xlpm.resident,FIND(",",_xlpm.resident)-1),_xlpm.resident),_xlpm.llMatch,(LeaseLock!$D$2:$D$500=_xlpm.unit)*ISNUMBER(SEARCH(_xlpm.lastName,LeaseLock!$C$2:$C$500)),_xlpm.hasLL,SUMPRODUCT(_xlpm.llMatch)>0,_xlpm.llStatus,IF(_xlpm.hasLL,_xlfn.LET(_xlpm.stat,LOOKUP(2,1/_xlpm.llMatch,LeaseLock!$F$2:$F$500),_xlpm.sub,LOOKUP(2,1/_xlpm.llMatch,LeaseLock!$G$2:$G$500),_xlpm.paid,LOOKUP(2,1/_xlpm.llMatch,LeaseLock!$M$2:$M$500),IF(_xlpm.stat="Claim Denied","Claim Denied ("&_xlpm.sub&")",IF(_xlpm.stat="Open","Open - "&_xlpm.sub,IF(_xlpm.paid>0,_xlpm.stat&" - $"&TEXT(_xlpm.paid,"#,##0.00")&" paid",_xlpm.stat&" - no payment")))),""),_xlpm.rsiMatches,ISNUMBER(SEARCH(_xlpm.lastName,Evictions_RSI!$B$3:$B$200))*(Evictions_RSI!$B$3:$B$200<>""),_xlpm.hasRSI,SUMPRODUCT(_xlpm.rsiMatches)>0,_xlpm.rsiStatus,IF(_xlpm.hasRSI,_xlfn.LET(_xlpm.dates,IF(_xlpm.rsiMatches,IFERROR(DATEVALUE(SUBSTITUTE(Evictions_RSI!$A$3:$A$200,_xlfn.UNICHAR(8204),"")),0),0),_xlpm.latestRow,MATCH(MAX(_xlpm.dates),_xlpm.dates,0),TRIM(SUBSTITUTE(INDEX(Evictions_RSI!$I$3:$I$200,_xlpm.latestRow),_xlfn.UNICHAR(8204),""))),""),IF(AND(_xlpm.llStatus="",_xlpm.rsiStatus=""),"",IF(_xlpm.llStatus="","RSI: "&_xlpm.rsiStatus,IF(_xlpm.rsiStatus="","LL: "&_xlpm.llStatus,"LL: "&_xlpm.llStatus&" | RSI: "&_xlpm.rsiStatus)))),""))} -> LL: Open - | RSI: Rent Suit Concluded (Notes) | N19: Eliuth, Gerson
A20: {=IFERROR(_xlfn.LET(_xlpm.n,ROW()-16,_xlpm.adj,IF((((ISNUMBER(SEARCH("Eviction",'resident aged receivable'!$E$2:$E$460)))+(ISNUMBER(SEARCH("Past",'resident aged receivable'!$E$2:$E$460)))+(ISNUMBER(SEARCH("Skip",'resident aged receivable'!$E$2:$E$460)))+(ISNUMBER(SEARCH("Collections",'resident aged receivable'!$E$2:$E$460)))+(COUNTIF($N$3:$N$24,'resident aged receivable'!$D$2:$D$460)>0))>0)*(((((LEFT('resident aged receivable'!$E$2:$E$460,7)="Current")+(LEFT('resident aged receivable'!$E$2:$E$460,6)="Notice"))=0)+(COUNTIF($N$3:$N$24,'resident aged receivable'!$D$2:$D$460)>0))>0)*(COUNTIF($P$3:$P$24,'resident aged receivable'!$D$2:$D$460)=0)*('resident aged receivable'!$I$2:$I$460>0),'resident aged receivable'!$I$2:$I$460-ROW('resident aged receivable'!$I$2:$I$460)/1000000),_xlpm.tgt,LARGE(_xlpm.adj,_xlpm.n),MATCH(_xlpm.tgt,_xlpm.adj,0)+1),"")} -> 58 | B20: {=IF($A20="","",INDEX('resident aged receivable'!$B:$B,$A20))} -> S26-414 | C20: {=IF($A20="","",INDEX('resident aged receivable'!$D:$D,$A20))} -> Cooks, Tatiana | D20: {=IF($A20="","",INDEX('resident aged receivable'!$F:$F,$A20))} -> 45890 | E20: {=IF($A20="","",_xlfn.LET(_xlpm.leaseEnd,INDEX('resident aged receivable'!$H:$H,$A20),_xlpm.moLookup,IFERROR(_xlfn.LET(_xlpm.lastFirst,C20,_xlpm.lastName,IFERROR(TRIM(LEFT(_xlpm.lastFirst,FIND(",",_xlpm.lastFirst)-1)),_xlpm.lastFirst),_xlpm.firstName,IFERROR(TRIM(MID(_xlpm.lastFirst,FIND(",",_xlpm.lastFirst)+1,100)),""),_xlpm.matches,IF((ISNUMBER(SEARCH(_xlpm.lastName,Move_Outs_ResMan!$C$8:$C$500)))*(ISNUMBER(SEARCH(_xlpm.firstName,Move_Outs_ResMan!$C$8:$C$500))),Move_Outs_ResMan!$G$8:$G$500),_xlpm.maxDate,MAX(_xlpm.matches),IF(_xlpm.maxDate=0,"",_xlpm.maxDate)),""),IF(ISNUMBER(_xlpm.leaseEnd),_xlpm.leaseEnd,IF(_xlpm.moLookup="","",_xlpm.moLookup))))} -> 46254 | F20: =IF(D20="","",IF(D20<DATE(2025,12,15),"IPS","CAF")) -> IPS | G20: {=IF($A20="","",IF(COUNTIF($N$3:$N$24,C20)>0,"Former",_xlfn.LET(_xlpm.s,INDEX('resident aged receivable'!$E:$E,$A20),IF(ISNUMBER(SEARCH("Eviction",_xlpm.s)),"Eviction",IF(ISNUMBER(SEARCH("Skip",_xlpm.s)),"Skip",IF(ISNUMBER(SEARCH("Past",_xlpm.s))+ISNUMBER(SEARCH("Collections",_xlpm.s)),"Former",_xlpm.s))))))} -> Former | H20: {=IF($A20="","",INDEX('resident aged receivable'!$I:$I,$A20))} -> 19396.38 | I20: {=IF($A20="","",INDEX('resident aged receivable'!$J:$J,$A20))} -> 0 | J20: {=IF($A20="","",INDEX('resident aged receivable'!$K:$K,$A20))} -> 0 | K20: {=IF($C20="","",IFERROR(_xlfn.LET(_xlpm.unit,B20,_xlpm.resident,C20,_xlpm.lastName,IFERROR(LEFT(_xlpm.resident,FIND(",",_xlpm.resident)-1),_xlpm.resident),_xlpm.llMatch,(LeaseLock!$D$2:$D$500=_xlpm.unit)*ISNUMBER(SEARCH(_xlpm.lastName,LeaseLock!$C$2:$C$500)),_xlpm.hasLL,SUMPRODUCT(_xlpm.llMatch)>0,_xlpm.llStatus,IF(_xlpm.hasLL,_xlfn.LET(_xlpm.stat,LOOKUP(2,1/_xlpm.llMatch,LeaseLock!$F$2:$F$500),_xlpm.sub,LOOKUP(2,1/_xlpm.llMatch,LeaseLock!$G$2:$G$500),_xlpm.paid,LOOKUP(2,1/_xlpm.llMatch,LeaseLock!$M$2:$M$500),IF(_xlpm.stat="Claim Denied","Claim Denied ("&_xlpm.sub&")",IF(_xlpm.stat="Open","Open - "&_xlpm.sub,IF(_xlpm.paid>0,_xlpm.stat&" - $"&TEXT(_xlpm.paid,"#,##0.00")&" paid",_xlpm.stat&" - no payment")))),""),_xlpm.rsiMatches,ISNUMBER(SEARCH(_xlpm.lastName,Evictions_RSI!$B$3:$B$200))*(Evictions_RSI!$B$3:$B$200<>""),_xlpm.hasRSI,SUMPRODUCT(_xlpm.rsiMatches)>0,_xlpm.rsiStatus,IF(_xlpm.hasRSI,_xlfn.LET(_xlpm.dates,IF(_xlpm.rsiMatches,IFERROR(DATEVALUE(SUBSTITUTE(Evictions_RSI!$A$3:$A$200,_xlfn.UNICHAR(8204),"")),0),0),_xlpm.latestRow,MATCH(MAX(_xlpm.dates),_xlpm.dates,0),TRIM(SUBSTITUTE(INDEX(Evictions_RSI!$I$3:$I$200,_xlpm.latestRow),_xlfn.UNICHAR(8204),""))),""),IF(AND(_xlpm.llStatus="",_xlpm.rsiStatus=""),"",IF(_xlpm.llStatus="","RSI: "&_xlpm.rsiStatus,IF(_xlpm.rsiStatus="","LL: "&_xlpm.llStatus,"LL: "&_xlpm.llStatus&" | RSI: "&_xlpm.rsiStatus)))),""))} -> LL: Claim Denied () | RSI: Dismissed (Notes) | N20: Walker, Myocsheonia
A21: {=IFERROR(_xlfn.LET(_xlpm.n,ROW()-16,_xlpm.adj,IF((((ISNUMBER(SEARCH("Eviction",'resident aged receivable'!$E$2:$E$460)))+(ISNUMBER(SEARCH("Past",'resident aged receivable'!$E$2:$E$460)))+(ISNUMBER(SEARCH("Skip",'resident aged receivable'!$E$2:$E$460)))+(ISNUMBER(SEARCH("Collections",'resident aged receivable'!$E$2:$E$460)))+(COUNTIF($N$3:$N$24,'resident aged receivable'!$D$2:$D$460)>0))>0)*(((((LEFT('resident aged receivable'!$E$2:$E$460,7)="Current")+(LEFT('resident aged receivable'!$E$2:$E$460,6)="Notice"))=0)+(COUNTIF($N$3:$N$24,'resident aged receivable'!$D$2:$D$460)>0))>0)*(COUNTIF($P$3:$P$24,'resident aged receivable'!$D$2:$D$460)=0)*('resident aged receivable'!$I$2:$I$460>0),'resident aged receivable'!$I$2:$I$460-ROW('resident aged receivable'!$I$2:$I$460)/1000000),_xlpm.tgt,LARGE(_xlpm.adj,_xlpm.n),MATCH(_xlpm.tgt,_xlpm.adj,0)+1),"")} -> 15 | B21: {=IF($A21="","",INDEX('resident aged receivable'!$B:$B,$A21))} -> N09-1037 | C21: {=IF($A21="","",INDEX('resident aged receivable'!$D:$D,$A21))} -> Flores, Estanislao | D21: {=IF($A21="","",INDEX('resident aged receivable'!$F:$F,$A21))} -> 45646 | E21: {=IF($A21="","",_xlfn.LET(_xlpm.leaseEnd,INDEX('resident aged receivable'!$H:$H,$A21),_xlpm.moLookup,IFERROR(_xlfn.LET(_xlpm.lastFirst,C21,_xlpm.lastName,IFERROR(TRIM(LEFT(_xlpm.lastFirst,FIND(",",_xlpm.lastFirst)-1)),_xlpm.lastFirst),_xlpm.firstName,IFERROR(TRIM(MID(_xlpm.lastFirst,FIND(",",_xlpm.lastFirst)+1,100)),""),_xlpm.matches,IF((ISNUMBER(SEARCH(_xlpm.lastName,Move_Outs_ResMan!$C$8:$C$500)))*(ISNUMBER(SEARCH(_xlpm.firstName,Move_Outs_ResMan!$C$8:$C$500))),Move_Outs_ResMan!$G$8:$G$500),_xlpm.maxDate,MAX(_xlpm.matches),IF(_xlpm.maxDate=0,"",_xlpm.maxDate)),""),IF(ISNUMBER(_xlpm.leaseEnd),_xlpm.leaseEnd,IF(_xlpm.moLookup="","",_xlpm.moLookup))))} -> 46204 | F21: =IF(D21="","",IF(D21<DATE(2025,12,15),"IPS","CAF")) -> IPS | G21: {=IF($A21="","",IF(COUNTIF($N$3:$N$24,C21)>0,"Former",_xlfn.LET(_xlpm.s,INDEX('resident aged receivable'!$E:$E,$A21),IF(ISNUMBER(SEARCH("Eviction",_xlpm.s)),"Eviction",IF(ISNUMBER(SEARCH("Skip",_xlpm.s)),"Skip",IF(ISNUMBER(SEARCH("Past",_xlpm.s))+ISNUMBER(SEARCH("Collections",_xlpm.s)),"Former",_xlpm.s))))))} -> Eviction | H21: {=IF($A21="","",INDEX('resident aged receivable'!$I:$I,$A21))} -> 17611.69 | I21: {=IF($A21="","",INDEX('resident aged receivable'!$J:$J,$A21))} -> 0 | J21: {=IF($A21="","",INDEX('resident aged receivable'!$K:$K,$A21))} -> 2888.78 | K21: {=IF($C21="","",IFERROR(_xlfn.LET(_xlpm.unit,B21,_xlpm.resident,C21,_xlpm.lastName,IFERROR(LEFT(_xlpm.resident,FIND(",",_xlpm.resident)-1),_xlpm.resident),_xlpm.llMatch,(LeaseLock!$D$2:$D$500=_xlpm.unit)*ISNUMBER(SEARCH(_xlpm.lastName,LeaseLock!$C$2:$C$500)),_xlpm.hasLL,SUMPRODUCT(_xlpm.llMatch)>0,_xlpm.llStatus,IF(_xlpm.hasLL,_xlfn.LET(_xlpm.stat,LOOKUP(2,1/_xlpm.llMatch,LeaseLock!$F$2:$F$500),_xlpm.sub,LOOKUP(2,1/_xlpm.llMatch,LeaseLock!$G$2:$G$500),_xlpm.paid,LOOKUP(2,1/_xlpm.llMatch,LeaseLock!$M$2:$M$500),IF(_xlpm.stat="Claim Denied","Claim Denied ("&_xlpm.sub&")",IF(_xlpm.stat="Open","Open - "&_xlpm.sub,IF(_xlpm.paid>0,_xlpm.stat&" - $"&TEXT(_xlpm.paid,"#,##0.00")&" paid",_xlpm.stat&" - no payment")))),""),_xlpm.rsiMatches,ISNUMBER(SEARCH(_xlpm.lastName,Evictions_RSI!$B$3:$B$200))*(Evictions_RSI!$B$3:$B$200<>""),_xlpm.hasRSI,SUMPRODUCT(_xlpm.rsiMatches)>0,_xlpm.rsiStatus,IF(_xlpm.hasRSI,_xlfn.LET(_xlpm.dates,IF(_xlpm.rsiMatches,IFERROR(DATEVALUE(SUBSTITUTE(Evictions_RSI!$A$3:$A$200,_xlfn.UNICHAR(8204),"")),0),0),_xlpm.latestRow,MATCH(MAX(_xlpm.dates),_xlpm.dates,0),TRIM(SUBSTITUTE(INDEX(Evictions_RSI!$I$3:$I$200,_xlpm.latestRow),_xlfn.UNICHAR(8204),""))),""),IF(AND(_xlpm.llStatus="",_xlpm.rsiStatus=""),"",IF(_xlpm.llStatus="","RSI: "&_xlpm.rsiStatus,IF(_xlpm.rsiStatus="","LL: "&_xlpm.llStatus,"LL: "&_xlpm.llStatus&" | RSI: "&_xlpm.rsiStatus)))),""))} -> RSI: COC - JOA Pending (Notes) | N21: Rodriguez, Joseph
A22: {=IFERROR(_xlfn.LET(_xlpm.n,ROW()-16,_xlpm.adj,IF((((ISNUMBER(SEARCH("Eviction",'resident aged receivable'!$E$2:$E$460)))+(ISNUMBER(SEARCH("Past",'resident aged receivable'!$E$2:$E$460)))+(ISNUMBER(SEARCH("Skip",'resident aged receivable'!$E$2:$E$460)))+(ISNUMBER(SEARCH("Collections",'resident aged receivable'!$E$2:$E$460)))+(COUNTIF($N$3:$N$24,'resident aged receivable'!$D$2:$D$460)>0))>0)*(((((LEFT('resident aged receivable'!$E$2:$E$460,7)="Current")+(LEFT('resident aged receivable'!$E$2:$E$460,6)="Notice"))=0)+(COUNTIF($N$3:$N$24,'resident aged receivable'!$D$2:$D$460)>0))>0)*(COUNTIF($P$3:$P$24,'resident aged receivable'!$D$2:$D$460)=0)*('resident aged receivable'!$I$2:$I$460>0),'resident aged receivable'!$I$2:$I$460-ROW('resident aged receivable'!$I$2:$I$460)/1000000),_xlpm.tgt,LARGE(_xlpm.adj,_xlpm.n),MATCH(_xlpm.tgt,_xlpm.adj,0)+1),"")} -> 152 | B22: {=IF($A22="","",INDEX('resident aged receivable'!$B:$B,$A22))} -> W17-2-1074 | C22: {=IF($A22="","",INDEX('resident aged receivable'!$D:$D,$A22))} -> Harris, Dynisha | D22: {=IF($A22="","",INDEX('resident aged receivable'!$F:$F,$A22))} -> 45696 | E22: {=IF($A22="","",_xlfn.LET(_xlpm.leaseEnd,INDEX('resident aged receivable'!$H:$H,$A22),_xlpm.moLookup,IFERROR(_xlfn.LET(_xlpm.lastFirst,C22,_xlpm.lastName,IFERROR(TRIM(LEFT(_xlpm.lastFirst,FIND(",",_xlpm.lastFirst)-1)),_xlpm.lastFirst),_xlpm.firstName,IFERROR(TRIM(MID(_xlpm.lastFirst,FIND(",",_xlpm.lastFirst)+1,100)),""),_xlpm.matches,IF((ISNUMBER(SEARCH(_xlpm.lastName,Move_Outs_ResMan!$C$8:$C$500)))*(ISNUMBER(SEARCH(_xlpm.firstName,Move_Outs_ResMan!$C$8:$C$500))),Move_Outs_ResMan!$G$8:$G$500),_xlpm.maxDate,MAX(_xlpm.matches),IF(_xlpm.maxDate=0,"",_xlpm.maxDate)),""),IF(ISNUMBER(_xlpm.leaseEnd),_xlpm.leaseEnd,IF(_xlpm.moLookup="","",_xlpm.moLookup))))} -> 46060 | F22: =IF(D22="","",IF(D22<DATE(2025,12,15),"IPS","CAF")) -> IPS | G22: {=IF($A22="","",IF(COUNTIF($N$3:$N$24,C22)>0,"Former",_xlfn.LET(_xlpm.s,INDEX('resident aged receivable'!$E:$E,$A22),IF(ISNUMBER(SEARCH("Eviction",_xlpm.s)),"Eviction",IF(ISNUMBER(SEARCH("Skip",_xlpm.s)),"Skip",IF(ISNUMBER(SEARCH("Past",_xlpm.s))+ISNUMBER(SEARCH("Collections",_xlpm.s)),"Former",_xlpm.s))))))} -> Eviction | H22: {=IF($A22="","",INDEX('resident aged receivable'!$I:$I,$A22))} -> 16185.1 | I22: {=IF($A22="","",INDEX('resident aged receivable'!$J:$J,$A22))} -> 0 | J22: {=IF($A22="","",INDEX('resident aged receivable'!$K:$K,$A22))} -> 0 | K22: {=IF($C22="","",IFERROR(_xlfn.LET(_xlpm.unit,B22,_xlpm.resident,C22,_xlpm.lastName,IFERROR(LEFT(_xlpm.resident,FIND(",",_xlpm.resident)-1),_xlpm.resident),_xlpm.llMatch,(LeaseLock!$D$2:$D$500=_xlpm.unit)*ISNUMBER(SEARCH(_xlpm.lastName,LeaseLock!$C$2:$C$500)),_xlpm.hasLL,SUMPRODUCT(_xlpm.llMatch)>0,_xlpm.llStatus,IF(_xlpm.hasLL,_xlfn.LET(_xlpm.stat,LOOKUP(2,1/_xlpm.llMatch,LeaseLock!$F$2:$F$500),_xlpm.sub,LOOKUP(2,1/_xlpm.llMatch,LeaseLock!$G$2:$G$500),_xlpm.paid,LOOKUP(2,1/_xlpm.llMatch,LeaseLock!$M$2:$M$500),IF(_xlpm.stat="Claim Denied","Claim Denied ("&_xlpm.sub&")",IF(_xlpm.stat="Open","Open - "&_xlpm.sub,IF(_xlpm.paid>0,_xlpm.stat&" - $"&TEXT(_xlpm.paid,"#,##0.00")&" paid",_xlpm.stat&" - no payment")))),""),_xlpm.rsiMatches,ISNUMBER(SEARCH(_xlpm.lastName,Evictions_RSI!$B$3:$B$200))*(Evictions_RSI!$B$3:$B$200<>""),_xlpm.hasRSI,SUMPRODUCT(_xlpm.rsiMatches)>0,_xlpm.rsiStatus,IF(_xlpm.hasRSI,_xlfn.LET(_xlpm.dates,IF(_xlpm.rsiMatches,IFERROR(DATEVALUE(SUBSTITUTE(Evictions_RSI!$A$3:$A$200,_xlfn.UNICHAR(8204),"")),0),0),_xlpm.latestRow,MATCH(MAX(_xlpm.dates),_xlpm.dates,0),TRIM(SUBSTITUTE(INDEX(Evictions_RSI!$I$3:$I$200,_xlpm.latestRow),_xlfn.UNICHAR(8204),""))),""),IF(AND(_xlpm.llStatus="",_xlpm.rsiStatus=""),"",IF(_xlpm.llStatus="","RSI: "&_xlpm.rsiStatus,IF(_xlpm.rsiStatus="","LL: "&_xlpm.llStatus,"LL: "&_xlpm.llStatus&" | RSI: "&_xlpm.rsiStatus)))),""))} -> LL: Claim Denied () | RSI: COC - JOA Pending (Notes) | N22: Yoryina, Emelyn
